Workbook

Sheet Cobra Web
A1: DOMAIN | B1: TABLE_NAME | C1: COLUMN_NAME | D1: COLUMN_ORDER | E1: DATA_TYPE | F1: SQL_DATA_TYPE | G1: DATA_LENGTH | H1: SCALE | I1: NOT_NULL | J1: DEFAULT | K1: PRIMARY_KEY | L1: NATURAL_KEY | M1: FKEY_TABLE | N1: FKEY_COLUMN | O1: FKEY_CARDINALITY | P1: DESCRIPTION | Q1: JAVA_PROPERTY_NAME | R1: JAVA_DATA_TYPE | S1: COLUMN_FLAGS | T1: TABLE_DESCRIPTION | U1: TABLE_FLAGS | V1: COMMENTS | W1: Table.Column | X1: Found in Mapping? | Y1: Old Table.Column | Z1: Old Data Type | AA1: Old Data Length | AB1: Migrate from Cobra DeskTop Table
A2: Codes | B2: CODE | C2: ROW_UID | D2: 1 | E2: GUID | F2: =VLOOKUP($E2,'Data Type Lookup'!$A$1:$C$21,2,FALSE) -> RAW(16) | I2: Y | K2: Y | P2: Unique Code Identifier. | Q2: uid | R2: =VLOOKUP(E2,'Data Type Lookup'!$A$1:$C$21,3,FALSE) -> java.util.UUID | S2: 3 | W2: =_xlfn.CONCAT(B2,".",C2) -> CODE.ROW_UID | X2: =VLOOKUP(W2,ColumnMapping[New Table.Column],1,) -> CODE.ROW_UID | Y2: =_xlfn.XLOOKUP(Table6[[#This Row],[Table.Column]],ColumnMapping[Add Column Name],ColumnMapping[Old Table.Column],"",0,1) | Z2: =_xlfn.XLOOKUP(Table6[[#This Row],[Old Table.Column]],Cobra8.6[Table.Column],Cobra8.6[TYPE],"",0,1) | AA2: =_xlfn.XLOOKUP(Table6[[#This Row],[Old Table.Column]],Cobra8.6[Table.Column],Cobra8.6[LENGTH],"",0,1)
A3: Codes | B3: CODE | C3: SEQUENCE | D3: 2 | E3: LONGINT | F3: =VLOOKUP($E3,'Data Type Lookup'!$A$1:$C$21,2,FALSE) -> NUMBER(19,0) | I3: Y | J3: 0 | P3: Concurrency Control Identifier. | Q3: sequence | R3: =VLOOKUP(E3,'Data Type Lookup'!$A$1:$C$21,3,FALSE) -> Long | S3: 3 | W3: =_xlfn.CONCAT(B3,".",C3) -> CODE.SEQUENCE | X3: =VLOOKUP(W3,ColumnMapping[New Table.Column],1,) -> CODE.SEQUENCE | Y3: =_xlfn.XLOOKUP(Table6[[#This Row],[Table.Column]],ColumnMapping[Add Column Name],ColumnMapping[Old Table.Column],"",0,1) | Z3: =_xlfn.XLOOKUP(Table6[[#This Row],[Old Table.Column]],Cobra8.6[Table.Column],Cobra8.6[TYPE],"",0,1) | AA3: =_xlfn.XLOOKUP(Table6[[#This Row],[Old Table.Column]],Cobra8.6[Table.Column],Cobra8.6[LENGTH],"",0,1)
A4: Codes | B4: CODE | C4: CODE_FILE_UID | D4: 3 | E4: GUID | F4: =VLOOKUP($E4,'Data Type Lookup'!$A$1:$C$21,2,FALSE) -> RAW(16) | I4: Y | L4: Y | M4: CODE_FILE | N4: ROW_UID | O4: 1:N | P4: Unique Identifier of the Code File record. | Q4: codeFile | R4: =VLOOKUP(E4,'Data Type Lookup'!$A$1:$C$21,3,FALSE) -> java.util.UUID | S4: 1 | W4: =_xlfn.CONCAT(B4,".",C4) -> CODE.CODE_FILE_UID | X4: =VLOOKUP(W4,ColumnMapping[New Table.Column],1,) -> CODE.CODE_FILE_UID | Y4: =_xlfn.XLOOKUP(Table6[[#This Row],[Table.Column]],ColumnMapping[Add Column Name],ColumnMapping[Old Table.Column],"",0,1) | Z4: =_xlfn.XLOOKUP(Table6[[#This Row],[Old Table.Column]],Cobra8.6[Table.Column],Cobra8.6[TYPE],"",0,1) | AA4: =_xlfn.XLOOKUP(Table6[[#This Row],[Old Table.Column]],Cobra8.6[Table.Column],Cobra8.6[LENGTH],"",0,1)
A5: Codes | B5: CODE | C5: PARENT_CODE_UID | D5: 4 | E5: GUID | F5: =VLOOKUP($E5,'Data Type Lookup'!$A$1:$C$21,2,FALSE) -> RAW(16) | L5: Y | M5: CODE | N5: ROW_UID | O5: 1:N | P5: Unique Identifier of the Parent Code record. | Q5: parentCode | R5: =VLOOKUP(E5,'Data Type Lookup'!$A$1:$C$21,3,FALSE) -> java.util.UUID | S5: 1 | W5: =_xlfn.CONCAT(B5,".",C5) -> CODE.PARENT_CODE_UID | X5: =VLOOKUP(W5,ColumnMapping[New Table.Column],1,) -> CODE.PARENT_CODE_UID | Y5: =_xlfn.XLOOKUP(Table6[[#This Row],[Table.Column]],ColumnMapping[Add Column Name],ColumnMapping[Old Table.Column],"",0,1) | Z5: =_xlfn.XLOOKUP(Table6[[#This Row],[Old Table.Column]],Cobra8.6[Table.Column],Cobra8.6[TYPE],"",0,1) | AA5: =_xlfn.XLOOKUP(Table6[[#This Row],[Old Table.Column]],Cobra8.6[Table.Column],Cobra8.6[LENGTH],"",0,1)
A6: Codes | B6: CODE | C6: NAME | D6: 5 | E6: NTEXT | F6: =VLOOKUP($E6,'Data Type Lookup'!$A$1:$C$21,2,FALSE) -> NVARCHAR2 | G6: 100 | I6: Y | L6: Y | P6: Code Name. | Q6: name | R6: =VLOOKUP(E6,'Data Type Lookup'!$A$1:$C$21,3,FALSE) -> String | W6: =_xlfn.CONCAT(B6,".",C6) -> CODE.NAME | X6: =VLOOKUP(W6,ColumnMapping[New Table.Column],1,) -> CODE.NAME | Y6: =_xlfn.XLOOKUP(Table6[[#This Row],[Table.Column]],ColumnMapping[Add Column Name],ColumnMapping[Old Table.Column],"",0,1) | Z6: =_xlfn.XLOOKUP(Table6[[#This Row],[Old Table.Column]],Cobra8.6[Table.Column],Cobra8.6[TYPE],"",0,1) | AA6: =_xlfn.XLOOKUP(Table6[[#This Row],[Old Table.Column]],Cobra8.6[Table.Column],Cobra8.6[LENGTH],"",0,1)
A7: Codes | B7: CODE | C7: CODE_LEVEL | D7: 6 | E7: SHORTINT | F7: =VLOOKUP($E7,'Data Type Lookup'!$A$1:$C$21,2,FALSE) -> NUMBER(5,0) | J7: 1 | P7: Code hierarchy level. | Q7: codeLevel | R7: =VLOOKUP(E7,'Data Type Lookup'!$A$1:$C$21,3,FALSE) -> Short | W7: =_xlfn.CONCAT(B7,".",C7) -> CODE.CODE_LEVEL | X7: =VLOOKUP(W7,ColumnMapping[New Table.Column],1,) -> CODE.CODE_LEVEL | Y7: =_xlfn.XLOOKUP(Table6[[#This Row],[Table.Column]],ColumnMapping[Add Column Name],ColumnMapping[Old Table.Column],"",0,1) | Z7: =_xlfn.XLOOKUP(Table6[[#This Row],[Old Table.Column]],Cobra8.6[Table.Column],Cobra8.6[TYPE],"",0,1) | AA7: =_xlfn.XLOOKUP(Table6[[#This Row],[Old Table.Column]],Cobra8.6[Table.Column],Cobra8.6[LENGTH],"",0,1)
A8: Codes | B8: CODE | C8: CHILD_COUNT | D8: 7 | E8: SHORTINT | F8: =VLOOKUP($E8,'Data Type Lookup'!$A$1:$C$21,2,FALSE) -> NUMBER(5,0) | J8: 0 | P8: Parent Code child count. | Q8: childCount | R8: =VLOOKUP(E8,'Data Type Lookup'!$A$1:$C$21,3,FALSE) -> Short | W8: =_xlfn.CONCAT(B8,".",C8) -> CODE.CHILD_COUNT | X8: =VLOOKUP(W8,ColumnMapping[New Table.Column],1,) -> CODE.CHILD_COUNT | Y8: =_xlfn.XLOOKUP(Table6[[#This Row],[Table.Column]],ColumnMapping[Add Column Name],ColumnMapping[Old Table.Column],"",0,1) | Z8: =_xlfn.XLOOKUP(Table6[[#This Row],[Old Table.Column]],Cobra8.6[Table.Column],Cobra8.6[TYPE],"",0,1) | AA8: =_xlfn.XLOOKUP(Table6[[#This Row],[Old Table.Column]],Cobra8.6[Table.Column],Cobra8.6[LENGTH],"",0,1)
A9: Codes | B9: CODE | C9: CHILD_POS | D9: 8 | E9: SHORTINT | F9: =VLOOKUP($E9,'Data Type Lookup'!$A$1:$C$21,2,FALSE) -> NUMBER(5,0) | J9: 0 | P9: Child Code position. | Q9: childPos | R9: =VLOOKUP(E9,'Data Type Lookup'!$A$1:$C$21,3,FALSE) -> Short | W9: =_xlfn.CONCAT(B9,".",C9) -> CODE.CHILD_POS | X9: =VLOOKUP(W9,ColumnMapping[New Table.Column],1,) -> CODE.CHILD_POS | Y9: =_xlfn.XLOOKUP(Table6[[#This Row],[Table.Column]],ColumnMapping[Add Column Name],ColumnMapping[Old Table.Column],"",0,1) | Z9: =_xlfn.XLOOKUP(Table6[[#This Row],[Old Table.Column]],Cobra8.6[Table.Column],Cobra8.6[TYPE],"",0,1) | AA9: =_xlfn.XLOOKUP(Table6[[#This Row],[Old Table.Column]],Cobra8.6[Table.Column],Cobra8.6[LENGTH],"",0,1)
A10: Codes | B10: CODE | C10: CREATED_BY_USER_UID | D10: 9 | E10: GUID | F10: =VLOOKUP($E10,'Data Type Lookup'!$A$1:$C$21,2,FALSE) -> RAW(16) | I10: Y | P10: The User that created the Code. | Q10: createdBy | R10: =VLOOKUP(E10,'Data Type Lookup'!$A$1:$C$21,3,FALSE) -> java.util.UUID | S10: 2 | W10: =_xlfn.CONCAT(B10,".",C10) -> CODE.CREATED_BY_USER_UID | X10: =VLOOKUP(W10,ColumnMapping[New Table.Column],1,) -> CODE.CREATED_BY_USER_UID | Y10: =_xlfn.XLOOKUP(Table6[[#This Row],[Table.Column]],ColumnMapping[Add Column Name],ColumnMapping[Old Table.Column],"",0,1) | Z10: =_xlfn.XLOOKUP(Table6[[#This Row],[Old Table.Column]],Cobra8.6[Table.Column],Cobra8.6[TYPE],"",0,1) | AA10: =_xlfn.XLOOKUP(Table6[[#This Row],[Old Table.Column]],Cobra8.6[Table.Column],Cobra8.6[LENGTH],"",0,1)
A11: Codes | B11: CODE | C11: CREATED_DATE | D11: 10 | E11: TIMESTAMP | F11: =VLOOKUP($E11,'Data Type Lookup'!$A$1:$C$21,2,FALSE) -> TIMESTAMP | I11: Y | P11: Date the Code was created. | Q11: createdDate | R11: =VLOOKUP(E11,'Data Type Lookup'!$A$1:$C$21,3,FALSE) -> java.time.Instant | S11: 2 | W11: =_xlfn.CONCAT(B11,".",C11) -> CODE.CREATED_DATE | X11: =VLOOKUP(W11,ColumnMapping[New Table.Column],1,) -> CODE.CREATED_DATE | Y11: =_xlfn.XLOOKUP(Table6[[#This Row],[Table.Column]],ColumnMapping[Add Column Name],ColumnMapping[Old Table.Column],"",0,1) | Z11: =_xlfn.XLOOKUP(Table6[[#This Row],[Old Table.Column]],Cobra8.6[Table.Column],Cobra8.6[TYPE],"",0,1) | AA11: =_xlfn.XLOOKUP(Table6[[#This Row],[Old Table.Column]],Cobra8.6[Table.Column],Cobra8.6[LENGTH],"",0,1)
A12: Codes | B12: CODE | C12: LAST_MODIFIED_BY_USER_UID | D12: 11 | E12: GUID | F12: =VLOOKUP($E12,'Data Type Lookup'!$A$1:$C$21,2,FALSE) -> RAW(16) | I12: Y | P12: The User that last changed the Code. | Q12: lastModifiedBy | R12: =VLOOKUP(E12,'Data Type Lookup'!$A$1:$C$21,3,FALSE) -> java.util.UUID | S12: 2 | W12: =_xlfn.CONCAT(B12,".",C12) -> CODE.LAST_MODIFIED_BY_USER_UID | X12: =VLOOKUP(W12,ColumnMapping[New Table.Column],1,) -> CODE.LAST_MODIFIED_BY_USER_UID | Y12: =_xlfn.XLOOKUP(Table6[[#This Row],[Table.Column]],ColumnMapping[Add Column Name],ColumnMapping[Old Table.Column],"",0,1) | Z12: =_xlfn.XLOOKUP(Table6[[#This Row],[Old Table.Column]],Cobra8.6[Table.Column],Cobra8.6[TYPE],"",0,1) | AA12: =_xlfn.XLOOKUP(Table6[[#This Row],[Old Table.Column]],Cobra8.6[Table.Column],Cobra8.6[LENGTH],"",0,1)
A13: Codes | B13: CODE | C13: LAST_MODIFIED_DATE | D13: 12 | E13: TIMESTAMP | F13: =VLOOKUP($E13,'Data Type Lookup'!$A$1:$C$21,2,FALSE) -> TIMESTAMP | I13: Y | P13: Date the last change was made to the Code. | Q13: lastModifiedDate | R13: =VLOOKUP(E13,'Data Type Lookup'!$A$1:$C$21,3,FALSE) -> java.time.Instant | S13: 2 | W13: =_xlfn.CONCAT(B13,".",C13) -> CODE.LAST_MODIFIED_DATE | X13: =VLOOKUP(W13,ColumnMapping[New Table.Column],1,) -> CODE.LAST_MODIFIED_DATE | Y13: =_xlfn.XLOOKUP(Table6[[#This Row],[Table.Column]],ColumnMapping[Add Column Name],ColumnMapping[Old Table.Column],"",0,1) | Z13: =_xlfn.XLOOKUP(Table6[[#This Row],[Old Table.Column]],Cobra8.6[Table.Column],Cobra8.6[TYPE],"",0,1) | AA13: =_xlfn.XLOOKUP(Table6[[#This Row],[Old Table.Column]],Cobra8.6[Table.Column],Cobra8.6[LENGTH],"",0,1)
A14: Codes | B14: CODE | C14: DESCRIPTION | D14: 13 | E14: NTEXT | F14: =VLOOKUP($E14,'Data Type Lookup'!$A$1:$C$21,2,FALSE) -> NVARCHAR2 | G14: 256 | P14: Code Description. | Q14: description | R14: =VLOOKUP(E14,'Data Type Lookup'!$A$1:$C$21,3,FALSE) -> String | W14: =_xlfn.CONCAT(B14,".",C14) -> CODE.DESCRIPTION | X14: =VLOOKUP(W14,ColumnMapping[New Table.Column],1,) -> CODE.DESCRIPTION | Y14: =_xlfn.XLOOKUP(Table6[[#This Row],[Table.Column]],ColumnMapping[Add Column Name],ColumnMapping[Old Table.Column],"",0,1) | Z14: =_xlfn.XLOOKUP(Table6[[#This Row],[Old Table.Column]],Cobra8.6[Table.Column],Cobra8.6[TYPE],"",0,1) | AA14: =_xlfn.XLOOKUP(Table6[[#This Row],[Old Table.Column]],Cobra8.6[Table.Column],Cobra8.6[LENGTH],"",0,1)
A15: Codes | B15: CODE | C15: D1 | D15: 14 | E15: NTEXT | F15: =VLOOKUP($E15,'Data Type Lookup'!$A$1:$C$21,2,FALSE) -> NVARCHAR2 | G15: 59 | W15: =_xlfn.CONCAT(B15,".",C15) -> CODE.D1 | X15: =VLOOKUP(W15,ColumnMapping[New Table.Column],1,) -> #N/A | Y15: =_xlfn.XLOOKUP(Table6[[#This Row],[Table.Column]],ColumnMapping[Add Column Name],ColumnMapping[Old Table.Column],"",0,1) | Z15: =_xlfn.XLOOKUP(Table6[[#This Row],[Old Table.Column]],Cobra8.6[Table.Column],Cobra8.6[TYPE],"",0,1) | AA15: =_xlfn.XLOOKUP(Table6[[#This Row],[Old Table.Column]],Cobra8.6[Table.Column],Cobra8.6[LENGTH],"",0,1)
A16: Codes | B16: CODE | C16: D2 | D16: 15 | E16: NTEXT | F16: =VLOOKUP($E16,'Data Type Lookup'!$A$1:$C$21,2,FALSE) -> NVARCHAR2 | G16: 59 | W16: =_xlfn.CONCAT(B16,".",C16) -> CODE.D2 | X16: =VLOOKUP(W16,ColumnMapping[New Table.Column],1,) -> #N/A | Y16: =_xlfn.XLOOKUP(Table6[[#This Row],[Table.Column]],ColumnMapping[Add Column Name],ColumnMapping[Old Table.Column],"",0,1) | Z16: =_xlfn.XLOOKUP(Table6[[#This Row],[Old Table.Column]],Cobra8.6[Table.Column],Cobra8.6[TYPE],"",0,1) | AA16: =_xlfn.XLOOKUP(Table6[[#This Row],[Old Table.Column]],Cobra8.6[Table.Column],Cobra8.6[LENGTH],"",0,1)
A17: Codes | B17: CODE | C17: D3 | D17: 16 | E17: NTEXT | F17: =VLOOKUP($E17,'Data Type Lookup'!$A$1:$C$21,2,FALSE) -> NVARCHAR2 | G17: 59 | W17: =_xlfn.CONCAT(B17,".",C17) -> CODE.D3 | X17: =VLOOKUP(W17,ColumnMapping[New Table.Column],1,) -> #N/A | Y17: =_xlfn.XLOOKUP(Table6[[#This Row],[Table.Column]],ColumnMapping[Add Column Name],ColumnMapping[Old Table.Column],"",0,1) | Z17: =_xlfn.XLOOKUP(Table6[[#This Row],[Old Table.Column]],Cobra8.6[Table.Column],Cobra8.6[TYPE],"",0,1) | AA17: =_xlfn.XLOOKUP(Table6[[#This Row],[Old Table.Column]],Cobra8.6[Table.Column],Cobra8.6[LENGTH],"",0,1)
A18: Codes | B18: CODE | C18: D4 | D18: 17 | E18: NTEXT | F18: =VLOOKUP($E18,'Data Type Lookup'!$A$1:$C$21,2,FALSE) -> NVARCHAR2 | G18: 59 | W18: =_xlfn.CONCAT(B18,".",C18) -> CODE.D4 | X18: =VLOOKUP(W18,ColumnMapping[New Table.Column],1,) -> #N/A | Y18: =_xlfn.XLOOKUP(Table6[[#This Row],[Table.Column]],ColumnMapping[Add Column Name],ColumnMapping[Old Table.Column],"",0,1) | Z18: =_xlfn.XLOOKUP(Table6[[#This Row],[Old Table.Column]],Cobra8.6[Table.Column],Cobra8.6[TYPE],"",0,1) | AA18: =_xlfn.XLOOKUP(Table6[[#This Row],[Old Table.Column]],Cobra8.6[Table.Column],Cobra8.6[LENGTH],"",0,1)
A19: Codes | B19: CODE | C19: D5 | D19: 18 | E19: NTEXT | F19: =VLOOKUP($E19,'Data Type Lookup'!$A$1:$C$21,2,FALSE) -> NVARCHAR2 | G19: 59 | W19: =_xlfn.CONCAT(B19,".",C19) -> CODE.D5 | X19: =VLOOKUP(W19,ColumnMapping[New Table.Column],1,) -> #N/A | Y19: =_xlfn.XLOOKUP(Table6[[#This Row],[Table.Column]],ColumnMapping[Add Column Name],ColumnMapping[Old Table.Column],"",0,1) | Z19: =_xlfn.XLOOKUP(Table6[[#This Row],[Old Table.Column]],Cobra8.6[Table.Column],Cobra8.6[TYPE],"",0,1) | AA19: =_xlfn.XLOOKUP(Table6[[#This Row],[Old Table.Column]],Cobra8.6[Table.Column],Cobra8.6[LENGTH],"",0,1)
A20: Codes | B20: CODE | C20: D6 | D20: 19 | E20: NTEXT | F20: =VLOOKUP($E20,'Data Type Lookup'!$A$1:$C$21,2,FALSE) -> NVARCHAR2 | G20: 59 | W20: =_xlfn.CONCAT(B20,".",C20) -> CODE.D6 | X20: =VLOOKUP(W20,ColumnMapping[New Table.Column],1,) -> #N/A | Y20: =_xlfn.XLOOKUP(Table6[[#This Row],[Table.Column]],ColumnMapping[Add Column Name],ColumnMapping[Old Table.Column],"",0,1) | Z20: =_xlfn.XLOOKUP(Table6[[#This Row],[Old Table.Column]],Cobra8.6[Table.Column],Cobra8.6[TYPE],"",0,1) | AA20: =_xlfn.XLOOKUP(Table6[[#This Row],[Old Table.Column]],Cobra8.6[Table.Column],Cobra8.6[LENGTH],"",0,1)
A21: Codes | B21: CODE | C21: D7 | D21: 20 | E21: NTEXT | F21: =VLOOKUP($E21,'Data Type Lookup'!$A$1:$C$21,2,FALSE) -> NVARCHAR2 | G21: 59 | W21: =_xlfn.CONCAT(B21,".",C21) -> CODE.D7 | X21: =VLOOKUP(W21,ColumnMapping[New Table.Column],1,) -> #N/A | Y21: =_xlfn.XLOOKUP(Table6[[#This Row],[Table.Column]],ColumnMapping[Add Column Name],ColumnMapping[Old Table.Column],"",0,1) | Z21: =_xlfn.XLOOKUP(Table6[[#This Row],[Old Table.Column]],Cobra8.6[Table.Column],Cobra8.6[TYPE],"",0,1) | AA21: =_xlfn.XLOOKUP(Table6[[#This Row],[Old Table.Column]],Cobra8.6[Table.Column],Cobra8.6[LENGTH],"",0,1)
A22: Codes | B22: CODE | C22: D8 | D22: 21 | E22: NTEXT | F22: =VLOOKUP($E22,'Data Type Lookup'!$A$1:$C$21,2,FALSE) -> NVARCHAR2 | G22: 59 | W22: =_xlfn.CONCAT(B22,".",C22) -> CODE.D8 | X22: =VLOOKUP(W22,ColumnMapping[New Table.Column],1,) -> #N/A | Y22: =_xlfn.XLOOKUP(Table6[[#This Row],[Table.Column]],ColumnMapping[Add Column Name],ColumnMapping[Old Table.Column],"",0,1) | Z22: =_xlfn.XLOOKUP(Table6[[#This Row],[Old Table.Column]],Cobra8.6[Table.Column],Cobra8.6[TYPE],"",0,1) | AA22: =_xlfn.XLOOKUP(Table6[[#This Row],[Old Table.Column]],Cobra8.6[Table.Column],Cobra8.6[LENGTH],"",0,1)
A23: Codes | B23: CODE | C23: D9 | D23: 22 | E23: NTEXT | F23: =VLOOKUP($E23,'Data Type Lookup'!$A$1:$C$21,2,FALSE) -> NVARCHAR2 | G23: 59 | W23: =_xlfn.CONCAT(B23,".",C23) -> CODE.D9 | X23: =VLOOKUP(W23,ColumnMapping[New Table.Column],1,) -> #N/A | Y23: =_xlfn.XLOOKUP(Table6[[#This Row],[Table.Column]],ColumnMapping[Add Column Name],ColumnMapping[Old Table.Column],"",0,1) | Z23: =_xlfn.XLOOKUP(Table6[[#This Row],[Old Table.Column]],Cobra8.6[Table.Column],Cobra8.6[TYPE],"",0,1) | AA23: =_xlfn.XLOOKUP(Table6[[#This Row],[Old Table.Column]],Cobra8.6[Table.Column],Cobra8.6[LENGTH],"",0,1)
A24: Codes | B24: CODE | C24: TAG | D24: 23 | E24: TEXT | F24: =VLOOKUP($E24,'Data Type Lookup'!$A$1:$C$21,2,FALSE) -> VARCHAR2 | G24: 60 | W24: =_xlfn.CONCAT(B24,".",C24) -> CODE.TAG | X24: =VLOOKUP(W24,ColumnMapping[New Table.Column],1,) -> CODE.TAG | Y24: =_xlfn.XLOOKUP(Table6[[#This Row],[Table.Column]],ColumnMapping[Add Column Name],ColumnMapping[Old Table.Column],"",0,1) -> BDNDETL.TAG | Z24: =_xlfn.XLOOKUP(Table6[[#This Row],[Old Table.Column]],Cobra8.6[Table.Column],Cobra8.6[TYPE],"",0,1) -> TEXT | AA24: =_xlfn.XLOOKUP(Table6[[#This Row],[Old Table.Column]],Cobra8.6[Table.Column],Cobra8.6[LENGTH],"",0,1) -> 60
A25: Codes | B25: CODE | C25: BREAKFILE | E25: NTEXT | F25: =VLOOKUP($E25,'Data Type Lookup'!$A$1:$C$21,2,FALSE) -> NVARCHAR2 | G25: 22 | W25: =_xlfn.CONCAT(B25,".",C25) -> CODE.BREAKFILE | X25: =VLOOKUP(W25,ColumnMapping[New Table.Column],1,) -> #N/A | Y25: =_xlfn.XLOOKUP(Table6[[#This Row],[Table.Column]],ColumnMapping[Add Column Name],ColumnMapping[Old Table.Column],"",0,1) -> BDNDETL.BREAKFILE | Z25: =_xlfn.XLOOKUP(Table6[[#This Row],[Old Table.Column]],Cobra8.6[Table.Column],Cobra8.6[TYPE],"",0,1) -> TEXT | AA25: =_xlfn.XLOOKUP(Table6[[#This Row],[Old Table.Column]],Cobra8.6[Table.Column],Cobra8.6[LENGTH],"",0,1) -> 22
A26: Codes | B26: CODE_FILE | C26: ROW_UID | D26: 1 | E26: GUID | F26: =VLOOKUP($E26,'Data Type Lookup'!$A$1:$C$21,2,FALSE) -> RAW(16) | I26: Y | K26: Y | P26: Unique Code File Identifier. | Q26: uid | R26: =VLOOKUP(E26,'Data Type Lookup'!$A$1:$C$21,3,FALSE) -> java.util.UUID | S26: 3 | U26: 8 | W26: =_xlfn.CONCAT(B26,".",C26) -> CODE_FILE.ROW_UID | X26: =VLOOKUP(W26,ColumnMapping[New Table.Column],1,) -> CODE_FILE.ROW_UID | Y26: =_xlfn.XLOOKUP(Table6[[#This Row],[Table.Column]],ColumnMapping[Add Column Name],ColumnMapping[Old Table.Column],"",0,1) | Z26: =_xlfn.XLOOKUP(Table6[[#This Row],[Old Table.Column]],Cobra8.6[Table.Column],Cobra8.6[TYPE],"",0,1) | AA26: =_xlfn.XLOOKUP(Table6[[#This Row],[Old Table.Column]],Cobra8.6[Table.Column],Cobra8.6[LENGTH],"",0,1)
A27: Codes | B27: CODE_FILE | C27: SEQUENCE | D27: 2 | E27: LONGINT | F27: =VLOOKUP($E27,'Data Type Lookup'!$A$1:$C$21,2,FALSE) -> NUMBER(19,0) | I27: Y | J27: 0 | P27: Concurrency Control Identifier. | Q27: sequence | R27: =VLOOKUP(E27,'Data Type Lookup'!$A$1:$C$21,3,FALSE) -> Long | S27: 3 | W27: =_xlfn.CONCAT(B27,".",C27) -> CODE_FILE.SEQUENCE | X27: =VLOOKUP(W27,ColumnMapping[New Table.Column],1,) -> CODE_FILE.SEQUENCE | Y27: =_xlfn.XLOOKUP(Table6[[#This Row],[Table.Column]],ColumnMapping[Add Column Name],ColumnMapping[Old Table.Column],"",0,1) | Z27: =_xlfn.XLOOKUP(Table6[[#This Row],[Old Table.Column]],Cobra8.6[Table.Column],Cobra8.6[TYPE],"",0,1) | AA27: =_xlfn.XLOOKUP(Table6[[#This Row],[Old Table.Column]],Cobra8.6[Table.Column],Cobra8.6[LENGTH],"",0,1)
A28: Codes | B28: CODE_FILE | C28: NAME | D28: 3 | E28: NTEXT | F28: =VLOOKUP($E28,'Data Type Lookup'!$A$1:$C$21,2,FALSE) -> NVARCHAR2 | G28: 100 | L28: Y | P28: Code File Name. | Q28: name | R28: =VLOOKUP(E28,'Data Type Lookup'!$A$1:$C$21,3,FALSE) -> String | W28: =_xlfn.CONCAT(B28,".",C28) -> CODE_FILE.NAME | X28: =VLOOKUP(W28,ColumnMapping[New Table.Column],1,) -> CODE_FILE.NAME | Y28: =_xlfn.XLOOKUP(Table6[[#This Row],[Table.Column]],ColumnMapping[Add Column Name],ColumnMapping[Old Table.Column],"",0,1) | Z28: =_xlfn.XLOOKUP(Table6[[#This Row],[Old Table.Column]],Cobra8.6[Table.Column],Cobra8.6[TYPE],"",0,1) | AA28: =_xlfn.XLOOKUP(Table6[[#This Row],[Old Table.Column]],Cobra8.6[Table.Column],Cobra8.6[LENGTH],"",0,1)
A29: Codes | B29: CODE_FILE | C29: CODE_TYPE | D29: 4 | E29: TEXT | F29: =VLOOKUP($E29,'Data Type Lookup'!$A$1:$C$21,2,FALSE) -> VARCHAR2 | G29: 1 | I29: Y | P29: Code File Code Type. Supported values are P or N. | Q29: codeType | R29: =VLOOKUP(E29,'Data Type Lookup'!$A$1:$C$21,3,FALSE) -> String | W29: =_xlfn.CONCAT(B29,".",C29) -> CODE_FILE.CODE_TYPE | X29: =VLOOKUP(W29,ColumnMapping[New Table.Column],1,) -> CODE_FILE.CODE_TYPE | Y29: =_xlfn.XLOOKUP(Table6[[#This Row],[Table.Column]],ColumnMapping[Add Column Name],ColumnMapping[Old Table.Column],"",0,1) | Z29: =_xlfn.XLOOKUP(Table6[[#This Row],[Old Table.Column]],Cobra8.6[Table.Column],Cobra8.6[TYPE],"",0,1) | AA29: =_xlfn.XLOOKUP(Table6[[#This Row],[Old Table.Column]],Cobra8.6[Table.Column],Cobra8.6[LENGTH],"",0,1)
A30: Codes | B30: CODE_FILE | C30: TH_FLAGS | D30: 6 | E30: TEXT | F30: =VLOOKUP($E30,'Data Type Lookup'!$A$1:$C$21,2,FALSE) -> VARCHAR2 | G30: 10 | I30: Y | J30: ''NNNNNNNNNN'' | P30: Flags to enable Code Threshold Variance options. | Q30: thresholdFlags | R30: =VLOOKUP(E30,'Data Type Lookup'!$A$1:$C$21,3,FALSE) -> String | W30: =_xlfn.CONCAT(B30,".",C30) -> CODE_FILE.TH_FLAGS | X30: =VLOOKUP(W30,ColumnMapping[New Table.Column],1,) -> CODE_FILE.TH_FLAGS | Y30: =_xlfn.XLOOKUP(Table6[[#This Row],[Table.Column]],ColumnMapping[Add Column Name],ColumnMapping[Old Table.Column],"",0,1) -> BREAKDWN.TH_FLAGS | Z30: =_xlfn.XLOOKUP(Table6[[#This Row],[Old Table.Column]],Cobra8.6[Table.Column],Cobra8.6[TYPE],"",0,1) -> TEXT | AA30: =_xlfn.XLOOKUP(Table6[[#This Row],[Old Table.Column]],Cobra8.6[Table.Column],Cobra8.6[LENGTH],"",0,1) -> 10 | AB30: Y
A31: Codes | B31: CODE_FILE | C31: DESCRIPTION | D31: 7 | E31: NTEXT | F31: =VLOOKUP($E31,'Data Type Lookup'!$A$1:$C$21,2,FALSE) -> NVARCHAR2 | G31: 256 | P31: Code File Description. | Q31: description | R31: =VLOOKUP(E31,'Data Type Lookup'!$A$1:$C$21,3,FALSE) -> String | W31: =_xlfn.CONCAT(B31,".",C31) -> CODE_FILE.DESCRIPTION | X31: =VLOOKUP(W31,ColumnMapping[New Table.Column],1,) -> CODE_FILE.DESCRIPTION | Y31: =_xlfn.XLOOKUP(Table6[[#This Row],[Table.Column]],ColumnMapping[Add Column Name],ColumnMapping[Old Table.Column],"",0,1) | Z31: =_xlfn.XLOOKUP(Table6[[#This Row],[Old Table.Column]],Cobra8.6[Table.Column],Cobra8.6[TYPE],"",0,1) | AA31: =_xlfn.XLOOKUP(Table6[[#This Row],[Old Table.Column]],Cobra8.6[Table.Column],Cobra8.6[LENGTH],"",0,1)
A32: Codes | B32: CODE_FILE | C32: FIELD_NAME | D32: 8 | E32: NTEXT | F32: =VLOOKUP($E32,'Data Type Lookup'!$A$1:$C$21,2,FALSE) -> NVARCHAR2 | G32: 30 | I32: Y | P32: Default User Field Name when this Code File is assigned to a User Define Field. | Q32: fieldName | R32: =VLOOKUP(E32,'Data Type Lookup'!$A$1:$C$21,3,FALSE) -> String | W32: =_xlfn.CONCAT(B32,".",C32) -> CODE_FILE.FIELD_NAME | X32: =VLOOKUP(W32,ColumnMapping[New Table.Column],1,) -> CODE_FILE.FIELD_NAME | Y32: =_xlfn.XLOOKUP(Table6[[#This Row],[Table.Column]],ColumnMapping[Add Column Name],ColumnMapping[Old Table.Column],"",0,1) | Z32: =_xlfn.XLOOKUP(Table6[[#This Row],[Old Table.Column]],Cobra8.6[Table.Column],Cobra8.6[TYPE],"",0,1) | AA32: =_xlfn.XLOOKUP(Table6[[#This Row],[Old Table.Column]],Cobra8.6[Table.Column],Cobra8.6[LENGTH],"",0,1)
A33: Codes | B33: CODE_FILE | C33: FIELD_DESCRIPTION | D33: 9 | E33: NTEXT | F33: =VLOOKUP($E33,'Data Type Lookup'!$A$1:$C$21,2,FALSE) -> NVARCHAR2 | G33: 256 | P33: Default Field Description when this Code File is assigned to a User Define Field. | Q33: fieldDescription | R33: =VLOOKUP(E33,'Data Type Lookup'!$A$1:$C$21,3,FALSE) -> String | W33: =_xlfn.CONCAT(B33,".",C33) -> CODE_FILE.FIELD_DESCRIPTION | X33: =VLOOKUP(W33,ColumnMapping[New Table.Column],1,) -> CODE_FILE.FIELD_DESCRIPTION | Y33: =_xlfn.XLOOKUP(Table6[[#This Row],[Table.Column]],ColumnMapping[Add Column Name],ColumnMapping[Old Table.Column],"",0,1) | Z33: =_xlfn.XLOOKUP(Table6[[#This Row],[Old Table.Column]],Cobra8.6[Table.Column],Cobra8.6[TYPE],"",0,1) | AA33: =_xlfn.XLOOKUP(Table6[[#This Row],[Old Table.Column]],Cobra8.6[Table.Column],Cobra8.6[LENGTH],"",0,1)
A34: Codes | B34: CODE_FILE | C34: OWNER_USER_UID | D34: 10 | E34: GUID | F34: =VLOOKUP($E34,'Data Type Lookup'!$A$1:$C$21,2,FALSE) -> RAW(16) | I34: Y | P34: The User that owns the Code File. | Q34: owner | R34: =VLOOKUP(E34,'Data Type Lookup'!$A$1:$C$21,3,FALSE) -> java.util.UUID | W34: =_xlfn.CONCAT(B34,".",C34) -> CODE_FILE.OWNER_USER_UID | X34: =VLOOKUP(W34,ColumnMapping[New Table.Column],1,) -> CODE_FILE.OWNER_USER_UID | Y34: =_xlfn.XLOOKUP(Table6[[#This Row],[Table.Column]],ColumnMapping[Add Column Name],ColumnMapping[Old Table.Column],"",0,1) | Z34: =_xlfn.XLOOKUP(Table6[[#This Row],[Old Table.Column]],Cobra8.6[Table.Column],Cobra8.6[TYPE],"",0,1) | AA34: =_xlfn.XLOOKUP(Table6[[#This Row],[Old Table.Column]],Cobra8.6[Table.Column],Cobra8.6[LENGTH],"",0,1)
A35: Codes | B35: CODE_FILE | C35: CREATED_BY_USER_UID | D35: 11 | E35: GUID | F35: =VLOOKUP($E35,'Data Type Lookup'!$A$1:$C$21,2,FALSE) -> RAW(16) | I35: Y | P35: The User that created the Code File. | Q35: createdBy | R35: =VLOOKUP(E35,'Data Type Lookup'!$A$1:$C$21,3,FALSE) -> java.util.UUID | S35: 2 | W35: =_xlfn.CONCAT(B35,".",C35) -> CODE_FILE.CREATED_BY_USER_UID | X35: =VLOOKUP(W35,ColumnMapping[New Table.Column],1,) -> CODE_FILE.CREATED_BY_USER_UID | Y35: =_xlfn.XLOOKUP(Table6[[#This Row],[Table.Column]],ColumnMapping[Add Column Name],ColumnMapping[Old Table.Column],"",0,1) | Z35: =_xlfn.XLOOKUP(Table6[[#This Row],[Old Table.Column]],Cobra8.6[Table.Column],Cobra8.6[TYPE],"",0,1) | AA35: =_xlfn.XLOOKUP(Table6[[#This Row],[Old Table.Column]],Cobra8.6[Table.Column],Cobra8.6[LENGTH],"",0,1)
A36: Codes | B36: CODE_FILE | C36: CREATED_DATE | D36: 12 | E36: TIMESTAMP | F36: =VLOOKUP($E36,'Data Type Lookup'!$A$1:$C$21,2,FALSE) -> TIMESTAMP | I36: Y | P36: Date the Code File was created. | Q36: createdDate | R36: =VLOOKUP(E36,'Data Type Lookup'!$A$1:$C$21,3,FALSE) -> java.time.Instant | S36: 2 | W36: =_xlfn.CONCAT(B36,".",C36) -> CODE_FILE.CREATED_DATE | X36: =VLOOKUP(W36,ColumnMapping[New Table.Column],1,) -> CODE_FILE.CREATED_DATE | Y36: =_xlfn.XLOOKUP(Table6[[#This Row],[Table.Column]],ColumnMapping[Add Column Name],ColumnMapping[Old Table.Column],"",0,1) | Z36: =_xlfn.XLOOKUP(Table6[[#This Row],[Old Table.Column]],Cobra8.6[Table.Column],Cobra8.6[TYPE],"",0,1) | AA36: =_xlfn.XLOOKUP(Table6[[#This Row],[Old Table.Column]],Cobra8.6[Table.Column],Cobra8.6[LENGTH],"",0,1)
A37: Codes | B37: CODE_FILE | C37: LAST_MODIFIED_BY_USER_UID | D37: 13 | E37: GUID | F37: =VLOOKUP($E37,'Data Type Lookup'!$A$1:$C$21,2,FALSE) -> RAW(16) | I37: Y | P37: The User that last changed the Code File. | Q37: lastModifiedBy | R37: =VLOOKUP(E37,'Data Type Lookup'!$A$1:$C$21,3,FALSE) -> java.util.UUID | S37: 2 | W37: =_xlfn.CONCAT(B37,".",C37) -> CODE_FILE.LAST_MODIFIED_BY_USER_UID | X37: =VLOOKUP(W37,ColumnMapping[New Table.Column],1,) -> CODE_FILE.LAST_MODIFIED_BY_USER_UID | Y37: =_xlfn.XLOOKUP(Table6[[#This Row],[Table.Column]],ColumnMapping[Add Column Name],ColumnMapping[Old Table.Column],"",0,1) | Z37: =_xlfn.XLOOKUP(Table6[[#This Row],[Old Table.Column]],Cobra8.6[Table.Column],Cobra8.6[TYPE],"",0,1) | AA37: =_xlfn.XLOOKUP(Table6[[#This Row],[Old Table.Column]],Cobra8.6[Table.Column],Cobra8.6[LENGTH],"",0,1)
A38: Codes | B38: CODE_FILE | C38: LAST_MODIFIED_DATE | D38: 14 | E38: TIMESTAMP | F38: =VLOOKUP($E38,'Data Type Lookup'!$A$1:$C$21,2,FALSE) -> TIMESTAMP | I38: Y | P38: Date the last change was made to the Code File. | Q38: lastModifiedDate | R38: =VLOOKUP(E38,'Data Type Lookup'!$A$1:$C$21,3,FALSE) -> java.time.Instant | S38: 2 | W38: =_xlfn.CONCAT(B38,".",C38) -> CODE_FILE.LAST_MODIFIED_DATE | X38: =VLOOKUP(W38,ColumnMapping[New Table.Column],1,) -> CODE_FILE.LAST_MODIFIED_DATE | Y38: =_xlfn.XLOOKUP(Table6[[#This Row],[Table.Column]],ColumnMapping[Add Column Name],ColumnMapping[Old Table.Column],"",0,1) | Z38: =_xlfn.XLOOKUP(Table6[[#This Row],[Old Table.Column]],Cobra8.6[Table.Column],Cobra8.6[TYPE],"",0,1) | AA38: =_xlfn.XLOOKUP(Table6[[#This Row],[Old Table.Column]],Cobra8.6[Table.Column],Cobra8.6[LENGTH],"",0,1)
A39: Codes | B39: CODE_FILE | C39: PAD_CHAR | D39: 15 | E39: TEXT | F39: =VLOOKUP($E39,'Data Type Lookup'!$A$1:$C$21,2,FALSE) -> VARCHAR2 | G39: 1 | P39: Padding Character | Q39: =IF(C39="","",LOWER(LEFT(TRIM(C39),FIND("_",TRIM(C39)&"_")-1))&SUBSTITUTE(PROPER(SUBSTITUTE(MID(TRIM(C39),FIND("_",TRIM(C39)&"_"),LEN(TRIM(C39))),"_"," "))," ","")) -> padChar | R39: =VLOOKUP(E39,'Data Type Lookup'!$A$1:$C$21,3,FALSE) -> String | W39: =_xlfn.CONCAT(B39,".",C39) -> CODE_FILE.PAD_CHAR | X39: =VLOOKUP(W39,ColumnMapping[New Table.Column],1,) -> CODE_FILE.PAD_CHAR | Y39: =_xlfn.XLOOKUP(Table6[[#This Row],[Table.Column]],ColumnMapping[Add Column Name],ColumnMapping[Old Table.Column],"",0,1) -> BREAKDWN.PAD_CHAR | Z39: =_xlfn.XLOOKUP(Table6[[#This Row],[Old Table.Column]],Cobra8.6[Table.Column],Cobra8.6[TYPE],"",0,1) -> TEXT | AA39: =_xlfn.XLOOKUP(Table6[[#This Row],[Old Table.Column]],Cobra8.6[Table.Column],Cobra8.6[LENGTH],"",0,1) -> 1 | AB39: Y
A40: Codes | B40: CODE_FILE | C40: MAX_LEVEL | D40: 16 | E40: LONGINT | F40: =VLOOKUP($E40,'Data Type Lookup'!$A$1:$C$21,2,FALSE) -> NUMBER(19,0) | J40: 0 | P40: Maximum Level | Q40: =IF(C40="","",LOWER(LEFT(TRIM(C40),FIND("_",TRIM(C40)&"_")-1))&SUBSTITUTE(PROPER(SUBSTITUTE(MID(TRIM(C40),FIND("_",TRIM(C40)&"_"),LEN(TRIM(C40))),"_"," "))," ","")) -> maxLevel | R40: =VLOOKUP(E40,'Data Type Lookup'!$A$1:$C$21,3,FALSE) -> Long | W40: =_xlfn.CONCAT(B40,".",C40) -> CODE_FILE.MAX_LEVEL | X40: =VLOOKUP(W40,ColumnMapping[New Table.Column],1,) -> CODE_FILE.MAX_LEVEL | Y40: =_xlfn.XLOOKUP(Table6[[#This Row],[Table.Column]],ColumnMapping[Add Column Name],ColumnMapping[Old Table.Column],"",0,1) -> BREAKDWN.MAX_LEVEL | Z40: =_xlfn.XLOOKUP(Table6[[#This Row],[Old Table.Column]],Cobra8.6[Table.Column],Cobra8.6[TYPE],"",0,1) -> INTE | AA40: =_xlfn.XLOOKUP(Table6[[#This Row],[Old Table.Column]],Cobra8.6[Table.Column],Cobra8.6[LENGTH],"",0,1) -> -1 | AB40: Y
A41: Codes | B41: CODE_FILE | C41: LEVEL1 | D41: 17 | E41: LONGINT | F41: =VLOOKUP($E41,'Data Type Lookup'!$A$1:$C$21,2,FALSE) -> NUMBER(19,0) | J41: 0 | P41: Level 1 | Q41: =IF(C41="","",LOWER(LEFT(TRIM(C41),FIND("_",TRIM(C41)&"_")-1))&SUBSTITUTE(PROPER(SUBSTITUTE(MID(TRIM(C41),FIND("_",TRIM(C41)&"_"),LEN(TRIM(C41))),"_"," "))," ","")) -> level1 | R41: =VLOOKUP(E41,'Data Type Lookup'!$A$1:$C$21,3,FALSE) -> Long | W41: =_xlfn.CONCAT(B41,".",C41) -> CODE_FILE.LEVEL1 | X41: =VLOOKUP(W41,ColumnMapping[New Table.Column],1,) -> CODE_FILE.LEVEL1 | Y41: =_xlfn.XLOOKUP(Table6[[#This Row],[Table.Column]],ColumnMapping[Add Column Name],ColumnMapping[Old Table.Column],"",0,1) -> BREAKDWN.LEVEL1 | Z41: =_xlfn.XLOOKUP(Table6[[#This Row],[Old Table.Column]],Cobra8.6[Table.Column],Cobra8.6[TYPE],"",0,1) -> INTE | AA41: =_xlfn.XLOOKUP(Table6[[#This Row],[Old Table.Column]],Cobra8.6[Table.Column],Cobra8.6[LENGTH],"",0,1) -> -1 | AB41: Y
A42: Codes | B42: CODE_FILE | C42: LEVEL2 | D42: 18 | E42: LONGINT | F42: =VLOOKUP($E42,'Data Type Lookup'!$A$1:$C$21,2,FALSE) -> NUMBER(19,0) | J42: 0 | P42: Level 2 | Q42: =IF(C42="","",LOWER(LEFT(TRIM(C42),FIND("_",TRIM(C42)&"_")-1))&SUBSTITUTE(PROPER(SUBSTITUTE(MID(TRIM(C42),FIND("_",TRIM(C42)&"_"),LEN(TRIM(C42))),"_"," "))," ","")) -> level2 | R42: =VLOOKUP(E42,'Data Type Lookup'!$A$1:$C$21,3,FALSE) -> Long | W42: =_xlfn.CONCAT(B42,".",C42) -> CODE_FILE.LEVEL2 | X42: =VLOOKUP(W42,ColumnMapping[New Table.Column],1,) -> CODE_FILE.LEVEL2 | Y42: =_xlfn.XLOOKUP(Table6[[#This Row],[Table.Column]],ColumnMapping[Add Column Name],ColumnMapping[Old Table.Column],"",0,1) -> BREAKDWN.LEVEL2 | Z42: =_xlfn.XLOOKUP(Table6[[#This Row],[Old Table.Column]],Cobra8.6[Table.Column],Cobra8.6[TYPE],"",0,1) -> INTE | AA42: =_xlfn.XLOOKUP(Table6[[#This Row],[Old Table.Column]],Cobra8.6[Table.Column],Cobra8.6[LENGTH],"",0,1) -> -1 | AB42: Y
A43: Codes | B43: CODE_FILE | C43: LEVEL3 | D43: 19 | E43: LONGINT | F43: =VLOOKUP($E43,'Data Type Lookup'!$A$1:$C$21,2,FALSE) -> NUMBER(19,0) | J43: 0 | P43: Level 3 | Q43: =IF(C43="","",LOWER(LEFT(TRIM(C43),FIND("_",TRIM(C43)&"_")-1))&SUBSTITUTE(PROPER(SUBSTITUTE(MID(TRIM(C43),FIND("_",TRIM(C43)&"_"),LEN(TRIM(C43))),"_"," "))," ","")) -> level3 | R43: =VLOOKUP(E43,'Data Type Lookup'!$A$1:$C$21,3,FALSE) -> Long | W43: =_xlfn.CONCAT(B43,".",C43) -> CODE_FILE.LEVEL3 | X43: =VLOOKUP(W43,ColumnMapping[New Table.Column],1,) -> CODE_FILE.LEVEL3 | Y43: =_xlfn.XLOOKUP(Table6[[#This Row],[Table.Column]],ColumnMapping[Add Column Name],ColumnMapping[Old Table.Column],"",0,1) -> BREAKDWN.LEVEL3 | Z43: =_xlfn.XLOOKUP(Table6[[#This Row],[Old Table.Column]],Cobra8.6[Table.Column],Cobra8.6[TYPE],"",0,1) -> INTE | AA43: =_xlfn.XLOOKUP(Table6[[#This Row],[Old Table.Column]],Cobra8.6[Table.Column],Cobra8.6[LENGTH],"",0,1) -> -1 | AB43: Y
A44: Codes | B44: CODE_FILE | C44: LEVEL4 | D44: 20 | E44: LONGINT | F44: =VLOOKUP($E44,'Data Type Lookup'!$A$1:$C$21,2,FALSE) -> NUMBER(19,0) | J44: 0 | P44: Level 4 | Q44: =IF(C44="","",LOWER(LEFT(TRIM(C44),FIND("_",TRIM(C44)&"_")-1))&SUBSTITUTE(PROPER(SUBSTITUTE(MID(TRIM(C44),FIND("_",TRIM(C44)&"_"),LEN(TRIM(C44))),"_"," "))," ","")) -> level4 | R44: =VLOOKUP(E44,'Data Type Lookup'!$A$1:$C$21,3,FALSE) -> Long | W44: =_xlfn.CONCAT(B44,".",C44) -> CODE_FILE.LEVEL4 | X44: =VLOOKUP(W44,ColumnMapping[New Table.Column],1,) -> CODE_FILE.LEVEL4 | Y44: =_xlfn.XLOOKUP(Table6[[#This Row],[Table.Column]],ColumnMapping[Add Column Name],ColumnMapping[Old Table.Column],"",0,1) -> BREAKDWN.LEVEL4 | Z44: =_xlfn.XLOOKUP(Table6[[#This Row],[Old Table.Column]],Cobra8.6[Table.Column],Cobra8.6[TYPE],"",0,1) -> INTE | AA44: =_xlfn.XLOOKUP(Table6[[#This Row],[Old Table.Column]],Cobra8.6[Table.Column],Cobra8.6[LENGTH],"",0,1) -> -1 | AB44: Y
A45: Codes | B45: CODE_FILE | C45: LEVEL5 | D45: 21 | E45: LONGINT | F45: =VLOOKUP($E45,'Data Type Lookup'!$A$1:$C$21,2,FALSE) -> NUMBER(19,0) | J45: 0 | P45: Level 5 | Q45: =IF(C45="","",LOWER(LEFT(TRIM(C45),FIND("_",TRIM(C45)&"_")-1))&SUBSTITUTE(PROPER(SUBSTITUTE(MID(TRIM(C45),FIND("_",TRIM(C45)&"_"),LEN(TRIM(C45))),"_"," "))," ","")) -> level5 | R45: =VLOOKUP(E45,'Data Type Lookup'!$A$1:$C$21,3,FALSE) -> Long | W45: =_xlfn.CONCAT(B45,".",C45) -> CODE_FILE.LEVEL5 | X45: =VLOOKUP(W45,ColumnMapping[New Table.Column],1,) -> CODE_FILE.LEVEL5 | Y45: =_xlfn.XLOOKUP(Table6[[#This Row],[Table.Column]],ColumnMapping[Add Column Name],ColumnMapping[Old Table.Column],"",0,1) -> BREAKDWN.LEVEL5 | Z45: =_xlfn.XLOOKUP(Table6[[#This Row],[Old Table.Column]],Cobra8.6[Table.Column],Cobra8.6[TYPE],"",0,1) -> INTE | AA45: =_xlfn.XLOOKUP(Table6[[#This Row],[Old Table.Column]],Cobra8.6[Table.Column],Cobra8.6[LENGTH],"",0,1) -> -1 | AB45: Y
A46: Codes | B46: CODE_FILE | C46: LEVEL6 | D46: 22 | E46: LONGINT | F46: =VLOOKUP($E46,'Data Type Lookup'!$A$1:$C$21,2,FALSE) -> NUMBER(19,0) | J46: 0 | P46: Level 6 | Q46: =IF(C46="","",LOWER(LEFT(TRIM(C46),FIND("_",TRIM(C46)&"_")-1))&SUBSTITUTE(PROPER(SUBSTITUTE(MID(TRIM(C46),FIND("_",TRIM(C46)&"_"),LEN(TRIM(C46))),"_"," "))," ","")) -> level6 | R46: =VLOOKUP(E46,'Data Type Lookup'!$A$1:$C$21,3,FALSE) -> Long | W46: =_xlfn.CONCAT(B46,".",C46) -> CODE_FILE.LEVEL6 | X46: =VLOOKUP(W46,ColumnMapping[New Table.Column],1,) -> CODE_FILE.LEVEL6 | Y46: =_xlfn.XLOOKUP(Table6[[#This Row],[Table.Column]],ColumnMapping[Add Column Name],ColumnMapping[Old Table.Column],"",0,1) -> BREAKDWN.LEVEL6 | Z46: =_xlfn.XLOOKUP(Table6[[#This Row],[Old Table.Column]],Cobra8.6[Table.Column],Cobra8.6[TYPE],"",0,1) -> INTE | AA46: =_xlfn.XLOOKUP(Table6[[#This Row],[Old Table.Column]],Cobra8.6[Table.Column],Cobra8.6[LENGTH],"",0,1) -> -1 | AB46: Y
A47: Codes | B47: CODE_FILE | C47: LEVEL7 | D47: 23 | E47: LONGINT | F47: =VLOOKUP($E47,'Data Type Lookup'!$A$1:$C$21,2,FALSE) -> NUMBER(19,0) | J47: 0 | P47: Level 7 | Q47: =IF(C47="","",LOWER(LEFT(TRIM(C47),FIND("_",TRIM(C47)&"_")-1))&SUBSTITUTE(PROPER(SUBSTITUTE(MID(TRIM(C47),FIND("_",TRIM(C47)&"_"),LEN(TRIM(C47))),"_"," "))," ","")) -> level7 | R47: =VLOOKUP(E47,'Data Type Lookup'!$A$1:$C$21,3,FALSE) -> Long | W47: =_xlfn.CONCAT(B47,".",C47) -> CODE_FILE.LEVEL7 | X47: =VLOOKUP(W47,ColumnMapping[New Table.Column],1,) -> CODE_FILE.LEVEL7 | Y47: =_xlfn.XLOOKUP(Table6[[#This Row],[Table.Column]],ColumnMapping[Add Column Name],ColumnMapping[Old Table.Column],"",0,1) -> BREAKDWN.LEVEL7 | Z47: =_xlfn.XLOOKUP(Table6[[#This Row],[Old Table.Column]],Cobra8.6[Table.Column],Cobra8.6[TYPE],"",0,1) -> INTE | AA47: =_xlfn.XLOOKUP(Table6[[#This Row],[Old Table.Column]],Cobra8.6[Table.Column],Cobra8.6[LENGTH],"",0,1) -> -1 | AB47: Y
A48: Codes | B48: CODE_FILE | C48: LEVEL8 | D48: 24 | E48: LONGINT | F48: =VLOOKUP($E48,'Data Type Lookup'!$A$1:$C$21,2,FALSE) -> NUMBER(19,0) | J48: 0 | P48: Level 8 | Q48: =IF(C48="","",LOWER(LEFT(TRIM(C48),FIND("_",TRIM(C48)&"_")-1))&SUBSTITUTE(PROPER(SUBSTITUTE(MID(TRIM(C48),FIND("_",TRIM(C48)&"_"),LEN(TRIM(C48))),"_"," "))," ","")) -> level8 | R48: =VLOOKUP(E48,'Data Type Lookup'!$A$1:$C$21,3,FALSE) -> Long | W48: =_xlfn.CONCAT(B48,".",C48) -> CODE_FILE.LEVEL8 | X48: =VLOOKUP(W48,ColumnMapping[New Table.Column],1,) -> CODE_FILE.LEVEL8 | Y48: =_xlfn.XLOOKUP(Table6[[#This Row],[Table.Column]],ColumnMapping[Add Column Name],ColumnMapping[Old Table.Column],"",0,1) -> BREAKDWN.LEVEL8 | Z48: =_xlfn.XLOOKUP(Table6[[#This Row],[Old Table.Column]],Cobra8.6[Table.Column],Cobra8.6[TYPE],"",0,1) -> INTE | AA48: =_xlfn.XLOOKUP(Table6[[#This Row],[Old Table.Column]],Cobra8.6[Table.Column],Cobra8.6[LENGTH],"",0,1) -> -1 | AB48: Y
A49: Codes | B49: CODE_FILE | C49: LEVEL9 | D49: 25 | E49: LONGINT | F49: =VLOOKUP($E49,'Data Type Lookup'!$A$1:$C$21,2,FALSE) -> NUMBER(19,0) | J49: 0 | P49: Level 9 | Q49: =IF(C49="","",LOWER(LEFT(TRIM(C49),FIND("_",TRIM(C49)&"_")-1))&SUBSTITUTE(PROPER(SUBSTITUTE(MID(TRIM(C49),FIND("_",TRIM(C49)&"_"),LEN(TRIM(C49))),"_"," "))," ","")) -> level9 | R49: =VLOOKUP(E49,'Data Type Lookup'!$A$1:$C$21,3,FALSE) -> Long | W49: =_xlfn.CONCAT(B49,".",C49) -> CODE_FILE.LEVEL9 | X49: =VLOOKUP(W49,ColumnMapping[New Table.Column],1,) -> CODE_FILE.LEVEL9 | Y49: =_xlfn.XLOOKUP(Table6[[#This Row],[Table.Column]],ColumnMapping[Add Column Name],ColumnMapping[Old Table.Column],"",0,1) -> BREAKDWN.LEVEL9 | Z49: =_xlfn.XLOOKUP(Table6[[#This Row],[Old Table.Column]],Cobra8.6[Table.Column],Cobra8.6[TYPE],"",0,1) -> INTE | AA49: =_xlfn.XLOOKUP(Table6[[#This Row],[Old Table.Column]],Cobra8.6[Table.Column],Cobra8.6[LENGTH],"",0,1) -> -1 | AB49: Y
A50: Codes | B50: CODE_FILE | C50: LEVEL10 | D50: 26 | E50: LONGINT | F50: =VLOOKUP($E50,'Data Type Lookup'!$A$1:$C$21,2,FALSE) -> NUMBER(19,0) | J50: 0 | P50: Level 10 | Q50: =IF(C50="","",LOWER(LEFT(TRIM(C50),FIND("_",TRIM(C50)&"_")-1))&SUBSTITUTE(PROPER(SUBSTITUTE(MID(TRIM(C50),FIND("_",TRIM(C50)&"_"),LEN(TRIM(C50))),"_"," "))," ","")) -> level10 | R50: =VLOOKUP(E50,'Data Type Lookup'!$A$1:$C$21,3,FALSE) -> Long | W50: =_xlfn.CONCAT(B50,".",C50) -> CODE_FILE.LEVEL10 | X50: =VLOOKUP(W50,ColumnMapping[New Table.Column],1,) -> CODE_FILE.LEVEL10 | Y50: =_xlfn.XLOOKUP(Table6[[#This Row],[Table.Column]],ColumnMapping[Add Column Name],ColumnMapping[Old Table.Column],"",0,1) -> BREAKDWN.LEVEL10 | Z50: =_xlfn.XLOOKUP(Table6[[#This Row],[Old Table.Column]],Cobra8.6[Table.Column],Cobra8.6[TYPE],"",0,1) -> INTE | AA50: =_xlfn.XLOOKUP(Table6[[#This Row],[Old Table.Column]],Cobra8.6[Table.Column],Cobra8.6[LENGTH],"",0,1) -> -1 | AB50: Y
A51: Codes | B51: CODE_FILE | C51: LEVEL11 | D51: 27 | E51: LONGINT | F51: =VLOOKUP($E51,'Data Type Lookup'!$A$1:$C$21,2,FALSE) -> NUMBER(19,0) | J51: 0 | P51: Level 11 | Q51: =IF(C51="","",LOWER(LEFT(TRIM(C51),FIND("_",TRIM(C51)&"_")-1))&SUBSTITUTE(PROPER(SUBSTITUTE(MID(TRIM(C51),FIND("_",TRIM(C51)&"_"),LEN(TRIM(C51))),"_"," "))," ","")) -> level11 | R51: =VLOOKUP(E51,'Data Type Lookup'!$A$1:$C$21,3,FALSE) -> Long | W51: =_xlfn.CONCAT(B51,".",C51) -> CODE_FILE.LEVEL11 | X51: =VLOOKUP(W51,ColumnMapping[New Table.Column],1,) -> CODE_FILE.LEVEL11 | Y51: =_xlfn.XLOOKUP(Table6[[#This Row],[Table.Column]],ColumnMapping[Add Column Name],ColumnMapping[Old Table.Column],"",0,1) -> BREAKDWN.LEVEL11 | Z51: =_xlfn.XLOOKUP(Table6[[#This Row],[Old Table.Column]],Cobra8.6[Table.Column],Cobra8.6[TYPE],"",0,1) -> INTE | AA51: =_xlfn.XLOOKUP(Table6[[#This Row],[Old Table.Column]],Cobra8.6[Table.Column],Cobra8.6[LENGTH],"",0,1) -> -1 | AB51: Y
... A61: Codes | B61: CODE_FILE | C61: CODELENGTH | D61: 37 | E61: LONGINT | F61: =VLOOKUP($E61,'Data Type Lookup'!$A$1:$C$21,2,FALSE) -> NUMBER(19,0) | J61: 0 | P61: Code Length | Q61: =IF(C61="","",LOWER(LEFT(TRIM(C61),FIND("_",TRIM(C61)&"_")-1))&SUBSTITUTE(PROPER(SUBSTITUTE(MID(TRIM(C61),FIND("_",TRIM(C61)&"_"),LEN(TRIM(C61))),"_"," "))," ","")) -> codelength | R61: =VLOOKUP(E61,'Data Type Lookup'!$A$1:$C$21,3,FALSE) -> Long | W61: =_xlfn.CONCAT(B61,".",C61) -> CODE_FILE.CODELENGTH | X61: =VLOOKUP(W61,ColumnMapping[New Table.Column],1,) -> CODE_FILE.CODELENGTH | Y61: =_xlfn.XLOOKUP(Table6[[#This Row],[Table.Column]],ColumnMapping[Add Column Name],ColumnMapping[Old Table.Column],"",0,1) -> BREAKDWN.CODELENGTH | Z61: =_xlfn.XLOOKUP(Table6[[#This Row],[Old Table.Column]],Cobra8.6[Table.Column],Cobra8.6[TYPE],"",0,1) -> INTE | AA61: =_xlfn.XLOOKUP(Table6[[#This Row],[Old Table.Column]],Cobra8.6[Table.Column],Cobra8.6[LENGTH],"",0,1) -> -1 | AB61: Y
A62: Codes | B62: CODE_THRESHOLD | C62: ROW_UID | D62: 1 | E62: GUID | F62: =VLOOKUP($E62,'Data Type Lookup'!$A$1:$C$21,2,FALSE) -> RAW(16) | I62: Y | K62: Y | M62: CODE | N62: ROW_UID | O62: 1: 0..1 | P62: Unique Code Threshold Identifier. | Q62: uid | R62: =VLOOKUP(E62,'Data Type Lookup'!$A$1:$C$21,3,FALSE) -> java.util.UUID | S62: 3 | W62: =_xlfn.CONCAT(B62,".",C62) -> CODE_THRESHOLD.ROW_UID | X62: =VLOOKUP(W62,ColumnMapping[New Table.Column],1,) -> CODE_THRESHOLD.ROW_UID | Y62: =_xlfn.XLOOKUP(Table6[[#This Row],[Table.Column]],ColumnMapping[Add Column Name],ColumnMapping[Old Table.Column],"",0,1) | Z62: =_xlfn.XLOOKUP(Table6[[#This Row],[Old Table.Column]],Cobra8.6[Table.Column],Cobra8.6[TYPE],"",0,1) | AA62: =_xlfn.XLOOKUP(Table6[[#This Row],[Old Table.Column]],Cobra8.6[Table.Column],Cobra8.6[LENGTH],"",0,1)
A63: Codes | B63: CODE_THRESHOLD | C63: SEQUENCE | D63: 2 | E63: LONGINT | F63: =VLOOKUP($E63,'Data Type Lookup'!$A$1:$C$21,2,FALSE) -> NUMBER(19,0) | I63: Y | J63: 0 | P63: Concurrency Control Identifier. | Q63: sequence | R63: =VLOOKUP(E63,'Data Type Lookup'!$A$1:$C$21,3,FALSE) -> Long | S63: 3 | W63: =_xlfn.CONCAT(B63,".",C63) -> CODE_THRESHOLD.SEQUENCE | X63: =VLOOKUP(W63,ColumnMapping[New Table.Column],1,) -> CODE_THRESHOLD.SEQUENCE | Y63: =_xlfn.XLOOKUP(Table6[[#This Row],[Table.Column]],ColumnMapping[Add Column Name],ColumnMapping[Old Table.Column],"",0,1) | Z63: =_xlfn.XLOOKUP(Table6[[#This Row],[Old Table.Column]],Cobra8.6[Table.Column],Cobra8.6[TYPE],"",0,1) | AA63: =_xlfn.XLOOKUP(Table6[[#This Row],[Old Table.Column]],Cobra8.6[Table.Column],Cobra8.6[LENGTH],"",0,1)
A64: Codes | B64: CODE_THRESHOLD | C64: SPVF | D64: 4 | E64: DECIMAL | F64: =VLOOKUP($E64,'Data Type Lookup'!$A$1:$C$21,2,FALSE) -> NUMBER(21,6) | I64: Y | J64: 0 | P64: Threshold SV Value Current Period Favorable | Q64: scheduleVarianceCurrentPeriodFavorableValue | R64: =VLOOKUP(E64,'Data Type Lookup'!$A$1:$C$21,3,FALSE) -> java.math.BigDecimal | W64: =_xlfn.CONCAT(B64,".",C64) -> CODE_THRESHOLD.SPVF | X64: =VLOOKUP(W64,ColumnMapping[New Table.Column],1,) -> CODE_THRESHOLD.SPVF | Y64: =_xlfn.XLOOKUP(Table6[[#This Row],[Table.Column]],ColumnMapping[Add Column Name],ColumnMapping[Old Table.Column],"",0,1) | Z64: =_xlfn.XLOOKUP(Table6[[#This Row],[Old Table.Column]],Cobra8.6[Table.Column],Cobra8.6[TYPE],"",0,1) | AA64: =_xlfn.XLOOKUP(Table6[[#This Row],[Old Table.Column]],Cobra8.6[Table.Column],Cobra8.6[LENGTH],"",0,1)
A65: Codes | B65: CODE_THRESHOLD | C65: SPVU | D65: 5 | E65: DECIMAL | F65: =VLOOKUP($E65,'Data Type Lookup'!$A$1:$C$21,2,FALSE) -> NUMBER(21,6) | I65: Y | J65: 0 | P65: Threshold SV Value Current Period Unfavorable | Q65: scheduleVarianceCurrentPeriodUnfavorableValue | R65: =VLOOKUP(E65,'Data Type Lookup'!$A$1:$C$21,3,FALSE) -> java.math.BigDecimal | W65: =_xlfn.CONCAT(B65,".",C65) -> CODE_THRESHOLD.SPVU | X65: =VLOOKUP(W65,ColumnMapping[New Table.Column],1,) -> CODE_THRESHOLD.SPVU | Y65: =_xlfn.XLOOKUP(Table6[[#This Row],[Table.Column]],ColumnMapping[Add Column Name],ColumnMapping[Old Table.Column],"",0,1) | Z65: =_xlfn.XLOOKUP(Table6[[#This Row],[Old Table.Column]],Cobra8.6[Table.Column],Cobra8.6[TYPE],"",0,1) | AA65: =_xlfn.XLOOKUP(Table6[[#This Row],[Old Table.Column]],Cobra8.6[Table.Column],Cobra8.6[LENGTH],"",0,1)
A66: Codes | B66: CODE_THRESHOLD | C66: SPPF | D66: 6 | E66: PERCENT | F66: =VLOOKUP($E66,'Data Type Lookup'!$A$1:$C$21,2,FALSE) -> NUMBER(5,2) | I66: Y | J66: 0 | P66: Threshold SV % Current Period Favorable | Q66: scheduleVarianceCurrentPeriodFavorablePercentage | R66: =VLOOKUP(E66,'Data Type Lookup'!$A$1:$C$21,3,FALSE) -> java.math.BigDecimal | W66: =_xlfn.CONCAT(B66,".",C66) -> CODE_THRESHOLD.SPPF | X66: =VLOOKUP(W66,ColumnMapping[New Table.Column],1,) -> CODE_THRESHOLD.SPPF | Y66: =_xlfn.XLOOKUP(Table6[[#This Row],[Table.Column]],ColumnMapping[Add Column Name],ColumnMapping[Old Table.Column],"",0,1) | Z66: =_xlfn.XLOOKUP(Table6[[#This Row],[Old Table.Column]],Cobra8.6[Table.Column],Cobra8.6[TYPE],"",0,1) | AA66: =_xlfn.XLOOKUP(Table6[[#This Row],[Old Table.Column]],Cobra8.6[Table.Column],Cobra8.6[LENGTH],"",0,1)
A67: Codes | B67: CODE_THRESHOLD | C67: SPPU | D67: 7 | E67: PERCENT | F67: =VLOOKUP($E67,'Data Type Lookup'!$A$1:$C$21,2,FALSE) -> NUMBER(5,2) | I67: Y | J67: 0 | P67: Threshold SV % Current Period Unfavorable | Q67: scheduleVarianceCurrentPeriodUnfavorablePercentage | R67: =VLOOKUP(E67,'Data Type Lookup'!$A$1:$C$21,3,FALSE) -> java.math.BigDecimal | W67: =_xlfn.CONCAT(B67,".",C67) -> CODE_THRESHOLD.SPPU | X67: =VLOOKUP(W67,ColumnMapping[New Table.Column],1,) -> CODE_THRESHOLD.SPPU | Y67: =_xlfn.XLOOKUP(Table6[[#This Row],[Table.Column]],ColumnMapping[Add Column Name],ColumnMapping[Old Table.Column],"",0,1) | Z67: =_xlfn.XLOOKUP(Table6[[#This Row],[Old Table.Column]],Cobra8.6[Table.Column],Cobra8.6[TYPE],"",0,1) | AA67: =_xlfn.XLOOKUP(Table6[[#This Row],[Old Table.Column]],Cobra8.6[Table.Column],Cobra8.6[LENGTH],"",0,1)
A68: Codes | B68: CODE_THRESHOLD | C68: SCVF | D68: 8 | E68: DECIMAL | F68: =VLOOKUP($E68,'Data Type Lookup'!$A$1:$C$21,2,FALSE) -> NUMBER(21,6) | I68: Y | J68: 0 | P68: Threshold SV Value Cumulative Favorable | Q68: scheduleVarianceCumulativeFavorableValue | R68: =VLOOKUP(E68,'Data Type Lookup'!$A$1:$C$21,3,FALSE) -> java.math.BigDecimal | W68: =_xlfn.CONCAT(B68,".",C68) -> CODE_THRESHOLD.SCVF | X68: =VLOOKUP(W68,ColumnMapping[New Table.Column],1,) -> CODE_THRESHOLD.SCVF | Y68: =_xlfn.XLOOKUP(Table6[[#This Row],[Table.Column]],ColumnMapping[Add Column Name],ColumnMapping[Old Table.Column],"",0,1) | Z68: =_xlfn.XLOOKUP(Table6[[#This Row],[Old Table.Column]],Cobra8.6[Table.Column],Cobra8.6[TYPE],"",0,1) | AA68: =_xlfn.XLOOKUP(Table6[[#This Row],[Old Table.Column]],Cobra8.6[Table.Column],Cobra8.6[LENGTH],"",0,1)
A69: Codes | B69: CODE_THRESHOLD | C69: SCVU | D69: 9 | E69: DECIMAL | F69: =VLOOKUP($E69,'Data Type Lookup'!$A$1:$C$21,2,FALSE) -> NUMBER(21,6) | I69: Y | J69: 0 | P69: Threshold SV Value Cumulative Unfavorable | Q69: scheduleVarianceCumulativeUnfavorableValue | R69: =VLOOKUP(E69,'Data Type Lookup'!$A$1:$C$21,3,FALSE) -> java.math.BigDecimal | W69: =_xlfn.CONCAT(B69,".",C69) -> CODE_THRESHOLD.SCVU | X69: =VLOOKUP(W69,ColumnMapping[New Table.Column],1,) -> CODE_THRESHOLD.SCVU | Y69: =_xlfn.XLOOKUP(Table6[[#This Row],[Table.Column]],ColumnMapping[Add Column Name],ColumnMapping[Old Table.Column],"",0,1) | Z69: =_xlfn.XLOOKUP(Table6[[#This Row],[Old Table.Column]],Cobra8.6[Table.Column],Cobra8.6[TYPE],"",0,1) | AA69: =_xlfn.XLOOKUP(Table6[[#This Row],[Old Table.Column]],Cobra8.6[Table.Column],Cobra8.6[LENGTH],"",0,1)
A70: Codes | B70: CODE_THRESHOLD | C70: SCPF | D70: 10 | E70: PERCENT | F70: =VLOOKUP($E70,'Data Type Lookup'!$A$1:$C$21,2,FALSE) -> NUMBER(5,2) | I70: Y | J70: 0 | P70: Threshold SV % Cumulative Favorable | Q70: scheduleVarianceCumulativeFavorablePercentage | R70: =VLOOKUP(E70,'Data Type Lookup'!$A$1:$C$21,3,FALSE) -> java.math.BigDecimal | W70: =_xlfn.CONCAT(B70,".",C70) -> CODE_THRESHOLD.SCPF | X70: =VLOOKUP(W70,ColumnMapping[New Table.Column],1,) -> CODE_THRESHOLD.SCPF | Y70: =_xlfn.XLOOKUP(Table6[[#This Row],[Table.Column]],ColumnMapping[Add Column Name],ColumnMapping[Old Table.Column],"",0,1) | Z70: =_xlfn.XLOOKUP(Table6[[#This Row],[Old Table.Column]],Cobra8.6[Table.Column],Cobra8.6[TYPE],"",0,1) | AA70: =_xlfn.XLOOKUP(Table6[[#This Row],[Old Table.Column]],Cobra8.6[Table.Column],Cobra8.6[LENGTH],"",0,1)
A71: Codes | B71: CODE_THRESHOLD | C71: SCPU | D71: 11 | E71: PERCENT | F71: =VLOOKUP($E71,'Data Type Lookup'!$A$1:$C$21,2,FALSE) -> NUMBER(5,2) | I71: Y | J71: 0 | P71: Threshold SV % Cumulative Unfavorable | Q71: scheduleVarianceCumulativeUnfavorablePercentage | R71: =VLOOKUP(E71,'Data Type Lookup'!$A$1:$C$21,3,FALSE) -> java.math.BigDecimal | W71: =_xlfn.CONCAT(B71,".",C71) -> CODE_THRESHOLD.SCPU | X71: =VLOOKUP(W71,ColumnMapping[New Table.Column],1,) -> CODE_THRESHOLD.SCPU | Y71: =_xlfn.XLOOKUP(Table6[[#This Row],[Table.Column]],ColumnMapping[Add Column Name],ColumnMapping[Old Table.Column],"",0,1) | Z71: =_xlfn.XLOOKUP(Table6[[#This Row],[Old Table.Column]],Cobra8.6[Table.Column],Cobra8.6[TYPE],"",0,1) | AA71: =_xlfn.XLOOKUP(Table6[[#This Row],[Old Table.Column]],Cobra8.6[Table.Column],Cobra8.6[LENGTH],"",0,1)
A72: Codes | B72: CODE_THRESHOLD | C72: CPVF | D72: 12 | E72: DECIMAL | F72: =VLOOKUP($E72,'Data Type Lookup'!$A$1:$C$21,2,FALSE) -> NUMBER(21,6) | I72: Y | J72: 0 | P72: Threshold CV Value Current Period Favorable | Q72: costVarianceCurrentPeriodFavorableValue | R72: =VLOOKUP(E72,'Data Type Lookup'!$A$1:$C$21,3,FALSE) -> java.math.BigDecimal | W72: =_xlfn.CONCAT(B72,".",C72) -> CODE_THRESHOLD.CPVF | X72: =VLOOKUP(W72,ColumnMapping[New Table.Column],1,) -> CODE_THRESHOLD.CPVF | Y72: =_xlfn.XLOOKUP(Table6[[#This Row],[Table.Column]],ColumnMapping[Add Column Name],ColumnMapping[Old Table.Column],"",0,1) | Z72: =_xlfn.XLOOKUP(Table6[[#This Row],[Old Table.Column]],Cobra8.6[Table.Column],Cobra8.6[TYPE],"",0,1) | AA72: =_xlfn.XLOOKUP(Table6[[#This Row],[Old Table.Column]],Cobra8.6[Table.Column],Cobra8.6[LENGTH],"",0,1)
A73: Codes | B73: CODE_THRESHOLD | C73: CPVU | D73: 13 | E73: DECIMAL | F73: =VLOOKUP($E73,'Data Type Lookup'!$A$1:$C$21,2,FALSE) -> NUMBER(21,6) | I73: Y | J73: 0 | P73: Threshold CV Value Current Period Unfavorable | Q73: costVarianceCurrentPeriodUnfavorableValue | R73: =VLOOKUP(E73,'Data Type Lookup'!$A$1:$C$21,3,FALSE) -> java.math.BigDecimal | W73: =_xlfn.CONCAT(B73,".",C73) -> CODE_THRESHOLD.CPVU | X73: =VLOOKUP(W73,ColumnMapping[New Table.Column],1,) -> CODE_THRESHOLD.CPVU | Y73: =_xlfn.XLOOKUP(Table6[[#This Row],[Table.Column]],ColumnMapping[Add Column Name],ColumnMapping[Old Table.Column],"",0,1) | Z73: =_xlfn.XLOOKUP(Table6[[#This Row],[Old Table.Column]],Cobra8.6[Table.Column],Cobra8.6[TYPE],"",0,1) | AA73: =_xlfn.XLOOKUP(Table6[[#This Row],[Old Table.Column]],Cobra8.6[Table.Column],Cobra8.6[LENGTH],"",0,1)
A74: Codes | B74: CODE_THRESHOLD | C74: CPPF | D74: 14 | E74: PERCENT | F74: =VLOOKUP($E74,'Data Type Lookup'!$A$1:$C$21,2,FALSE) -> NUMBER(5,2) | I74: Y | J74: 0 | P74: Threshold CV % Current Period Favorable | Q74: costVarianceCurrentPeriodFavorablePercentage | R74: =VLOOKUP(E74,'Data Type Lookup'!$A$1:$C$21,3,FALSE) -> java.math.BigDecimal | W74: =_xlfn.CONCAT(B74,".",C74) -> CODE_THRESHOLD.CPPF | X74: =VLOOKUP(W74,ColumnMapping[New Table.Column],1,) -> CODE_THRESHOLD.CPPF | Y74: =_xlfn.XLOOKUP(Table6[[#This Row],[Table.Column]],ColumnMapping[Add Column Name],ColumnMapping[Old Table.Column],"",0,1) | Z74: =_xlfn.XLOOKUP(Table6[[#This Row],[Old Table.Column]],Cobra8.6[Table.Column],Cobra8.6[TYPE],"",0,1) | AA74: =_xlfn.XLOOKUP(Table6[[#This Row],[Old Table.Column]],Cobra8.6[Table.Column],Cobra8.6[LENGTH],"",0,1)
A75: Codes | B75: CODE_THRESHOLD | C75: CPPU | D75: 15 | E75: PERCENT | F75: =VLOOKUP($E75,'Data Type Lookup'!$A$1:$C$21,2,FALSE) -> NUMBER(5,2) | I75: Y | J75: 0 | P75: Threshold CV % Current Period Unfavorable | Q75: costVarianceCurrentPeriodUnfavorablePercentage | R75: =VLOOKUP(E75,'Data Type Lookup'!$A$1:$C$21,3,FALSE) -> java.math.BigDecimal | W75: =_xlfn.CONCAT(B75,".",C75) -> CODE_THRESHOLD.CPPU | X75: =VLOOKUP(W75,ColumnMapping[New Table.Column],1,) -> CODE_THRESHOLD.CPPU | Y75: =_xlfn.XLOOKUP(Table6[[#This Row],[Table.Column]],ColumnMapping[Add Column Name],ColumnMapping[Old Table.Column],"",0,1) | Z75: =_xlfn.XLOOKUP(Table6[[#This Row],[Old Table.Column]],Cobra8.6[Table.Column],Cobra8.6[TYPE],"",0,1) | AA75: =_xlfn.XLOOKUP(Table6[[#This Row],[Old Table.Column]],Cobra8.6[Table.Column],Cobra8.6[LENGTH],"",0,1)
... A83: Codes | B83: CODE_THRESHOLD | C83: CAPU | D83: 23 | E83: PERCENT | F83: =VLOOKUP($E83,'Data Type Lookup'!$A$1:$C$21,2,FALSE) -> NUMBER(5,2) | I83: Y | J83: 0 | P83: Threshold CV % At Complete Unfavorable | Q83: costVarianceAtCompleteUnfavorablePercentage | R83: =VLOOKUP(E83,'Data Type Lookup'!$A$1:$C$21,3,FALSE) -> java.math.BigDecimal | W83: =_xlfn.CONCAT(B83,".",C83) -> CODE_THRESHOLD.CAPU | X83: =VLOOKUP(W83,ColumnMapping[New Table.Column],1,) -> CODE_THRESHOLD.CAPU | Y83: =_xlfn.XLOOKUP(Table6[[#This Row],[Table.Column]],ColumnMapping[Add Column Name],ColumnMapping[Old Table.Column],"",0,1) | Z83: =_xlfn.XLOOKUP(Table6[[#This Row],[Old Table.Column]],Cobra8.6[Table.Column],Cobra8.6[TYPE],"",0,1) | AA83: =_xlfn.XLOOKUP(Table6[[#This Row],[Old Table.Column]],Cobra8.6[Table.Column],Cobra8.6[LENGTH],"",0,1)
A84: Codes | B84: CODE_THRESHOLD | C84: SPF_TL | D84: 24 | E84: TEXT | F84: =VLOOKUP($E84,'Data Type Lookup'!$A$1:$C$21,2,FALSE) -> VARCHAR2 | G84: 3 | P84: Threshold Logic SV Current Period Favorable | Q84: scheduleVarianceCurrentPeriodFavorableOperator | R84: =VLOOKUP(E84,'Data Type Lookup'!$A$1:$C$21,3,FALSE) -> String | W84: =_xlfn.CONCAT(B84,".",C84) -> CODE_THRESHOLD.SPF_TL | X84: =VLOOKUP(W84,ColumnMapping[New Table.Column],1,) -> CODE_THRESHOLD.SPF_TL | Y84: =_xlfn.XLOOKUP(Table6[[#This Row],[Table.Column]],ColumnMapping[Add Column Name],ColumnMapping[Old Table.Column],"",0,1) | Z84: =_xlfn.XLOOKUP(Table6[[#This Row],[Old Table.Column]],Cobra8.6[Table.Column],Cobra8.6[TYPE],"",0,1) | AA84: =_xlfn.XLOOKUP(Table6[[#This Row],[Old Table.Column]],Cobra8.6[Table.Column],Cobra8.6[LENGTH],"",0,1)
A85: Codes | B85: CODE_THRESHOLD | C85: SPU_TL | D85: 25 | E85: TEXT | F85: =VLOOKUP($E85,'Data Type Lookup'!$A$1:$C$21,2,FALSE) -> VARCHAR2 | G85: 3 | P85: Threshold Logic SV Current Period Unfavorable | Q85: scheduleVarianceCurrentPeriodUnfavorableOperator | R85: =VLOOKUP(E85,'Data Type Lookup'!$A$1:$C$21,3,FALSE) -> String | W85: =_xlfn.CONCAT(B85,".",C85) -> CODE_THRESHOLD.SPU_TL | X85: =VLOOKUP(W85,ColumnMapping[New Table.Column],1,) -> CODE_THRESHOLD.SPU_TL | Y85: =_xlfn.XLOOKUP(Table6[[#This Row],[Table.Column]],ColumnMapping[Add Column Name],ColumnMapping[Old Table.Column],"",0,1) | Z85: =_xlfn.XLOOKUP(Table6[[#This Row],[Old Table.Column]],Cobra8.6[Table.Column],Cobra8.6[TYPE],"",0,1) | AA85: =_xlfn.XLOOKUP(Table6[[#This Row],[Old Table.Column]],Cobra8.6[Table.Column],Cobra8.6[LENGTH],"",0,1)
A86: Codes | B86: CODE_THRESHOLD | C86: SCF_TL | D86: 26 | E86: TEXT | F86: =VLOOKUP($E86,'Data Type Lookup'!$A$1:$C$21,2,FALSE) -> VARCHAR2 | G86: 3 | P86: Threshold Logic SV Cumulative Favorable | Q86: scheduleVarianceCumulativeFavorableOperator | R86: =VLOOKUP(E86,'Data Type Lookup'!$A$1:$C$21,3,FALSE) -> String | W86: =_xlfn.CONCAT(B86,".",C86) -> CODE_THRESHOLD.SCF_TL | X86: =VLOOKUP(W86,ColumnMapping[New Table.Column],1,) -> CODE_THRESHOLD.SCF_TL | Y86: =_xlfn.XLOOKUP(Table6[[#This Row],[Table.Column]],ColumnMapping[Add Column Name],ColumnMapping[Old Table.Column],"",0,1) | Z86: =_xlfn.XLOOKUP(Table6[[#This Row],[Old Table.Column]],Cobra8.6[Table.Column],Cobra8.6[TYPE],"",0,1) | AA86: =_xlfn.XLOOKUP(Table6[[#This Row],[Old Table.Column]],Cobra8.6[Table.Column],Cobra8.6[LENGTH],"",0,1)
A87: Codes | B87: CODE_THRESHOLD | C87: SCU_TL | D87: 27 | E87: TEXT | F87: =VLOOKUP($E87,'Data Type Lookup'!$A$1:$C$21,2,FALSE) -> VARCHAR2 | G87: 3 | P87: Threshold Logic SV Cumulative Unfavorable | Q87: scheduleVarianceCumulativeUnfavorableOperator | R87: =VLOOKUP(E87,'Data Type Lookup'!$A$1:$C$21,3,FALSE) -> String | W87: =_xlfn.CONCAT(B87,".",C87) -> CODE_THRESHOLD.SCU_TL | X87: =VLOOKUP(W87,ColumnMapping[New Table.Column],1,) -> CODE_THRESHOLD.SCU_TL | Y87: =_xlfn.XLOOKUP(Table6[[#This Row],[Table.Column]],ColumnMapping[Add Column Name],ColumnMapping[Old Table.Column],"",0,1) | Z87: =_xlfn.XLOOKUP(Table6[[#This Row],[Old Table.Column]],Cobra8.6[Table.Column],Cobra8.6[TYPE],"",0,1) | AA87: =_xlfn.XLOOKUP(Table6[[#This Row],[Old Table.Column]],Cobra8.6[Table.Column],Cobra8.6[LENGTH],"",0,1)
A88: Codes | B88: CODE_THRESHOLD | C88: CPF_TL | D88: 28 | E88: TEXT | F88: =VLOOKUP($E88,'Data Type Lookup'!$A$1:$C$21,2,FALSE) -> VARCHAR2 | G88: 3 | P88: Threshold Logic CV Current Period Favorable | Q88: costVarianceCurrentPeriodFavorableOperator | R88: =VLOOKUP(E88,'Data Type Lookup'!$A$1:$C$21,3,FALSE) -> String | W88: =_xlfn.CONCAT(B88,".",C88) -> CODE_THRESHOLD.CPF_TL | X88: =VLOOKUP(W88,ColumnMapping[New Table.Column],1,) -> CODE_THRESHOLD.CPF_TL | Y88: =_xlfn.XLOOKUP(Table6[[#This Row],[Table.Column]],ColumnMapping[Add Column Name],ColumnMapping[Old Table.Column],"",0,1) | Z88: =_xlfn.XLOOKUP(Table6[[#This Row],[Old Table.Column]],Cobra8.6[Table.Column],Cobra8.6[TYPE],"",0,1) | AA88: =_xlfn.XLOOKUP(Table6[[#This Row],[Old Table.Column]],Cobra8.6[Table.Column],Cobra8.6[LENGTH],"",0,1)
A89: Codes | B89: CODE_THRESHOLD | C89: CPU_TL | D89: 29 | E89: TEXT | F89: =VLOOKUP($E89,'Data Type Lookup'!$A$1:$C$21,2,FALSE) -> VARCHAR2 | G89: 3 | P89: Threshold Logic CV Current Period Unfavorable | Q89: costVarianceCurrentPeriodUnfavorableOperator | R89: =VLOOKUP(E89,'Data Type Lookup'!$A$1:$C$21,3,FALSE) -> String | W89: =_xlfn.CONCAT(B89,".",C89) -> CODE_THRESHOLD.CPU_TL | X89: =VLOOKUP(W89,ColumnMapping[New Table.Column],1,) -> CODE_THRESHOLD.CPU_TL | Y89: =_xlfn.XLOOKUP(Table6[[#This Row],[Table.Column]],ColumnMapping[Add Column Name],ColumnMapping[Old Table.Column],"",0,1) | Z89: =_xlfn.XLOOKUP(Table6[[#This Row],[Old Table.Column]],Cobra8.6[Table.Column],Cobra8.6[TYPE],"",0,1) | AA89: =_xlfn.XLOOKUP(Table6[[#This Row],[Old Table.Column]],Cobra8.6[Table.Column],Cobra8.6[LENGTH],"",0,1)
A90: Codes | B90: CODE_THRESHOLD | C90: CCF_TL | D90: 30 | E90: TEXT | F90: =VLOOKUP($E90,'Data Type Lookup'!$A$1:$C$21,2,FALSE) -> VARCHAR2 | G90: 3 | P90: Threshold Logic CV Cumulative Favorable | Q90: costVarianceCumulativeFavorableOperator | R90: =VLOOKUP(E90,'Data Type Lookup'!$A$1:$C$21,3,FALSE) -> String | W90: =_xlfn.CONCAT(B90,".",C90) -> CODE_THRESHOLD.CCF_TL | X90: =VLOOKUP(W90,ColumnMapping[New Table.Column],1,) -> CODE_THRESHOLD.CCF_TL | Y90: =_xlfn.XLOOKUP(Table6[[#This Row],[Table.Column]],ColumnMapping[Add Column Name],ColumnMapping[Old Table.Column],"",0,1) | Z90: =_xlfn.XLOOKUP(Table6[[#This Row],[Old Table.Column]],Cobra8.6[Table.Column],Cobra8.6[TYPE],"",0,1) | AA90: =_xlfn.XLOOKUP(Table6[[#This Row],[Old Table.Column]],Cobra8.6[Table.Column],Cobra8.6[LENGTH],"",0,1)
A91: Codes | B91: CODE_THRESHOLD | C91: CCU_TL | D91: 31 | E91: TEXT | F91: =VLOOKUP($E91,'Data Type Lookup'!$A$1:$C$21,2,FALSE) -> VARCHAR2 | G91: 3 | P91: Threshold Logic CV Cumulative Unfavorable | Q91: costVarianceCumulativeUnfavorableOperator | R91: =VLOOKUP(E91,'Data Type Lookup'!$A$1:$C$21,3,FALSE) -> String | W91: =_xlfn.CONCAT(B91,".",C91) -> CODE_THRESHOLD.CCU_TL | X91: =VLOOKUP(W91,ColumnMapping[New Table.Column],1,) -> CODE_THRESHOLD.CCU_TL | Y91: =_xlfn.XLOOKUP(Table6[[#This Row],[Table.Column]],ColumnMapping[Add Column Name],ColumnMapping[Old Table.Column],"",0,1) | Z91: =_xlfn.XLOOKUP(Table6[[#This Row],[Old Table.Column]],Cobra8.6[Table.Column],Cobra8.6[TYPE],"",0,1) | AA91: =_xlfn.XLOOKUP(Table6[[#This Row],[Old Table.Column]],Cobra8.6[Table.Column],Cobra8.6[LENGTH],"",0,1)
A92: Codes | B92: CODE_THRESHOLD | C92: CAF_TL | D92: 32 | E92: TEXT | F92: =VLOOKUP($E92,'Data Type Lookup'!$A$1:$C$21,2,FALSE) -> VARCHAR2 | G92: 3 | P92: Threshold Logic CV At Complete Favorable | Q92: costVarianceAtCompleteFavorableOperator | R92: =VLOOKUP(E92,'Data Type Lookup'!$A$1:$C$21,3,FALSE) -> String | W92: =_xlfn.CONCAT(B92,".",C92) -> CODE_THRESHOLD.CAF_TL | X92: =VLOOKUP(W92,ColumnMapping[New Table.Column],1,) -> CODE_THRESHOLD.CAF_TL | Y92: =_xlfn.XLOOKUP(Table6[[#This Row],[Table.Column]],ColumnMapping[Add Column Name],ColumnMapping[Old Table.Column],"",0,1) | Z92: =_xlfn.XLOOKUP(Table6[[#This Row],[Old Table.Column]],Cobra8.6[Table.Column],Cobra8.6[TYPE],"",0,1) | AA92: =_xlfn.XLOOKUP(Table6[[#This Row],[Old Table.Column]],Cobra8.6[Table.Column],Cobra8.6[LENGTH],"",0,1)
A93: Codes | B93: CODE_THRESHOLD | C93: CAU_TL | D93: 33 | E93: TEXT | F93: =VLOOKUP($E93,'Data Type Lookup'!$A$1:$C$21,2,FALSE) -> VARCHAR2 | G93: 3 | P93: Threshold Logic CV At Complete Unfavorable | Q93: costVarianceAtCompleteUnfavorableOperator | R93: =VLOOKUP(E93,'Data Type Lookup'!$A$1:$C$21,3,FALSE) -> String | W93: =_xlfn.CONCAT(B93,".",C93) -> CODE_THRESHOLD.CAU_TL | X93: =VLOOKUP(W93,ColumnMapping[New Table.Column],1,) -> CODE_THRESHOLD.CAU_TL | Y93: =_xlfn.XLOOKUP(Table6[[#This Row],[Table.Column]],ColumnMapping[Add Column Name],ColumnMapping[Old Table.Column],"",0,1) | Z93: =_xlfn.XLOOKUP(Table6[[#This Row],[Old Table.Column]],Cobra8.6[Table.Column],Cobra8.6[TYPE],"",0,1) | AA93: =_xlfn.XLOOKUP(Table6[[#This Row],[Old Table.Column]],Cobra8.6[Table.Column],Cobra8.6[LENGTH],"",0,1)
A94: Common | B94: PRODUCT_CONFIG | C94: ROW_UID | D94: 1 | E94: GUID | F94: =VLOOKUP($E94,'Data Type Lookup'!$A$1:$C$21,2,FALSE) -> RAW(16) | I94: Y | K94: Y | P94: Unique Product Setting Identifier. | Q94: uid | R94: =VLOOKUP(E94,'Data Type Lookup'!$A$1:$C$21,3,FALSE) -> java.util.UUID | S94: 3 | W94: =_xlfn.CONCAT(B94,".",C94) -> PRODUCT_CONFIG.ROW_UID | X94: =VLOOKUP(W94,ColumnMapping[New Table.Column],1,) -> PRODUCT_CONFIG.ROW_UID | Y94: =_xlfn.XLOOKUP(Table6[[#This Row],[Table.Column]],ColumnMapping[Add Column Name],ColumnMapping[Old Table.Column],"",0,1) | Z94: =_xlfn.XLOOKUP(Table6[[#This Row],[Old Table.Column]],Cobra8.6[Table.Column],Cobra8.6[TYPE],"",0,1) | AA94: =_xlfn.XLOOKUP(Table6[[#This Row],[Old Table.Column]],Cobra8.6[Table.Column],Cobra8.6[LENGTH],"",0,1)
A95: Common | B95: PRODUCT_CONFIG | C95: SEQUENCE | D95: 2 | E95: LONGINT | F95: =VLOOKUP($E95,'Data Type Lookup'!$A$1:$C$21,2,FALSE) -> NUMBER(19,0) | I95: Y | J95: 0 | P95: Concurrency Control Identifier. | Q95: sequence | R95: =VLOOKUP(E95,'Data Type Lookup'!$A$1:$C$21,3,FALSE) -> Long | S95: 3 | W95: =_xlfn.CONCAT(B95,".",C95) -> PRODUCT_CONFIG.SEQUENCE | X95: =VLOOKUP(W95,ColumnMapping[New Table.Column],1,) -> PRODUCT_CONFIG.SEQUENCE | Y95: =_xlfn.XLOOKUP(Table6[[#This Row],[Table.Column]],ColumnMapping[Add Column Name],ColumnMapping[Old Table.Column],"",0,1) | Z95: =_xlfn.XLOOKUP(Table6[[#This Row],[Old Table.Column]],Cobra8.6[Table.Column],Cobra8.6[TYPE],"",0,1) | AA95: =_xlfn.XLOOKUP(Table6[[#This Row],[Old Table.Column]],Cobra8.6[Table.Column],Cobra8.6[LENGTH],"",0,1)
A96: Common | B96: PRODUCT_CONFIG | C96: PRODUCT_ID | D96: 3 | E96: SHORTINT | F96: =VLOOKUP($E96,'Data Type Lookup'!$A$1:$C$21,2,FALSE) -> NUMBER(5,0) | I96: Y | J96: 0 | P96: Product ID that the Product Setting is associate with. 0 If Product Setting is not Product specific. | Q96: productId | R96: =VLOOKUP(E96,'Data Type Lookup'!$A$1:$C$21,3,FALSE) -> Short | W96: =_xlfn.CONCAT(B96,".",C96) -> PRODUCT_CONFIG.PRODUCT_ID | X96: =VLOOKUP(W96,ColumnMapping[New Table.Column],1,) -> PRODUCT_CONFIG.PRODUCT_ID | Y96: =_xlfn.XLOOKUP(Table6[[#This Row],[Table.Column]],ColumnMapping[Add Column Name],ColumnMapping[Old Table.Column],"",0,1) | Z96: =_xlfn.XLOOKUP(Table6[[#This Row],[Old Table.Column]],Cobra8.6[Table.Column],Cobra8.6[TYPE],"",0,1) | AA96: =_xlfn.XLOOKUP(Table6[[#This Row],[Old Table.Column]],Cobra8.6[Table.Column],Cobra8.6[LENGTH],"",0,1)
A97: Common | B97: PRODUCT_CONFIG | C97: TYPE | D97: 4 | E97: TEXT | F97: =VLOOKUP($E97,'Data Type Lookup'!$A$1:$C$21,2,FALSE) -> VARCHAR2 | G97: 30 | I97: Y | P97: Config Type | Q97: type | R97: =VLOOKUP(E97,'Data Type Lookup'!$A$1:$C$21,3,FALSE) -> String | V97: ? Are identical names allow for differernt settings distunguished by a setting type? | W97: =_xlfn.CONCAT(B97,".",C97) -> PRODUCT_CONFIG.TYPE | X97: =VLOOKUP(W97,ColumnMapping[New Table.Column],1,) -> PRODUCT_CONFIG.TYPE | Y97: =_xlfn.XLOOKUP(Table6[[#This Row],[Table.Column]],ColumnMapping[Add Column Name],ColumnMapping[Old Table.Column],"",0,1) | Z97: =_xlfn.XLOOKUP(Table6[[#This Row],[Old Table.Column]],Cobra8.6[Table.Column],Cobra8.6[TYPE],"",0,1) | AA97: =_xlfn.XLOOKUP(Table6[[#This Row],[Old Table.Column]],Cobra8.6[Table.Column],Cobra8.6[LENGTH],"",0,1)
A98: Common | B98: PRODUCT_CONFIG | C98: NAME | D98: 5 | E98: NTEXT | F98: =VLOOKUP($E98,'Data Type Lookup'!$A$1:$C$21,2,FALSE) -> NVARCHAR2 | G98: 100 | I98: Y | P98: Product Setting Name | Q98: name | R98: =VLOOKUP(E98,'Data Type Lookup'!$A$1:$C$21,3,FALSE) -> String | W98: =_xlfn.CONCAT(B98,".",C98) -> PRODUCT_CONFIG.NAME | X98: =VLOOKUP(W98,ColumnMapping[New Table.Column],1,) -> PRODUCT_CONFIG.NAME | Y98: =_xlfn.XLOOKUP(Table6[[#This Row],[Table.Column]],ColumnMapping[Add Column Name],ColumnMapping[Old Table.Column],"",0,1) | Z98: =_xlfn.XLOOKUP(Table6[[#This Row],[Old Table.Column]],Cobra8.6[Table.Column],Cobra8.6[TYPE],"",0,1) | AA98: =_xlfn.XLOOKUP(Table6[[#This Row],[Old Table.Column]],Cobra8.6[Table.Column],Cobra8.6[LENGTH],"",0,1)
A99: Common | B99: PRODUCT_CONFIG | C99: OWNER_USER_UID | D99: 6 | E99: GUID | F99: =VLOOKUP($E99,'Data Type Lookup'!$A$1:$C$21,2,FALSE) -> RAW(16) | P99: The User that owns the Product Config. | Q99: owner | R99: =VLOOKUP(E99,'Data Type Lookup'!$A$1:$C$21,3,FALSE) -> java.util.UUID | V99: ? I don't think we need an owner for a setting unless we also want to add ACL. But we currently don't support this. | W99: =_xlfn.CONCAT(B99,".",C99) -> PRODUCT_CONFIG.OWNER_USER_UID | X99: =VLOOKUP(W99,ColumnMapping[New Table.Column],1,) -> PRODUCT_CONFIG.OWNER_USER_UID | Y99: =_xlfn.XLOOKUP(Table6[[#This Row],[Table.Column]],ColumnMapping[Add Column Name],ColumnMapping[Old Table.Column],"",0,1) | Z99: =_xlfn.XLOOKUP(Table6[[#This Row],[Old Table.Column]],Cobra8.6[Table.Column],Cobra8.6[TYPE],"",0,1) | AA99: =_xlfn.XLOOKUP(Table6[[#This Row],[Old Table.Column]],Cobra8.6[Table.Column],Cobra8.6[LENGTH],"",0,1)
A100: Common | B100: PRODUCT_CONFIG | C100: CREATED_BY_USER_UID | D100: 7 | E100: GUID | F100: =VLOOKUP($E100,'Data Type Lookup'!$A$1:$C$21,2,FALSE) -> RAW(16) | I100: Y | P100: The User that created the Product Config. | Q100: createdBy | R100: =VLOOKUP(E100,'Data Type Lookup'!$A$1:$C$21,3,FALSE) -> java.util.UUID | S100: 2 | W100: =_xlfn.CONCAT(B100,".",C100) -> PRODUCT_CONFIG.CREATED_BY_USER_UID | X100: =VLOOKUP(W100,ColumnMapping[New Table.Column],1,) -> PRODUCT_CONFIG.CREATED_BY_USER_UID | Y100: =_xlfn.XLOOKUP(Table6[[#This Row],[Table.Column]],ColumnMapping[Add Column Name],ColumnMapping[Old Table.Column],"",0,1) | Z100: =_xlfn.XLOOKUP(Table6[[#This Row],[Old Table.Column]],Cobra8.6[Table.Column],Cobra8.6[TYPE],"",0,1) | AA100: =_xlfn.XLOOKUP(Table6[[#This Row],[Old Table.Column]],Cobra8.6[Table.Column],Cobra8.6[LENGTH],"",0,1)
A101: Common | B101: PRODUCT_CONFIG | C101: CREATED_DATE | D101: 8 | E101: TIMESTAMP | F101: =VLOOKUP($E101,'Data Type Lookup'!$A$1:$C$21,2,FALSE) -> TIMESTAMP | I101: Y | P101: Date the Product Config was created. | Q101: createdDate | R101: =VLOOKUP(E101,'Data Type Lookup'!$A$1:$C$21,3,FALSE) -> java.time.Instant | S101: 2 | W101: =_xlfn.CONCAT(B101,".",C101) -> PRODUCT_CONFIG.CREATED_DATE | X101: =VLOOKUP(W101,ColumnMapping[New Table.Column],1,) -> PRODUCT_CONFIG.CREATED_DATE | Y101: =_xlfn.XLOOKUP(Table6[[#This Row],[Table.Column]],ColumnMapping[Add Column Name],ColumnMapping[Old Table.Column],"",0,1) | Z101: =_xlfn.XLOOKUP(Table6[[#This Row],[Old Table.Column]],Cobra8.6[Table.Column],Cobra8.6[TYPE],"",0,1) | AA101: =_xlfn.XLOOKUP(Table6[[#This Row],[Old Table.Column]],Cobra8.6[Table.Column],Cobra8.6[LENGTH],"",0,1)
A102: Common | B102: PRODUCT_CONFIG | C102: LAST_MODIFIED_BY_USER_UID | D102: 9 | E102: GUID | F102: =VLOOKUP($E102,'Data Type Lookup'!$A$1:$C$21,2,FALSE) -> RAW(16) | I102: Y | P102: The User that last changed the Product Config. | Q102: lastModifiedBy | R102: =VLOOKUP(E102,'Data Type Lookup'!$A$1:$C$21,3,FALSE) -> java.util.UUID | S102: 2 | W102: =_xlfn.CONCAT(B102,".",C102) -> PRODUCT_CONFIG.LAST_MODIFIED_BY_USER_UID | X102: =VLOOKUP(W102,ColumnMapping[New Table.Column],1,) -> PRODUCT_CONFIG.LAST_MODIFIED_BY_USER_UID | Y102: =_xlfn.XLOOKUP(Table6[[#This Row],[Table.Column]],ColumnMapping[Add Column Name],ColumnMapping[Old Table.Column],"",0,1) | Z102: =_xlfn.XLOOKUP(Table6[[#This Row],[Old Table.Column]],Cobra8.6[Table.Column],Cobra8.6[TYPE],"",0,1) | AA102: =_xlfn.XLOOKUP(Table6[[#This Row],[Old Table.Column]],Cobra8.6[Table.Column],Cobra8.6[LENGTH],"",0,1)
A103: Common | B103: PRODUCT_CONFIG | C103: LAST_MODIFIED_DATE | D103: 10 | E103: TIMESTAMP | F103: =VLOOKUP($E103,'Data Type Lookup'!$A$1:$C$21,2,FALSE) -> TIMESTAMP | I103: Y | P103: Date the last change was made to the Product Config. | Q103: lastModifiedDate | R103: =VLOOKUP(E103,'Data Type Lookup'!$A$1:$C$21,3,FALSE) -> java.time.Instant | S103: 2 | W103: =_xlfn.CONCAT(B103,".",C103) -> PRODUCT_CONFIG.LAST_MODIFIED_DATE | X103: =VLOOKUP(W103,ColumnMapping[New Table.Column],1,) -> PRODUCT_CONFIG.LAST_MODIFIED_DATE | Y103: =_xlfn.XLOOKUP(Table6[[#This Row],[Table.Column]],ColumnMapping[Add Column Name],ColumnMapping[Old Table.Column],"",0,1) | Z103: =_xlfn.XLOOKUP(Table6[[#This Row],[Old Table.Column]],Cobra8.6[Table.Column],Cobra8.6[TYPE],"",0,1) | AA103: =_xlfn.XLOOKUP(Table6[[#This Row],[Old Table.Column]],Cobra8.6[Table.Column],Cobra8.6[LENGTH],"",0,1)
A104: Common | B104: PRODUCT_CONFIG | C104: DESCRIPTION | D104: 11 | E104: NTEXT | F104: =VLOOKUP($E104,'Data Type Lookup'!$A$1:$C$21,2,FALSE) -> NVARCHAR2 | G104: 256 | P104: Product Setting Description. | Q104: description | R104: =VLOOKUP(E104,'Data Type Lookup'!$A$1:$C$21,3,FALSE) -> String | W104: =_xlfn.CONCAT(B104,".",C104) -> PRODUCT_CONFIG.DESCRIPTION | X104: =VLOOKUP(W104,ColumnMapping[New Table.Column],1,) -> PRODUCT_CONFIG.DESCRIPTION | Y104: =_xlfn.XLOOKUP(Table6[[#This Row],[Table.Column]],ColumnMapping[Add Column Name],ColumnMapping[Old Table.Column],"",0,1) | Z104: =_xlfn.XLOOKUP(Table6[[#This Row],[Old Table.Column]],Cobra8.6[Table.Column],Cobra8.6[TYPE],"",0,1) | AA104: =_xlfn.XLOOKUP(Table6[[#This Row],[Old Table.Column]],Cobra8.6[Table.Column],Cobra8.6[LENGTH],"",0,1)
A105: Common | B105: PRODUCT_CONFIG | C105: DATA | D105: 12 | E105: MEMO | F105: =VLOOKUP($E105,'Data Type Lookup'!$A$1:$C$21,2,FALSE) -> NCLOB | P105: Product Setting data value. | Q105: data | R105: =VLOOKUP(E105,'Data Type Lookup'!$A$1:$C$21,3,FALSE) -> String | W105: =_xlfn.CONCAT(B105,".",C105) -> PRODUCT_CONFIG.DATA | X105: =VLOOKUP(W105,ColumnMapping[New Table.Column],1,) -> PRODUCT_CONFIG.DATA | Y105: =_xlfn.XLOOKUP(Table6[[#This Row],[Table.Column]],ColumnMapping[Add Column Name],ColumnMapping[Old Table.Column],"",0,1) | Z105: =_xlfn.XLOOKUP(Table6[[#This Row],[Old Table.Column]],Cobra8.6[Table.Column],Cobra8.6[TYPE],"",0,1) | AA105: =_xlfn.XLOOKUP(Table6[[#This Row],[Old Table.Column]],Cobra8.6[Table.Column],Cobra8.6[LENGTH],"",0,1)
A106: Common | B106: PRODUCT_PREFERENCE | C106: ROW_UID | D106: 1 | E106: GUID | F106: =VLOOKUP($E106,'Data Type Lookup'!$A$1:$C$21,2,FALSE) -> RAW(16) | I106: Y | K106: Y | P106: Unique Preferences Identifier. | Q106: uid | R106: =VLOOKUP(E106,'Data Type Lookup'!$A$1:$C$21,3,FALSE) -> java.util.UUID | S106: 3 | W106: =_xlfn.CONCAT(B106,".",C106) -> PRODUCT_PREFERENCE.ROW_UID | X106: =VLOOKUP(W106,ColumnMapping[New Table.Column],1,) -> PRODUCT_PREFERENCE.ROW_UID | Y106: =_xlfn.XLOOKUP(Table6[[#This Row],[Table.Column]],ColumnMapping[Add Column Name],ColumnMapping[Old Table.Column],"",0,1) | Z106: =_xlfn.XLOOKUP(Table6[[#This Row],[Old Table.Column]],Cobra8.6[Table.Column],Cobra8.6[TYPE],"",0,1) | AA106: =_xlfn.XLOOKUP(Table6[[#This Row],[Old Table.Column]],Cobra8.6[Table.Column],Cobra8.6[LENGTH],"",0,1)
A107: Common | B107: PRODUCT_PREFERENCE | C107: SEQUENCE | D107: 2 | E107: LONGINT | F107: =VLOOKUP($E107,'Data Type Lookup'!$A$1:$C$21,2,FALSE) -> NUMBER(19,0) | I107: Y | J107: 0 | P107: Concurrency Control Identifier. | Q107: sequence | R107: =VLOOKUP(E107,'Data Type Lookup'!$A$1:$C$21,3,FALSE) -> Long | S107: 3 | W107: =_xlfn.CONCAT(B107,".",C107) -> PRODUCT_PREFERENCE.SEQUENCE | X107: =VLOOKUP(W107,ColumnMapping[New Table.Column],1,) -> PRODUCT_PREFERENCE.SEQUENCE | Y107: =_xlfn.XLOOKUP(Table6[[#This Row],[Table.Column]],ColumnMapping[Add Column Name],ColumnMapping[Old Table.Column],"",0,1) | Z107: =_xlfn.XLOOKUP(Table6[[#This Row],[Old Table.Column]],Cobra8.6[Table.Column],Cobra8.6[TYPE],"",0,1) | AA107: =_xlfn.XLOOKUP(Table6[[#This Row],[Old Table.Column]],Cobra8.6[Table.Column],Cobra8.6[LENGTH],"",0,1)
A108: Common | B108: PRODUCT_PREFERENCE | C108: PRODUCT_ID | D108: 3 | E108: SHORTINT | F108: =VLOOKUP($E108,'Data Type Lookup'!$A$1:$C$21,2,FALSE) -> NUMBER(5,0) | J108: 0 | L108: Y | P108: Product ID that the Product Preference is associate with. 0 If preference is not Product specific. | Q108: productId | R108: =VLOOKUP(E108,'Data Type Lookup'!$A$1:$C$21,3,FALSE) -> Short | V108: For Product Specific Preferences | W108: =_xlfn.CONCAT(B108,".",C108) -> PRODUCT_PREFERENCE.PRODUCT_ID | X108: =VLOOKUP(W108,ColumnMapping[New Table.Column],1,) -> PRODUCT_PREFERENCE.PRODUCT_ID | Y108: =_xlfn.XLOOKUP(Table6[[#This Row],[Table.Column]],ColumnMapping[Add Column Name],ColumnMapping[Old Table.Column],"",0,1) | Z108: =_xlfn.XLOOKUP(Table6[[#This Row],[Old Table.Column]],Cobra8.6[Table.Column],Cobra8.6[TYPE],"",0,1) | AA108: =_xlfn.XLOOKUP(Table6[[#This Row],[Old Table.Column]],Cobra8.6[Table.Column],Cobra8.6[LENGTH],"",0,1)
A109: Common | B109: PRODUCT_PREFERENCE | C109: PRIMARY_ENTITY_UID | D109: 4 | E109: GUID | F109: =VLOOKUP($E109,'Data Type Lookup'!$A$1:$C$21,2,FALSE) -> RAW(16) | L109: Y | P109: Unique Identifier for the Root Parent Entity the Product Preference is associated with. NULL if preference is not associated with a Primary Entity. | Q109: primaryEntityUid | R109: =VLOOKUP(E109,'Data Type Lookup'!$A$1:$C$21,3,FALSE) -> java.util.UUID | S109: 1 | V109: For File Specific Preferences. Foreign Key to the DIRECTORY table. We don't expect to version preferences. | W109: =_xlfn.CONCAT(B109,".",C109) -> PRODUCT_PREFERENCE.PRIMARY_ENTITY_UID | X109: =VLOOKUP(W109,ColumnMapping[New Table.Column],1,) -> PRODUCT_PREFERENCE.PRIMARY_ENTITY_UID | Y109: =_xlfn.XLOOKUP(Table6[[#This Row],[Table.Column]],ColumnMapping[Add Column Name],ColumnMapping[Old Table.Column],"",0,1) | Z109: =_xlfn.XLOOKUP(Table6[[#This Row],[Old Table.Column]],Cobra8.6[Table.Column],Cobra8.6[TYPE],"",0,1) | AA109: =_xlfn.XLOOKUP(Table6[[#This Row],[Old Table.Column]],Cobra8.6[Table.Column],Cobra8.6[LENGTH],"",0,1)
A110: Common | B110: PRODUCT_PREFERENCE | C110: LAST_MODIFIED_BY_USER_UID | D110: 5 | E110: GUID | F110: =VLOOKUP($E110,'Data Type Lookup'!$A$1:$C$21,2,FALSE) -> RAW(16) | L110: Y | P110: User that the Product preference is associated with. NULL if the preference is not User specific. | Q110: user | R110: =VLOOKUP(E110,'Data Type Lookup'!$A$1:$C$21,3,FALSE) -> java.util.UUID | V110: For User Specific Preferences | W110: =_xlfn.CONCAT(B110,".",C110) -> PRODUCT_PREFERENCE.LAST_MODIFIED_BY_USER_UID | X110: =VLOOKUP(W110,ColumnMapping[New Table.Column],1,) -> PRODUCT_PREFERENCE.LAST_MODIFIED_BY_USER_UID | Y110: =_xlfn.XLOOKUP(Table6[[#This Row],[Table.Column]],ColumnMapping[Add Column Name],ColumnMapping[Old Table.Column],"",0,1) | Z110: =_xlfn.XLOOKUP(Table6[[#This Row],[Old Table.Column]],Cobra8.6[Table.Column],Cobra8.6[TYPE],"",0,1) | AA110: =_xlfn.XLOOKUP(Table6[[#This Row],[Old Table.Column]],Cobra8.6[Table.Column],Cobra8.6[LENGTH],"",0,1)
A111: Common | B111: PRODUCT_PREFERENCE | C111: NAME | D111: 6 | E111: TEXT | F111: =VLOOKUP($E111,'Data Type Lookup'!$A$1:$C$21,2,FALSE) -> VARCHAR2 | G111: 60 | I111: Y | L111: Y | P111: Product Preference Name. | Q111: name | R111: =VLOOKUP(E111,'Data Type Lookup'!$A$1:$C$21,3,FALSE) -> String | W111: =_xlfn.CONCAT(B111,".",C111) -> PRODUCT_PREFERENCE.NAME | X111: =VLOOKUP(W111,ColumnMapping[New Table.Column],1,) -> PRODUCT_PREFERENCE.NAME | Y111: =_xlfn.XLOOKUP(Table6[[#This Row],[Table.Column]],ColumnMapping[Add Column Name],ColumnMapping[Old Table.Column],"",0,1) | Z111: =_xlfn.XLOOKUP(Table6[[#This Row],[Old Table.Column]],Cobra8.6[Table.Column],Cobra8.6[TYPE],"",0,1) | AA111: =_xlfn.XLOOKUP(Table6[[#This Row],[Old Table.Column]],Cobra8.6[Table.Column],Cobra8.6[LENGTH],"",0,1)
A112: Common | B112: PRODUCT_PREFERENCE | C112: DATA | D112: 7 | E112: TEXT | F112: =VLOOKUP($E112,'Data Type Lookup'!$A$1:$C$21,2,FALSE) -> VARCHAR2 | G112: 2048 | I112: Y | P112: Product Preference data value. | Q112: data | R112: =VLOOKUP(E112,'Data Type Lookup'!$A$1:$C$21,3,FALSE) -> String | W112: =_xlfn.CONCAT(B112,".",C112) -> PRODUCT_PREFERENCE.DATA | X112: =VLOOKUP(W112,ColumnMapping[New Table.Column],1,) -> PRODUCT_PREFERENCE.DATA | Y112: =_xlfn.XLOOKUP(Table6[[#This Row],[Table.Column]],ColumnMapping[Add Column Name],ColumnMapping[Old Table.Column],"",0,1) | Z112: =_xlfn.XLOOKUP(Table6[[#This Row],[Old Table.Column]],Cobra8.6[Table.Column],Cobra8.6[TYPE],"",0,1) | AA112: =_xlfn.XLOOKUP(Table6[[#This Row],[Old Table.Column]],Cobra8.6[Table.Column],Cobra8.6[LENGTH],"",0,1)
A113: Common | B113: PRODUCT_PREFERENCE | C113: SECURE | D113: 8 | E113: BOOLEAN | F113: =VLOOKUP($E113,'Data Type Lookup'!$A$1:$C$21,2,FALSE) -> NUMBER(1,0) | I113: Y | J113: 0 | P113: Identifies if the Product Preference Value is encrypted. | Q113: secure | R113: =VLOOKUP(E113,'Data Type Lookup'!$A$1:$C$21,3,FALSE) -> Boolean | W113: =_xlfn.CONCAT(B113,".",C113) -> PRODUCT_PREFERENCE.SECURE | X113: =VLOOKUP(W113,ColumnMapping[New Table.Column],1,) -> PRODUCT_PREFERENCE.SECURE | Y113: =_xlfn.XLOOKUP(Table6[[#This Row],[Table.Column]],ColumnMapping[Add Column Name],ColumnMapping[Old Table.Column],"",0,1) | Z113: =_xlfn.XLOOKUP(Table6[[#This Row],[Old Table.Column]],Cobra8.6[Table.Column],Cobra8.6[TYPE],"",0,1) | AA113: =_xlfn.XLOOKUP(Table6[[#This Row],[Old Table.Column]],Cobra8.6[Table.Column],Cobra8.6[LENGTH],"",0,1)
A114: Common | B114: PRODUCT_PREFERENCE | C114: CREATED_DATE | D114: 9 | E114: TIMESTAMP | F114: =VLOOKUP($E114,'Data Type Lookup'!$A$1:$C$21,2,FALSE) -> TIMESTAMP | I114: Y | P114: Date the Product Config was created. | Q114: createdDate | R114: =VLOOKUP(E114,'Data Type Lookup'!$A$1:$C$21,3,FALSE) -> java.time.Instant | S114: 2 | W114: =_xlfn.CONCAT(B114,".",C114) -> PRODUCT_PREFERENCE.CREATED_DATE | X114: =VLOOKUP(W114,ColumnMapping[New Table.Column],1,) -> #N/A | Y114: =_xlfn.XLOOKUP(Table6[[#This Row],[Table.Column]],ColumnMapping[Add Column Name],ColumnMapping[Old Table.Column],"",0,1) | Z114: =_xlfn.XLOOKUP(Table6[[#This Row],[Old Table.Column]],Cobra8.6[Table.Column],Cobra8.6[TYPE],"",0,1) | AA114: =_xlfn.XLOOKUP(Table6[[#This Row],[Old Table.Column]],Cobra8.6[Table.Column],Cobra8.6[LENGTH],"",0,1)
A115: Common | B115: PRODUCT_PREFERENCE | C115: CREATED_BY_USER_UID | D115: 10 | E115: GUID | F115: =VLOOKUP($E115,'Data Type Lookup'!$A$1:$C$21,2,FALSE) -> RAW(16) | I115: Y | P115: The User that created the Product Config. | Q115: createdBy | R115: =VLOOKUP(E115,'Data Type Lookup'!$A$1:$C$21,3,FALSE) -> java.util.UUID | S115: 2 | W115: =_xlfn.CONCAT(B115,".",C115) -> PRODUCT_PREFERENCE.CREATED_BY_USER_UID | X115: =VLOOKUP(W115,ColumnMapping[New Table.Column],1,) -> #N/A | Y115: =_xlfn.XLOOKUP(Table6[[#This Row],[Table.Column]],ColumnMapping[Add Column Name],ColumnMapping[Old Table.Column],"",0,1) | Z115: =_xlfn.XLOOKUP(Table6[[#This Row],[Old Table.Column]],Cobra8.6[Table.Column],Cobra8.6[TYPE],"",0,1) | AA115: =_xlfn.XLOOKUP(Table6[[#This Row],[Old Table.Column]],Cobra8.6[Table.Column],Cobra8.6[LENGTH],"",0,1)
A116: Common | B116: PRODUCT_PREFERENCE | C116: OWNER_USER_UID | D116: 11 | E116: GUID | F116: =VLOOKUP($E116,'Data Type Lookup'!$A$1:$C$21,2,FALSE) -> RAW(16) | P116: The User that owns the Product Config. | Q116: owner | R116: =VLOOKUP(E116,'Data Type Lookup'!$A$1:$C$21,3,FALSE) -> java.util.UUID | W116: =_xlfn.CONCAT(B116,".",C116) -> PRODUCT_PREFERENCE.OWNER_USER_UID | X116: =VLOOKUP(W116,ColumnMapping[New Table.Column],1,) -> #N/A | Y116: =_xlfn.XLOOKUP(Table6[[#This Row],[Table.Column]],ColumnMapping[Add Column Name],ColumnMapping[Old Table.Column],"",0,1) | Z116: =_xlfn.XLOOKUP(Table6[[#This Row],[Old Table.Column]],Cobra8.6[Table.Column],Cobra8.6[TYPE],"",0,1) | AA116: =_xlfn.XLOOKUP(Table6[[#This Row],[Old Table.Column]],Cobra8.6[Table.Column],Cobra8.6[LENGTH],"",0,1)
...

Sheet Data Type Lookup
A1: Dictionary_Type | B1: Oracle_Data_Type | C1: Java Type
A2: BOOL | B2: NUMBER(1,0) | C2: boolean
A3: BOOLEAN | B3: NUMBER(1,0) | C3: Boolean
A4: DATE | B4: DATE | C4: java.time.Instant
A5: DECIMAL | B5: NUMBER(21,6) | C5: java.math.BigDecimal
A6: ENUM | B6: NUMBER(3,0) | C6: enum
A7: GUID | B7: RAW(16) | C7: java.util.UUID
A8: HOURS | B8: NUMBER(6,2) | C8: java.math.BigDecimal | D8: Number length mappings fromhttps://docs.oracle.com/cd/E23095_01/ACI.93/ACIDataWarehouse/html/s0107keytocolumndatatypenames01.html
A9: INTEGER | B9: NUMBER(10,0) | C9: Integer
A10: JSON | B10: NCLOB | C10: String
A11: JSONO | B11: JSON | C11: String | D11: 0 or 1
A12: LONGINT | B12: NUMBER(19,0) | C12: Long | D12: Byte (0-255) Java recommends Short for this.
A13: MEMO | B13: NCLOB | C13: String | D13: Short Integer (-32768 | 32768)
A14: NTEXT | B14: NVARCHAR2 | C14: String | D14: Long Integer (-2147483648 | 2147483648)
A15: NUMBER | B15: NUMBER | C15: java.math.BigDecimal | D15: 64Bit Integer (-9223372036854775808 | 9223372036854775808)
A16: PERCENT | B16: NUMBER(5,2) | C16: java.math.BigDecimal | D16: JSON type for Oracle 21 and later.
A17: RAW | B17: RAW | C17: byte | D17: JSON type for Oracle 20 and earlier.
A18: SHORTINT | B18: NUMBER(5,0) | C18: Short
A19: TEXT | B19: VARCHAR2 | C19: String | D19: Work in Progress
A20: TIMESTAMP | B20: TIMESTAMP | C20: java.time.Instant
A21: TINYINT | B21: NUMBER(3,0) | C21: Short | D21: Allows non-standard length and scale values to be specified.

Sheet Table Flags
A1: FLAG_NAME | B1: FLAG_VALUE | C1: DESCRIPTION
A2: USER_FIELDS | B2: 0x00000001L | C2: Entity Supports User Defined Fields
A3: USER_NOTES | B3: 0x00000002L | C3: Entity Supports User Defined Note Fields
A4: USER_CODES | B4: 0x00000004L | C4: Entity Supports User Defined Code Fields
A5: ACCESS_CONTROL | B5: 0x00000008L | C5: Entity Supports Access Control Entries
A6: CALCULATED_FIELDS | B6: 0x00000010L | C6: Entity Supports User Defined Calculated Fields
A7: USER_VALIDATIONS | B7: 0x00000020L | C7: Entity Supports User Defined Validations

Sheet Column Flags
A1: FLAG_NAME | B1: FLAG_VALUE | C1: DESCRIPTION
A2: HIDDEN | B2: 0x00000001L | C2: Column is not displayed in the UI.
A3: READ_ONLY | B3: 0x00000002L | C3: Column is Read-Only.
A4: ALLOW_NEGATIVE_DURATION | B4: 0x00000004L | C4: Duration column allows Negative Durations.
A5: ALLOW_PERCENT_DURATION | B5: 0x00000008L | C5: Duration Column allows Percentage Durations.
A6: ALLOW_NEGATIVE_PERCENT | B6: 0x00000010L | C6: Percentage column allows Negative Percentage Values.
A7: USER_DEFINED_FIELD | B7: 0x00000020L | C7: Column is a User defined Field Column.
A8: USER_DEFINED_NOTE_FIELD | B8: 0x00000040L | C8: Column is a User defined Note Field Column.
A9: USER_DEFINED_CODE_FIELD | B9: 0x00000080L | C9: Column is a User defined Code Field Column.
A10: CALCULATED_FIELD | B10: 0x00000100L | C10: Column is a Calculated Field Column.

Sheet Cobra 8.5
A1: TABLE_NAME | B1: TABLE_FLAGS | C1: TABLE_TYPE | D1: FLD_NAME | E1: TYPE | F1: LENGTH | G1: SCALE | H1: COL_FLAGS | I1: SYS_NAME | J1: USR_NAME | K1: STRING_ID | L1: FKEY_TABLE | M1: FKEY_FLD_NAME | N1: FKEY_REQUIRED | O1: FKEY_VIRTUAL | P1: Table.Column | Q1: Found In Mapping?
A2: ACCOUNTS | B2: 0 | C2: ACCOUNTS | D2: ACCT | E2: TEXT | F2: 3 | G2: 0 | H2: 0 | K2: 0 | N2: 0 | O2: 0 | P2: =_xlfn.CONCAT(A2,".",D2) -> ACCOUNTS.ACCT | Q2: =VLOOKUP(Cobra8.5[[#This Row],[Table.Column]],ColumnMapping[Old Table.Column],1,) -> ACCOUNTS.ACCT
A3: ACCOUNTS | B3: 0 | C3: ACCOUNTS | D3: ACCTDESC | E3: TEXT | F3: 254 | G3: 0 | H3: 0 | K3: 0 | N3: 0 | O3: 0 | P3: =_xlfn.CONCAT(A3,".",D3) -> ACCOUNTS.ACCTDESC | Q3: =VLOOKUP(Cobra8.5[[#This Row],[Table.Column]],ColumnMapping[Old Table.Column],1,) -> ACCOUNTS.ACCTDESC
A4: ACCOUNTS | B4: 0 | C4: ACCOUNTS | D4: PROGRAM | E4: TEXT | F4: 22 | G4: 0 | H4: 0 | K4: 0 | N4: 0 | O4: 0 | P4: =_xlfn.CONCAT(A4,".",D4) -> ACCOUNTS.PROGRAM | Q4: =VLOOKUP(Cobra8.5[[#This Row],[Table.Column]],ColumnMapping[Old Table.Column],1,) -> ACCOUNTS.PROGRAM
A5: ACCOUNTS | B5: 0 | C5: ACCOUNTS | D5: REQUIRED | E5: INTE | F5: -1 | G5: 0 | H5: 0 | K5: 0 | N5: 0 | O5: 0 | P5: =_xlfn.CONCAT(A5,".",D5) -> ACCOUNTS.REQUIRED | Q5: =VLOOKUP(Cobra8.5[[#This Row],[Table.Column]],ColumnMapping[Old Table.Column],1,) -> ACCOUNTS.REQUIRED
A6: APPBE | B6: 0 | C6: APPBE | D6: CALCFILE | E6: TEXT | F6: 22 | G6: 0 | H6: 0 | K6: 0 | N6: 0 | O6: 0 | P6: =_xlfn.CONCAT(A6,".",D6) -> APPBE.CALCFILE | Q6: =VLOOKUP(Cobra8.5[[#This Row],[Table.Column]],ColumnMapping[Old Table.Column],1,) -> APPBE.CALCFILE
A7: APPBE | B7: 0 | C7: APPBE | D7: CALCORDER | E7: INTE | F7: -1 | G7: 0 | H7: 0 | K7: 0 | N7: 0 | O7: 0 | P7: =_xlfn.CONCAT(A7,".",D7) -> APPBE.CALCORDER | Q7: =VLOOKUP(Cobra8.5[[#This Row],[Table.Column]],ColumnMapping[Old Table.Column],1,) -> APPBE.CALCORDER
A8: APPBE | B8: 0 | C8: APPBE | D8: CECODE | E8: TEXT | F8: 59 | G8: 0 | H8: 0 | K8: 0 | N8: 0 | O8: 0 | P8: =_xlfn.CONCAT(A8,".",D8) -> APPBE.CECODE | Q8: =VLOOKUP(Cobra8.5[[#This Row],[Table.Column]],ColumnMapping[Old Table.Column],1,) -> APPBE.CECODE
A9: APPBE | B9: 0 | C9: APPBE | D9: LASTUPDATE | E9: DATE | F9: -1 | G9: 0 | H9: 0 | K9: 0 | N9: 0 | O9: 0 | P9: =_xlfn.CONCAT(A9,".",D9) -> APPBE.LASTUPDATE | Q9: =VLOOKUP(Cobra8.5[[#This Row],[Table.Column]],ColumnMapping[Old Table.Column],1,) -> APPBE.LASTUPDATE
A10: APPBE | B10: 0 | C10: APPBE | D10: RESULT | E10: TEXT | F10: 10 | G10: 0 | H10: 0 | K10: 0 | N10: 0 | O10: 0 | P10: =_xlfn.CONCAT(A10,".",D10) -> APPBE.RESULT | Q10: =VLOOKUP(Cobra8.5[[#This Row],[Table.Column]],ColumnMapping[Old Table.Column],1,) -> APPBE.RESULT
A11: APPBE | B11: 0 | C11: APPBE | D11: SEQUENCE | E11: INTE | F11: -1 | G11: 0 | H11: 0 | K11: 0 | N11: 0 | O11: 0 | P11: =_xlfn.CONCAT(A11,".",D11) -> APPBE.SEQUENCE | Q11: =VLOOKUP(Cobra8.5[[#This Row],[Table.Column]],ColumnMapping[Old Table.Column],1,) -> APPBE.SEQUENCE
A12: APPBE | B12: 0 | C12: APPBE | D12: USR_ID | E12: TEXT | F12: 20 | G12: 0 | H12: 0 | K12: 0 | N12: 0 | O12: 0 | P12: =_xlfn.CONCAT(A12,".",D12) -> APPBE.USR_ID | Q12: =VLOOKUP(Cobra8.5[[#This Row],[Table.Column]],ColumnMapping[Old Table.Column],1,) -> APPBE.USR_ID
A13: APPBEDTL | B13: 0 | C13: APPBEDTL | D13: CALCFILE | E13: TEXT | F13: 22 | G13: 0 | H13: 0 | K13: 0 | N13: 0 | O13: 0 | P13: =_xlfn.CONCAT(A13,".",D13) -> APPBEDTL.CALCFILE | Q13: =VLOOKUP(Cobra8.5[[#This Row],[Table.Column]],ColumnMapping[Old Table.Column],1,) -> APPBEDTL.CALCFILE
... A272: CALCDETL | B272: 0 | C272: CALCDETL | D272: SEQUENCE | E272: INTE | F272: -1 | G272: 0 | H272: 0 | K272: 0 | N272: 0 | O272: 0 | P272: =_xlfn.CONCAT(A272,".",D272) -> CALCDETL.SEQUENCE | Q272: =VLOOKUP(Cobra8.5[[#This Row],[Table.Column]],ColumnMapping[Old Table.Column],1,) -> CALCDETL.SEQUENCE
A273: CALCDETL | C273: CALCDETL | D273: SORT_CODE | E273: TEXT | F273: 1 | G273: 0 | H273: 0 | K273: 0 | N273: 0 | O273: 0 | P273: =_xlfn.CONCAT(A273,".",D273) -> CALCDETL.SORT_CODE | Q273: =VLOOKUP(Cobra8.5[[#This Row],[Table.Column]],ColumnMapping[Old Table.Column],1,) -> CALCDETL.SORT_CODE
A274: CALCDETL | B274: 0 | C274: CALCDETL | D274: SOURCE1 | E274: TEXT | F274: 10 | G274: 0 | H274: 0 | K274: 0 | N274: 0 | O274: 0 | P274: =_xlfn.CONCAT(A274,".",D274) -> CALCDETL.SOURCE1 | Q274: =VLOOKUP(Cobra8.5[[#This Row],[Table.Column]],ColumnMapping[Old Table.Column],1,) -> #N/A
A275: CALCDETL | B275: 0 | C275: CALCDETL | D275: SOURCE10 | E275: TEXT | F275: 10 | G275: 0 | H275: 0 | K275: 0 | N275: 0 | O275: 0 | P275: =_xlfn.CONCAT(A275,".",D275) -> CALCDETL.SOURCE10 | Q275: =VLOOKUP(Cobra8.5[[#This Row],[Table.Column]],ColumnMapping[Old Table.Column],1,) -> #N/A
A276: CALCDETL | B276: 0 | C276: CALCDETL | D276: SOURCE2 | E276: TEXT | F276: 10 | G276: 0 | H276: 0 | K276: 0 | N276: 0 | O276: 0 | P276: =_xlfn.CONCAT(A276,".",D276) -> CALCDETL.SOURCE2 | Q276: =VLOOKUP(Cobra8.5[[#This Row],[Table.Column]],ColumnMapping[Old Table.Column],1,) -> #N/A
A277: CALCDETL | B277: 0 | C277: CALCDETL | D277: SOURCE3 | E277: TEXT | F277: 10 | G277: 0 | H277: 0 | K277: 0 | N277: 0 | O277: 0 | P277: =_xlfn.CONCAT(A277,".",D277) -> CALCDETL.SOURCE3 | Q277: =VLOOKUP(Cobra8.5[[#This Row],[Table.Column]],ColumnMapping[Old Table.Column],1,) -> #N/A
A278: CALCDETL | B278: 0 | C278: CALCDETL | D278: SOURCE4 | E278: TEXT | F278: 10 | G278: 0 | H278: 0 | K278: 0 | N278: 0 | O278: 0 | P278: =_xlfn.CONCAT(A278,".",D278) -> CALCDETL.SOURCE4 | Q278: =VLOOKUP(Cobra8.5[[#This Row],[Table.Column]],ColumnMapping[Old Table.Column],1,) -> #N/A
A279: CALCDETL | B279: 0 | C279: CALCDETL | D279: SOURCE5 | E279: TEXT | F279: 10 | G279: 0 | H279: 0 | K279: 0 | N279: 0 | O279: 0 | P279: =_xlfn.CONCAT(A279,".",D279) -> CALCDETL.SOURCE5 | Q279: =VLOOKUP(Cobra8.5[[#This Row],[Table.Column]],ColumnMapping[Old Table.Column],1,) -> #N/A
A280: CALCDETL | B280: 0 | C280: CALCDETL | D280: SOURCE6 | E280: TEXT | F280: 10 | G280: 0 | H280: 0 | K280: 0 | N280: 0 | O280: 0 | P280: =_xlfn.CONCAT(A280,".",D280) -> CALCDETL.SOURCE6 | Q280: =VLOOKUP(Cobra8.5[[#This Row],[Table.Column]],ColumnMapping[Old Table.Column],1,) -> #N/A
A281: CALCDETL | B281: 0 | C281: CALCDETL | D281: SOURCE7 | E281: TEXT | F281: 10 | G281: 0 | H281: 0 | K281: 0 | N281: 0 | O281: 0 | P281: =_xlfn.CONCAT(A281,".",D281) -> CALCDETL.SOURCE7 | Q281: =VLOOKUP(Cobra8.5[[#This Row],[Table.Column]],ColumnMapping[Old Table.Column],1,) -> #N/A
A282: CALCDETL | B282: 0 | C282: CALCDETL | D282: SOURCE8 | E282: TEXT | F282: 10 | G282: 0 | H282: 0 | K282: 0 | N282: 0 | O282: 0 | P282: =_xlfn.CONCAT(A282,".",D282) -> CALCDETL.SOURCE8 | Q282: =VLOOKUP(Cobra8.5[[#This Row],[Table.Column]],ColumnMapping[Old Table.Column],1,) -> #N/A
A283: CALCDETL | B283: 0 | C283: CALCDETL | D283: SOURCE9 | E283: TEXT | F283: 10 | G283: 0 | H283: 0 | K283: 0 | N283: 0 | O283: 0 | P283: =_xlfn.CONCAT(A283,".",D283) -> CALCDETL.SOURCE9 | Q283: =VLOOKUP(Cobra8.5[[#This Row],[Table.Column]],ColumnMapping[Old Table.Column],1,) -> #N/A
A284: CALCDETL | B284: 0 | C284: CALCDETL | D284: UNITS | E284: TEXT | F284: 10 | G284: 0 | H284: 0 | K284: 0 | N284: 0 | O284: 0 | P284: =_xlfn.CONCAT(A284,".",D284) -> CALCDETL.UNITS | Q284: =VLOOKUP(Cobra8.5[[#This Row],[Table.Column]],ColumnMapping[Old Table.Column],1,) -> CALCDETL.UNITS
A285: CALCDETL | B285: 0 | C285: CALCDETL | D285: USR_ID | E285: TEXT | F285: 20 | G285: 0 | H285: 0 | K285: 0 | N285: 0 | O285: 0 | P285: =_xlfn.CONCAT(A285,".",D285) -> CALCDETL.USR_ID | Q285: =VLOOKUP(Cobra8.5[[#This Row],[Table.Column]],ColumnMapping[Old Table.Column],1,) -> CALCDETL.USR_ID
... A952: WST_CDR | B952: 7 | C952: CDR | D952: DESCRIPTION | E952: TEXT | F952: 125 | G952: 0 | H952: 0 | K952: 30245 | N952: 0 | O952: 0 | P952: =_xlfn.CONCAT(A952,".",D952) -> WST_CDR.DESCRIPTION | Q952: =VLOOKUP(Cobra8.5[[#This Row],[Table.Column]],ColumnMapping[Old Table.Column],1,) -> #N/A
A953: WST_CDR | B953: 7 | C953: CDR | D953: DIR_UID | E953: GUID | F953: 22 | G953: 0 | H953: 0 | K953: 712 | L953: COD | M953: DIR_UID | N953: 1 | O953: 0 | P953: =_xlfn.CONCAT(A953,".",D953) -> WST_CDR.DIR_UID | Q953: =VLOOKUP(Cobra8.5[[#This Row],[Table.Column]],ColumnMapping[Old Table.Column],1,) -> #N/A
A954: WST_CDR | B954: 7 | C954: CDR | D954: INTEGRATION_ID | E954: INTE | F954: 10 | G954: 0 | H954: 0 | K954: 31947 | N954: 0 | O954: 0 | P954: =_xlfn.CONCAT(A954,".",D954) -> WST_CDR.INTEGRATION_ID | Q954: =VLOOKUP(Cobra8.5[[#This Row],[Table.Column]],ColumnMapping[Old Table.Column],1,) -> #N/A
A955: WST_CDR | B955: 7 | C955: CDR | D955: LASTUPDATE | E955: DATE | F955: 20 | G955: 0 | H955: 131072 | K955: 30460 | N955: 0 | O955: 0 | P955: =_xlfn.CONCAT(A955,".",D955) -> WST_CDR.LASTUPDATE | Q955: =VLOOKUP(Cobra8.5[[#This Row],[Table.Column]],ColumnMapping[Old Table.Column],1,) -> #N/A
A956: WST_CDR | B956: 7 | C956: CDR | D956: POSITION_NUM | E956: INTE | F956: 8 | G956: 0 | H956: 0 | K956: 30248 | N956: 0 | O956: 0 | P956: =_xlfn.CONCAT(A956,".",D956) -> WST_CDR.POSITION_NUM | Q956: =VLOOKUP(Cobra8.5[[#This Row],[Table.Column]],ColumnMapping[Old Table.Column],1,) -> #N/A
A957: WST_CDR | B957: 7 | C957: CDR | D957: SEQUENCE | E957: INTE | F957: 4 | G957: 0 | H957: 196608 | K957: 30042 | N957: 0 | O957: 0 | P957: =_xlfn.CONCAT(A957,".",D957) -> WST_CDR.SEQUENCE | Q957: =VLOOKUP(Cobra8.5[[#This Row],[Table.Column]],ColumnMapping[Old Table.Column],1,) -> #N/A
A958: WST_CDR | B958: 7 | C958: CDR | D958: SUPPRESS | E958: BOOL | F958: 4 | G958: 0 | H958: 0 | K958: 30332 | N958: 0 | O958: 0 | P958: =_xlfn.CONCAT(A958,".",D958) -> WST_CDR.SUPPRESS | Q958: =VLOOKUP(Cobra8.5[[#This Row],[Table.Column]],ColumnMapping[Old Table.Column],1,) -> #N/A
A959: WST_CDR | B959: 7 | C959: CDR | D959: USR_ID | E959: TEXT | F959: 20 | G959: 0 | H959: 131072 | K959: 30451 | N959: 0 | O959: 0 | P959: =_xlfn.CONCAT(A959,".",D959) -> WST_CDR.USR_ID | Q959: =VLOOKUP(Cobra8.5[[#This Row],[Table.Column]],ColumnMapping[Old Table.Column],1,) -> #N/A
A960: WST_CFG | B960: 2 | C960: CFG | D960: CFG_ID | E960: TEXT | F960: 60 | G960: 0 | H960: 0 | K960: 0 | N960: 0 | O960: 0 | P960: =_xlfn.CONCAT(A960,".",D960) -> WST_CFG.CFG_ID | Q960: =VLOOKUP(Cobra8.5[[#This Row],[Table.Column]],ColumnMapping[Old Table.Column],1,) -> #N/A
A961: WST_CFG | B961: 2 | C961: CFG | D961: CFG_TYPE | E961: TEXT | F961: 30 | G961: 0 | H961: 0 | K961: 0 | N961: 0 | O961: 0 | P961: =_xlfn.CONCAT(A961,".",D961) -> WST_CFG.CFG_TYPE | Q961: =VLOOKUP(Cobra8.5[[#This Row],[Table.Column]],ColumnMapping[Old Table.Column],1,) -> #N/A
A962: WST_CFG | B962: 2 | C962: CFG | D962: CFG_UID | E962: GUID | F962: 22 | G962: 0 | H962: 0 | K962: 0 | N962: 0 | O962: 0 | P962: =_xlfn.CONCAT(A962,".",D962) -> WST_CFG.CFG_UID | Q962: =VLOOKUP(Cobra8.5[[#This Row],[Table.Column]],ColumnMapping[Old Table.Column],1,) -> #N/A
A963: WST_CFG | B963: 2 | C963: CFG | D963: DATA | E963: TEXT | F963: 8192 | G963: 0 | H963: 0 | K963: 0 | N963: 0 | O963: 0 | P963: =_xlfn.CONCAT(A963,".",D963) -> WST_CFG.DATA | Q963: =VLOOKUP(Cobra8.5[[#This Row],[Table.Column]],ColumnMapping[Old Table.Column],1,) -> #N/A
A964: WST_CFG | B964: 2 | C964: CFG | D964: DESCRIPTION | E964: TEXT | F964: 254 | G964: 0 | H964: 0 | K964: 0 | N964: 0 | O964: 0 | P964: =_xlfn.CONCAT(A964,".",D964) -> WST_CFG.DESCRIPTION | Q964: =VLOOKUP(Cobra8.5[[#This Row],[Table.Column]],ColumnMapping[Old Table.Column],1,) -> #N/A
A965: WST_CFG | B965: 2 | C965: CFG | D965: LASTUPDATE | E965: DATE | F965: 20 | G965: 0 | H965: 131072 | K965: 30460 | N965: 0 | O965: 0 | P965: =_xlfn.CONCAT(A965,".",D965) -> WST_CFG.LASTUPDATE | Q965: =VLOOKUP(Cobra8.5[[#This Row],[Table.Column]],ColumnMapping[Old Table.Column],1,) -> #N/A
... A970: WST_COD | B970: 7 | C970: COD | D970: DATA | E970: TEXT | F970: 60 | G970: 0 | H970: 0 | K970: 30512 | N970: 0 | O970: 0 | P970: =_xlfn.CONCAT(A970,".",D970) -> WST_COD.DATA | Q970: =VLOOKUP(Cobra8.5[[#This Row],[Table.Column]],ColumnMapping[Old Table.Column],1,) -> #N/A
A971: WST_COD | B971: 7 | C971: COD | D971: DIR_UID | E971: GUID | F971: 22 | G971: 0 | H971: 0 | K971: 0 | L971: 0 | M971: DIR_UID | N971: 1 | O971: 0 | P971: =_xlfn.CONCAT(A971,".",D971) -> WST_COD.DIR_UID | Q971: =VLOOKUP(Cobra8.5[[#This Row],[Table.Column]],ColumnMapping[Old Table.Column],1,) -> #N/A
A972: WST_COD | B972: 7 | C972: COD | D972: PROMPT_TEXT | E972: TEXT | F972: 20 | G972: 0 | H972: 0 | K972: 30511 | N972: 0 | O972: 0 | P972: =_xlfn.CONCAT(A972,".",D972) -> WST_COD.PROMPT_TEXT | Q972: =VLOOKUP(Cobra8.5[[#This Row],[Table.Column]],ColumnMapping[Old Table.Column],1,) -> #N/A
A973: WST_COD | B973: 7 | C973: COD | D973: STARTVIEW | E973: TEXT | F973: 20 | G973: 0 | H973: 0 | K973: 31505 | N973: 0 | O973: 0 | P973: =_xlfn.CONCAT(A973,".",D973) -> WST_COD.STARTVIEW | Q973: =VLOOKUP(Cobra8.5[[#This Row],[Table.Column]],ColumnMapping[Old Table.Column],1,) -> #N/A
A974: WST_COD | B974: 7 | C974: COD | D974: TH_FLAGS | E974: TEXT | F974: 10 | G974: 0 | H974: 0 | K974: 30513 | N974: 0 | O974: 0 | P974: =_xlfn.CONCAT(A974,".",D974) -> WST_COD.TH_FLAGS | Q974: =VLOOKUP(Cobra8.5[[#This Row],[Table.Column]],ColumnMapping[Old Table.Column],1,) -> #N/A
A975: WST_DIR | B975: 0 | C975: DIR | D975: DESCRIPTION | E975: TEXT | F975: 125 | G975: 0 | H975: 0 | K975: 30525 | N975: 0 | O975: 0 | P975: =_xlfn.CONCAT(A975,".",D975) -> WST_DIR.DESCRIPTION | Q975: =VLOOKUP(Cobra8.5[[#This Row],[Table.Column]],ColumnMapping[Old Table.Column],1,) -> #N/A
A976: WST_DIR | B976: 0 | C976: DIR | D976: DIR_ID | E976: TEXT | F976: 22 | G976: 0 | H976: 0 | K976: 30527 | N976: 0 | O976: 0 | P976: =_xlfn.CONCAT(A976,".",D976) -> WST_DIR.DIR_ID | Q976: =VLOOKUP(Cobra8.5[[#This Row],[Table.Column]],ColumnMapping[Old Table.Column],1,) -> #N/A
A977: WST_DIR | B977: 0 | C977: DIR | D977: DIR_UID | E977: GUID | F977: 22 | G977: 0 | H977: 0 | K977: 0 | N977: 0 | O977: 0 | P977: =_xlfn.CONCAT(A977,".",D977) -> WST_DIR.DIR_UID | Q977: =VLOOKUP(Cobra8.5[[#This Row],[Table.Column]],ColumnMapping[Old Table.Column],1,) -> #N/A
A978: WST_DIR | B978: 0 | C978: DIR | D978: LASTUPDATE | E978: DATE | F978: 20 | G978: 0 | H978: 131072 | K978: 30460 | N978: 0 | O978: 0 | P978: =_xlfn.CONCAT(A978,".",D978) -> WST_DIR.LASTUPDATE | Q978: =VLOOKUP(Cobra8.5[[#This Row],[Table.Column]],ColumnMapping[Old Table.Column],1,) -> #N/A
A979: WST_DIR | B979: 0 | C979: DIR | D979: OPENMODE | E979: TEXT | F979: 1 | G979: 0 | H979: 0 | K979: 30528 | N979: 0 | O979: 0 | P979: =_xlfn.CONCAT(A979,".",D979) -> WST_DIR.OPENMODE | Q979: =VLOOKUP(Cobra8.5[[#This Row],[Table.Column]],ColumnMapping[Old Table.Column],1,) -> #N/A
A980: WST_DIR | B980: 0 | C980: DIR | D980: OWNER_ID | E980: TEXT | F980: 20 | G980: 0 | H980: 131072 | K980: 30452 | N980: 0 | O980: 0 | P980: =_xlfn.CONCAT(A980,".",D980) -> WST_DIR.OWNER_ID | Q980: =VLOOKUP(Cobra8.5[[#This Row],[Table.Column]],ColumnMapping[Old Table.Column],1,) -> #N/A
A981: WST_DIR | B981: 0 | C981: DIR | D981: SEQUENCE | E981: INTE | F981: 4 | G981: 0 | H981: 196608 | K981: 30042 | N981: 0 | O981: 0 | P981: =_xlfn.CONCAT(A981,".",D981) -> WST_DIR.SEQUENCE | Q981: =VLOOKUP(Cobra8.5[[#This Row],[Table.Column]],ColumnMapping[Old Table.Column],1,) -> #N/A
A982: WST_DIR | B982: 0 | C982: DIR | D982: TABLE_TYPE | E982: TEXT | F982: 30 | G982: 0 | H982: 0 | K982: 30526 | N982: 0 | O982: 0 | P982: =_xlfn.CONCAT(A982,".",D982) -> WST_DIR.TABLE_TYPE | Q982: =VLOOKUP(Cobra8.5[[#This Row],[Table.Column]],ColumnMapping[Old Table.Column],1,) -> #N/A
A983: WST_DIR | B983: 0 | C983: DIR | D983: USR_ID | E983: TEXT | F983: 20 | G983: 0 | H983: 131072 | K983: 30451 | N983: 0 | O983: 0 | P983: =_xlfn.CONCAT(A983,".",D983) -> WST_DIR.USR_ID | Q983: =VLOOKUP(Cobra8.5[[#This Row],[Table.Column]],ColumnMapping[Old Table.Column],1,) -> #N/A
... A997: WST_LCK | B997: 32 | C997: LCK | D997: USR_ID | E997: TEXT | F997: 20 | G997: 0 | H997: 131072 | K997: 30451 | N997: 0 | O997: 0 | P997: =_xlfn.CONCAT(A997,".",D997) -> WST_LCK.USR_ID | Q997: =VLOOKUP(Cobra8.5[[#This Row],[Table.Column]],ColumnMapping[Old Table.Column],1,) -> WST_LCK.USR_ID
A998: WST_NTX | B998: 0 | C998: NTX | D998: DIR_UID | E998: GUID | F998: 22 | G998: 0 | H998: 0 | K998: 0 | L998: 0 | M998: DIR_UID | N998: 0 | O998: 0 | P998: =_xlfn.CONCAT(A998,".",D998) -> WST_NTX.DIR_UID | Q998: =VLOOKUP(Cobra8.5[[#This Row],[Table.Column]],ColumnMapping[Old Table.Column],1,) -> #N/A
A999: WST_NTX | B999: 0 | C999: NTX | D999: FIELD_NAME | E999: TEXT | F999: 60 | G999: 0 | H999: 0 | K999: 0 | N999: 0 | O999: 0 | P999: =_xlfn.CONCAT(A999,".",D999) -> WST_NTX.FIELD_NAME | Q999: =VLOOKUP(Cobra8.5[[#This Row],[Table.Column]],ColumnMapping[Old Table.Column],1,) -> #N/A
A1000: WST_NTX | B1000: 0 | C1000: NTX | D1000: FIELD_VALUE | E1000: MEMO | F1000: 32768 | G1000: 0 | H1000: 0 | K1000: 0 | N1000: 0 | O1000: 0 | P1000: =_xlfn.CONCAT(A1000,".",D1000) -> WST_NTX.FIELD_VALUE | Q1000: =VLOOKUP(Cobra8.5[[#This Row],[Table.Column]],ColumnMapping[Old Table.Column],1,) -> #N/A
A1001: WST_NTX | B1001: 0 | C1001: NTX | D1001: FK_UID | E1001: GUID | F1001: 22 | G1001: 0 | H1001: 0 | K1001: 0 | L1001: 0 | M1001: 0 | N1001: 0 | O1001: 0 | P1001: =_xlfn.CONCAT(A1001,".",D1001) -> WST_NTX.FK_UID | Q1001: =VLOOKUP(Cobra8.5[[#This Row],[Table.Column]],ColumnMapping[Old Table.Column],1,) -> #N/A
A1002: WST_NTX | B1002: 0 | C1002: NTX | D1002: ROW_UID | E1002: GUID | F1002: 22 | G1002: 0 | H1002: 0 | K1002: 0 | N1002: 0 | O1002: 0 | P1002: =_xlfn.CONCAT(A1002,".",D1002) -> WST_NTX.ROW_UID | Q1002: =VLOOKUP(Cobra8.5[[#This Row],[Table.Column]],ColumnMapping[Old Table.Column],1,) -> #N/A
A1003: WST_NTX | B1003: 0 | C1003: NTX | D1003: TABLE_TYPE | E1003: TEXT | F1003: 30 | G1003: 0 | H1003: 0 | K1003: 30526 | N1003: 0 | O1003: 0 | P1003: =_xlfn.CONCAT(A1003,".",D1003) -> WST_NTX.TABLE_TYPE | Q1003: =VLOOKUP(Cobra8.5[[#This Row],[Table.Column]],ColumnMapping[Old Table.Column],1,) -> #N/A
A1004: WST_ROL | B1004: 2 | C1004: ROL | D1004: DESCRIPTION | E1004: TEXT | F1004: 60 | G1004: 0 | H1004: 0 | K1004: 30525 | N1004: 0 | O1004: 0 | P1004: =_xlfn.CONCAT(A1004,".",D1004) -> WST_ROL.DESCRIPTION | Q1004: =VLOOKUP(Cobra8.5[[#This Row],[Table.Column]],ColumnMapping[Old Table.Column],1,) -> #N/A
A1005: WST_ROL | B1005: 2 | C1005: ROL | D1005: MANAGER | E1005: TEXT | F1005: 20 | G1005: 0 | H1005: 0 | K1005: 0 | N1005: 0 | O1005: 0 | P1005: =_xlfn.CONCAT(A1005,".",D1005) -> WST_ROL.MANAGER | Q1005: =VLOOKUP(Cobra8.5[[#This Row],[Table.Column]],ColumnMapping[Old Table.Column],1,) -> #N/A
A1006: WST_ROL | B1006: 2 | C1006: ROL | D1006: ROL_ID | E1006: TEXT | F1006: 20 | G1006: 0 | H1006: 0 | K1006: 0 | N1006: 0 | O1006: 0 | P1006: =_xlfn.CONCAT(A1006,".",D1006) -> WST_ROL.ROL_ID | Q1006: =VLOOKUP(Cobra8.5[[#This Row],[Table.Column]],ColumnMapping[Old Table.Column],1,) -> #N/A
A1007: WST_UDF | B1007: 0 | C1007: UDF | D1007: DESCRIPTION | E1007: TEXT | F1007: 60 | G1007: 0 | H1007: 0 | K1007: 30525 | N1007: 0 | O1007: 0 | P1007: =_xlfn.CONCAT(A1007,".",D1007) -> WST_UDF.DESCRIPTION | Q1007: =VLOOKUP(Cobra8.5[[#This Row],[Table.Column]],ColumnMapping[Old Table.Column],1,) -> WST_UDF.DESCRIPTION
A1008: WST_UDF | B1008: 0 | C1008: UDF | D1008: FIELD_NAME | E1008: TEXT | F1008: 60 | G1008: 0 | H1008: 0 | K1008: 0 | N1008: 0 | O1008: 0 | P1008: =_xlfn.CONCAT(A1008,".",D1008) -> WST_UDF.FIELD_NAME | Q1008: =VLOOKUP(Cobra8.5[[#This Row],[Table.Column]],ColumnMapping[Old Table.Column],1,) -> #N/A
A1009: WST_UDF | B1009: 0 | C1009: UDF | D1009: FIELD_TYPE | E1009: TEXT | F1009: 4 | G1009: 0 | H1009: 0 | K1009: 0 | N1009: 0 | O1009: 0 | P1009: =_xlfn.CONCAT(A1009,".",D1009) -> WST_UDF.FIELD_TYPE | Q1009: =VLOOKUP(Cobra8.5[[#This Row],[Table.Column]],ColumnMapping[Old Table.Column],1,) -> WST_UDF.FIELD_TYPE
A1010: WST_UDF | B1010: 0 | C1010: UDF | D1010: LOOKUP_FIELD | E1010: TEXT | F1010: 30 | G1010: 0 | H1010: 0 | K1010: 0 | N1010: 0 | O1010: 0 | P1010: =_xlfn.CONCAT(A1010,".",D1010) -> WST_UDF.LOOKUP_FIELD | Q1010: =VLOOKUP(Cobra8.5[[#This Row],[Table.Column]],ColumnMapping[Old Table.Column],1,) -> WST_UDF.LOOKUP_FIELD
A1011: WST_UDF | B1011: 0 | C1011: UDF | D1011: LOOKUP_TABLE_NAME | E1011: TEXT | F1011: 30 | G1011: 0 | H1011: 0 | K1011: 0 | N1011: 0 | O1011: 0 | P1011: =_xlfn.CONCAT(A1011,".",D1011) -> WST_UDF.LOOKUP_TABLE_NAME | Q1011: =VLOOKUP(Cobra8.5[[#This Row],[Table.Column]],ColumnMapping[Old Table.Column],1,) -> WST_UDF.LOOKUP_TABLE_NAME
A1012: WST_UDF | B1012: 0 | C1012: UDF | D1012: LOOKUP_TABLE_TYPE | E1012: TEXT | F1012: 30 | G1012: 0 | H1012: 0 | K1012: 0 | N1012: 0 | O1012: 0 | P1012: =_xlfn.CONCAT(A1012,".",D1012) -> WST_UDF.LOOKUP_TABLE_TYPE | Q1012: =VLOOKUP(Cobra8.5[[#This Row],[Table.Column]],ColumnMapping[Old Table.Column],1,) -> WST_UDF.LOOKUP_TABLE_TYPE
A1013: WST_UDF | B1013: 0 | C1013: UDF | D1013: SEQUENCE | E1013: INTE | F1013: 4 | G1013: 0 | H1013: 196608 | K1013: 30042 | N1013: 0 | O1013: 0 | P1013: =_xlfn.CONCAT(A1013,".",D1013) -> WST_UDF.SEQUENCE | Q1013: =VLOOKUP(Cobra8.5[[#This Row],[Table.Column]],ColumnMapping[Old Table.Column],1,) -> #N/A
... A1015: WST_UDF | B1015: 0 | C1015: UDF | D1015: UDF_UID | E1015: GUID | F1015: 22 | G1015: 0 | H1015: 0 | K1015: 0 | N1015: 0 | O1015: 0 | P1015: =_xlfn.CONCAT(A1015,".",D1015) -> WST_UDF.UDF_UID | Q1015: =VLOOKUP(Cobra8.5[[#This Row],[Table.Column]],ColumnMapping[Old Table.Column],1,) -> #N/A
A1016: WST_UDT | B1016: 0 | C1016: UDT | D1016: DIR_UID | E1016: GUID | F1016: 22 | G1016: 0 | H1016: 0 | K1016: 0 | L1016: 0 | M1016: DIR_UID | N1016: 1 | O1016: 0 | P1016: =_xlfn.CONCAT(A1016,".",D1016) -> WST_UDT.DIR_UID | Q1016: =VLOOKUP(Cobra8.5[[#This Row],[Table.Column]],ColumnMapping[Old Table.Column],1,) -> #N/A
A1017: WST_UDT | B1017: 0 | C1017: UDT | D1017: FIELD_NAME | E1017: TEXT | F1017: 60 | G1017: 0 | H1017: 0 | K1017: 0 | N1017: 0 | O1017: 0 | P1017: =_xlfn.CONCAT(A1017,".",D1017) -> WST_UDT.FIELD_NAME | Q1017: =VLOOKUP(Cobra8.5[[#This Row],[Table.Column]],ColumnMapping[Old Table.Column],1,) -> #N/A
A1018: WST_UDT | B1018: 0 | C1018: UDT | D1018: FIELD_VALUE | E1018: DATE | F1018: 20 | G1018: 0 | H1018: 0 | K1018: 0 | N1018: 0 | O1018: 0 | P1018: =_xlfn.CONCAT(A1018,".",D1018) -> WST_UDT.FIELD_VALUE | Q1018: =VLOOKUP(Cobra8.5[[#This Row],[Table.Column]],ColumnMapping[Old Table.Column],1,) -> #N/A
A1019: WST_UDT | B1019: 0 | C1019: UDT | D1019: FK_UID | E1019: GUID | F1019: 22 | G1019: 0 | H1019: 0 | K1019: 0 | L1019: 0 | M1019: 0 | N1019: 0 | O1019: 0 | P1019: =_xlfn.CONCAT(A1019,".",D1019) -> WST_UDT.FK_UID | Q1019: =VLOOKUP(Cobra8.5[[#This Row],[Table.Column]],ColumnMapping[Old Table.Column],1,) -> #N/A
A1020: WST_UDT | B1020: 0 | C1020: UDT | D1020: ROW_UID | E1020: GUID | F1020: 22 | G1020: 0 | H1020: 0 | K1020: 0 | N1020: 0 | O1020: 0 | P1020: =_xlfn.CONCAT(A1020,".",D1020) -> WST_UDT.ROW_UID | Q1020: =VLOOKUP(Cobra8.5[[#This Row],[Table.Column]],ColumnMapping[Old Table.Column],1,) -> #N/A
A1021: WST_UDT | B1021: 0 | C1021: UDT | D1021: TABLE_TYPE | E1021: TEXT | F1021: 30 | G1021: 0 | H1021: 0 | K1021: 30526 | N1021: 0 | O1021: 0 | P1021: =_xlfn.CONCAT(A1021,".",D1021) -> WST_UDT.TABLE_TYPE | Q1021: =VLOOKUP(Cobra8.5[[#This Row],[Table.Column]],ColumnMapping[Old Table.Column],1,) -> #N/A
A1022: WST_UDU | B1022: 0 | C1022: UDU | D1022: DIR_UID | E1022: GUID | F1022: 22 | G1022: 0 | H1022: 0 | K1022: 0 | L1022: 0 | M1022: DIR_UID | N1022: 1 | O1022: 0 | P1022: =_xlfn.CONCAT(A1022,".",D1022) -> WST_UDU.DIR_UID | Q1022: =VLOOKUP(Cobra8.5[[#This Row],[Table.Column]],ColumnMapping[Old Table.Column],1,) -> #N/A
A1023: WST_UDU | B1023: 0 | C1023: UDU | D1023: FIELD_NAME | E1023: TEXT | F1023: 60 | G1023: 0 | H1023: 0 | K1023: 0 | N1023: 0 | O1023: 0 | P1023: =_xlfn.CONCAT(A1023,".",D1023) -> WST_UDU.FIELD_NAME | Q1023: =VLOOKUP(Cobra8.5[[#This Row],[Table.Column]],ColumnMapping[Old Table.Column],1,) -> #N/A
A1024: WST_UDU | B1024: 0 | C1024: UDU | D1024: FIELD_VALUE | E1024: DURA | F1024: 8 | G1024: 0 | H1024: 0 | K1024: 0 | N1024: 0 | O1024: 0 | P1024: =_xlfn.CONCAT(A1024,".",D1024) -> WST_UDU.FIELD_VALUE | Q1024: =VLOOKUP(Cobra8.5[[#This Row],[Table.Column]],ColumnMapping[Old Table.Column],1,) -> #N/A
A1025: WST_UDU | B1025: 0 | C1025: UDU | D1025: FK_UID | E1025: GUID | F1025: 22 | G1025: 0 | H1025: 0 | K1025: 0 | L1025: 0 | M1025: 0 | N1025: 0 | O1025: 0 | P1025: =_xlfn.CONCAT(A1025,".",D1025) -> WST_UDU.FK_UID | Q1025: =VLOOKUP(Cobra8.5[[#This Row],[Table.Column]],ColumnMapping[Old Table.Column],1,) -> #N/A
A1026: WST_UDU | B1026: 0 | C1026: UDU | D1026: ROW_UID | E1026: GUID | F1026: 22 | G1026: 0 | H1026: 0 | K1026: 0 | N1026: 0 | O1026: 0 | P1026: =_xlfn.CONCAT(A1026,".",D1026) -> WST_UDU.ROW_UID | Q1026: =VLOOKUP(Cobra8.5[[#This Row],[Table.Column]],ColumnMapping[Old Table.Column],1,) -> #N/A
A1027: WST_UDU | B1027: 0 | C1027: UDU | D1027: TABLE_TYPE | E1027: TEXT | F1027: 30 | G1027: 0 | H1027: 0 | K1027: 30526 | N1027: 0 | O1027: 0 | P1027: =_xlfn.CONCAT(A1027,".",D1027) -> WST_UDU.TABLE_TYPE | Q1027: =VLOOKUP(Cobra8.5[[#This Row],[Table.Column]],ColumnMapping[Old Table.Column],1,) -> #N/A
A1028: WST_ULI | B1028: 0 | C1028: ULI | D1028: LICENSEREVOKED | E1028: INTE | F1028: 4 | G1028: 0 | H1028: 0 | K1028: 0 | N1028: 0 | O1028: 0 | P1028: =_xlfn.CONCAT(A1028,".",D1028) -> WST_ULI.LICENSEREVOKED | Q1028: =VLOOKUP(Cobra8.5[[#This Row],[Table.Column]],ColumnMapping[Old Table.Column],1,) -> #N/A
A1029: WST_ULI | B1029: 0 | C1029: ULI | D1029: LOGINTIME | E1029: DATE | F1029: 8 | G1029: 0 | H1029: 0 | K1029: 12418 | N1029: 0 | O1029: 0 | P1029: =_xlfn.CONCAT(A1029,".",D1029) -> WST_ULI.LOGINTIME | Q1029: =VLOOKUP(Cobra8.5[[#This Row],[Table.Column]],ColumnMapping[Old Table.Column],1,) -> #N/A
A1030: WST_ULI | B1030: 0 | C1030: ULI | D1030: MACHINE_ID | E1030: TEXT | F1030: 48 | G1030: 0 | H1030: 0 | K1030: 5085 | N1030: 0 | O1030: 0 | P1030: =_xlfn.CONCAT(A1030,".",D1030) -> WST_ULI.MACHINE_ID | Q1030: =VLOOKUP(Cobra8.5[[#This Row],[Table.Column]],ColumnMapping[Old Table.Column],1,) -> #N/A
A1031: WST_ULI | B1031: 0 | C1031: ULI | D1031: PRD_UID | E1031: INTE | F1031: 4 | G1031: 0 | H1031: 0 | K1031: 15032 | N1031: 0 | O1031: 0 | P1031: =_xlfn.CONCAT(A1031,".",D1031) -> WST_ULI.PRD_UID | Q1031: =VLOOKUP(Cobra8.5[[#This Row],[Table.Column]],ColumnMapping[Old Table.Column],1,) -> #N/A
A1032: WST_ULI | B1032: 0 | C1032: ULI | D1032: ULI_UID | E1032: GUID | F1032: 22 | G1032: 0 | H1032: 0 | K1032: 0 | N1032: 0 | O1032: 0 | P1032: =_xlfn.CONCAT(A1032,".",D1032) -> WST_ULI.ULI_UID | Q1032: =VLOOKUP(Cobra8.5[[#This Row],[Table.Column]],ColumnMapping[Old Table.Column],1,) -> #N/A
A1033: WST_ULI | B1033: 0 | C1033: ULI | D1033: USR_ID | E1033: TEXT | F1033: 20 | G1033: 0 | H1033: 131072 | K1033: 10422 | N1033: 0 | O1033: 0 | P1033: =_xlfn.CONCAT(A1033,".",D1033) -> WST_ULI.USR_ID | Q1033: =VLOOKUP(Cobra8.5[[#This Row],[Table.Column]],ColumnMapping[Old Table.Column],1,) -> #N/A
A1034: WST_UNM | B1034: 0 | C1034: UNM | D1034: DIR_UID | E1034: GUID | F1034: 22 | G1034: 0 | H1034: 0 | K1034: 0 | L1034: 0 | M1034: DIR_UID | N1034: 1 | O1034: 0 | P1034: =_xlfn.CONCAT(A1034,".",D1034) -> WST_UNM.DIR_UID | Q1034: =VLOOKUP(Cobra8.5[[#This Row],[Table.Column]],ColumnMapping[Old Table.Column],1,) -> #N/A
A1035: WST_UNM | B1035: 0 | C1035: UNM | D1035: FIELD_NAME | E1035: TEXT | F1035: 60 | G1035: 0 | H1035: 0 | K1035: 0 | N1035: 0 | O1035: 0 | P1035: =_xlfn.CONCAT(A1035,".",D1035) -> WST_UNM.FIELD_NAME | Q1035: =VLOOKUP(Cobra8.5[[#This Row],[Table.Column]],ColumnMapping[Old Table.Column],1,) -> #N/A
A1036: WST_UNM | B1036: 0 | C1036: UNM | D1036: FIELD_VALUE | E1036: DBLE | F1036: 15 | G1036: 2 | H1036: 0 | K1036: 0 | N1036: 0 | O1036: 0 | P1036: =_xlfn.CONCAT(A1036,".",D1036) -> WST_UNM.FIELD_VALUE | Q1036: =VLOOKUP(Cobra8.5[[#This Row],[Table.Column]],ColumnMapping[Old Table.Column],1,) -> #N/A
A1037: WST_UNM | B1037: 0 | C1037: UNM | D1037: FK_UID | E1037: GUID | F1037: 22 | G1037: 0 | H1037: 0 | K1037: 0 | L1037: 0 | M1037: 0 | N1037: 0 | O1037: 0 | P1037: =_xlfn.CONCAT(A1037,".",D1037) -> WST_UNM.FK_UID | Q1037: =VLOOKUP(Cobra8.5[[#This Row],[Table.Column]],ColumnMapping[Old Table.Column],1,) -> #N/A
A1038: WST_UNM | B1038: 0 | C1038: UNM | D1038: ROW_UID | E1038: GUID | F1038: 22 | G1038: 0 | H1038: 0 | K1038: 0 | N1038: 0 | O1038: 0 | P1038: =_xlfn.CONCAT(A1038,".",D1038) -> WST_UNM.ROW_UID | Q1038: =VLOOKUP(Cobra8.5[[#This Row],[Table.Column]],ColumnMapping[Old Table.Column],1,) -> #N/A
A1039: WST_UNM | B1039: 0 | C1039: UNM | D1039: TABLE_TYPE | E1039: TEXT | F1039: 30 | G1039: 0 | H1039: 0 | K1039: 30526 | N1039: 0 | O1039: 0 | P1039: =_xlfn.CONCAT(A1039,".",D1039) -> WST_UNM.TABLE_TYPE | Q1039: =VLOOKUP(Cobra8.5[[#This Row],[Table.Column]],ColumnMapping[Old Table.Column],1,) -> #N/A
A1040: WST_UPA | B1040: 0 | C1040: UPA | D1040: FLAGS | E1040: INTE | F1040: 4 | G1040: 0 | H1040: 0 | K1040: 0 | N1040: 0 | O1040: 0 | P1040: =_xlfn.CONCAT(A1040,".",D1040) -> WST_UPA.FLAGS | Q1040: =VLOOKUP(Cobra8.5[[#This Row],[Table.Column]],ColumnMapping[Old Table.Column],1,) -> #N/A
A1041: WST_UPA | B1041: 0 | C1041: UPA | D1041: LICN_UID | E1041: GUID | F1041: 22 | G1041: 0 | H1041: 0 | K1041: 0 | N1041: 0 | O1041: 0 | P1041: =_xlfn.CONCAT(A1041,".",D1041) -> WST_UPA.LICN_UID | Q1041: =VLOOKUP(Cobra8.5[[#This Row],[Table.Column]],ColumnMapping[Old Table.Column],1,) -> #N/A
A1042: WST_UPA | B1042: 0 | C1042: UPA | D1042: PRD_UID | E1042: INTE | F1042: 4 | G1042: 0 | H1042: 0 | K1042: 15032 | N1042: 0 | O1042: 0 | P1042: =_xlfn.CONCAT(A1042,".",D1042) -> WST_UPA.PRD_UID | Q1042: =VLOOKUP(Cobra8.5[[#This Row],[Table.Column]],ColumnMapping[Old Table.Column],1,) -> #N/A
...

Sheet Cobra 8.6
A1: TABLE_NAME | B1: TABLE_FLAGS | C1: TABLE_TYPE | D1: FLD_NAME | E1: TYPE | F1: LENGTH | G1: SCALE | H1: COL_FLAGS | I1: SYS_NAME | J1: USR_NAME | K1: STRING_ID | L1: FKEY_TABLE | M1: FKEY_FLD_NAME | N1: FKEY_REQUIRED | O1: FKEY_VIRTUAL | P1: Table.Column | Q1: Found In Mapping?
A2: ACCOUNTS | B2: 0 | C2: ACCOUNTS | D2: ACCT | E2: TEXT | F2: 3 | G2: 0 | H2: 0 | K2: 0 | N2: 0 | O2: 0 | P2: =_xlfn.CONCAT(A2,".",D2) -> ACCOUNTS.ACCT | Q2: =VLOOKUP(Cobra8.6[[#This Row],[Table.Column]],ColumnMapping[Old Table.Column],1,) -> ACCOUNTS.ACCT
A3: ACCOUNTS | B3: 0 | C3: ACCOUNTS | D3: ACCTDESC | E3: TEXT | F3: 254 | G3: 0 | H3: 0 | K3: 0 | N3: 0 | O3: 0 | P3: =_xlfn.CONCAT(A3,".",D3) -> ACCOUNTS.ACCTDESC | Q3: =VLOOKUP(Cobra8.6[[#This Row],[Table.Column]],ColumnMapping[Old Table.Column],1,) -> ACCOUNTS.ACCTDESC
A4: ACCOUNTS | B4: 0 | C4: ACCOUNTS | D4: PROGRAM | E4: TEXT | F4: 22 | G4: 0 | H4: 0 | K4: 0 | N4: 0 | O4: 0 | P4: =_xlfn.CONCAT(A4,".",D4) -> ACCOUNTS.PROGRAM | Q4: =VLOOKUP(Cobra8.6[[#This Row],[Table.Column]],ColumnMapping[Old Table.Column],1,) -> ACCOUNTS.PROGRAM
A5: ACCOUNTS | B5: 0 | C5: ACCOUNTS | D5: REQUIRED | E5: INTE | F5: -1 | G5: 0 | H5: 0 | K5: 0 | N5: 0 | O5: 0 | P5: =_xlfn.CONCAT(A5,".",D5) -> ACCOUNTS.REQUIRED | Q5: =VLOOKUP(Cobra8.6[[#This Row],[Table.Column]],ColumnMapping[Old Table.Column],1,) -> ACCOUNTS.REQUIRED
A6: APPBE | B6: 0 | C6: APPBE | D6: CALCFILE | E6: TEXT | F6: 22 | G6: 0 | H6: 0 | K6: 0 | N6: 0 | O6: 0 | P6: =_xlfn.CONCAT(A6,".",D6) -> APPBE.CALCFILE | Q6: =VLOOKUP(Cobra8.6[[#This Row],[Table.Column]],ColumnMapping[Old Table.Column],1,) -> APPBE.CALCFILE
A7: APPBE | B7: 0 | C7: APPBE | D7: CALCORDER | E7: INTE | F7: -1 | G7: 0 | H7: 0 | K7: 0 | N7: 0 | O7: 0 | P7: =_xlfn.CONCAT(A7,".",D7) -> APPBE.CALCORDER | Q7: =VLOOKUP(Cobra8.6[[#This Row],[Table.Column]],ColumnMapping[Old Table.Column],1,) -> APPBE.CALCORDER
A8: APPBE | B8: 0 | C8: APPBE | D8: CECODE | E8: TEXT | F8: 59 | G8: 0 | H8: 0 | K8: 0 | N8: 0 | O8: 0 | P8: =_xlfn.CONCAT(A8,".",D8) -> APPBE.CECODE | Q8: =VLOOKUP(Cobra8.6[[#This Row],[Table.Column]],ColumnMapping[Old Table.Column],1,) -> APPBE.CECODE
A9: APPBE | B9: 0 | C9: APPBE | D9: LASTUPDATE | E9: DATE | F9: -1 | G9: 0 | H9: 0 | K9: 0 | N9: 0 | O9: 0 | P9: =_xlfn.CONCAT(A9,".",D9) -> APPBE.LASTUPDATE | Q9: =VLOOKUP(Cobra8.6[[#This Row],[Table.Column]],ColumnMapping[Old Table.Column],1,) -> APPBE.LASTUPDATE
A10: APPBE | B10: 0 | C10: APPBE | D10: RESULT | E10: TEXT | F10: 10 | G10: 0 | H10: 0 | K10: 0 | N10: 0 | O10: 0 | P10: =_xlfn.CONCAT(A10,".",D10) -> APPBE.RESULT | Q10: =VLOOKUP(Cobra8.6[[#This Row],[Table.Column]],ColumnMapping[Old Table.Column],1,) -> APPBE.RESULT
A11: APPBE | B11: 0 | C11: APPBE | D11: SEQUENCE | E11: INTE | F11: -1 | G11: 0 | H11: 0 | K11: 0 | N11: 0 | O11: 0 | P11: =_xlfn.CONCAT(A11,".",D11) -> APPBE.SEQUENCE | Q11: =VLOOKUP(Cobra8.6[[#This Row],[Table.Column]],ColumnMapping[Old Table.Column],1,) -> APPBE.SEQUENCE
A12: APPBE | B12: 0 | C12: APPBE | D12: USR_ID | E12: TEXT | F12: 20 | G12: 0 | H12: 0 | K12: 0 | N12: 0 | O12: 0 | P12: =_xlfn.CONCAT(A12,".",D12) -> APPBE.USR_ID | Q12: =VLOOKUP(Cobra8.6[[#This Row],[Table.Column]],ColumnMapping[Old Table.Column],1,) -> APPBE.USR_ID
A13: APPBEDTL | B13: 0 | C13: APPBEDTL | D13: CALCFILE | E13: TEXT | F13: 22 | G13: 0 | H13: 0 | K13: 0 | N13: 0 | O13: 0 | P13: =_xlfn.CONCAT(A13,".",D13) -> APPBEDTL.CALCFILE | Q13: =VLOOKUP(Cobra8.6[[#This Row],[Table.Column]],ColumnMapping[Old Table.Column],1,) -> APPBEDTL.CALCFILE
... A272: CALCDETL | B272: 0 | C272: CALCDETL | D272: SEQUENCE | E272: INTE | F272: -1 | G272: 0 | H272: 0 | K272: 0 | N272: 0 | O272: 0 | P272: =_xlfn.CONCAT(A272,".",D272) -> CALCDETL.SEQUENCE | Q272: =VLOOKUP(Cobra8.6[[#This Row],[Table.Column]],ColumnMapping[Old Table.Column],1,) -> CALCDETL.SEQUENCE
A273: CALCDETL | C273: CALCDETL | D273: SORT_CODE | E273: TEXT | F273: 1 | G273: 0 | H273: 0 | K273: 0 | N273: 0 | O273: 0 | P273: =_xlfn.CONCAT(A273,".",D273) -> CALCDETL.SORT_CODE | Q273: =VLOOKUP(Cobra8.6[[#This Row],[Table.Column]],ColumnMapping[Old Table.Column],1,) -> CALCDETL.SORT_CODE
A274: CALCDETL | B274: 0 | C274: CALCDETL | D274: SOURCE1 | E274: TEXT | F274: 10 | G274: 0 | H274: 0 | K274: 0 | N274: 0 | O274: 0 | P274: =_xlfn.CONCAT(A274,".",D274) -> CALCDETL.SOURCE1 | Q274: =VLOOKUP(Cobra8.6[[#This Row],[Table.Column]],ColumnMapping[Old Table.Column],1,) -> #N/A
A275: CALCDETL | B275: 0 | C275: CALCDETL | D275: SOURCE10 | E275: TEXT | F275: 10 | G275: 0 | H275: 0 | K275: 0 | N275: 0 | O275: 0 | P275: =_xlfn.CONCAT(A275,".",D275) -> CALCDETL.SOURCE10 | Q275: =VLOOKUP(Cobra8.6[[#This Row],[Table.Column]],ColumnMapping[Old Table.Column],1,) -> #N/A
A276: CALCDETL | B276: 0 | C276: CALCDETL | D276: SOURCE2 | E276: TEXT | F276: 10 | G276: 0 | H276: 0 | K276: 0 | N276: 0 | O276: 0 | P276: =_xlfn.CONCAT(A276,".",D276) -> CALCDETL.SOURCE2 | Q276: =VLOOKUP(Cobra8.6[[#This Row],[Table.Column]],ColumnMapping[Old Table.Column],1,) -> #N/A
A277: CALCDETL | B277: 0 | C277: CALCDETL | D277: SOURCE3 | E277: TEXT | F277: 10 | G277: 0 | H277: 0 | K277: 0 | N277: 0 | O277: 0 | P277: =_xlfn.CONCAT(A277,".",D277) -> CALCDETL.SOURCE3 | Q277: =VLOOKUP(Cobra8.6[[#This Row],[Table.Column]],ColumnMapping[Old Table.Column],1,) -> #N/A
A278: CALCDETL | B278: 0 | C278: CALCDETL | D278: SOURCE4 | E278: TEXT | F278: 10 | G278: 0 | H278: 0 | K278: 0 | N278: 0 | O278: 0 | P278: =_xlfn.CONCAT(A278,".",D278) -> CALCDETL.SOURCE4 | Q278: =VLOOKUP(Cobra8.6[[#This Row],[Table.Column]],ColumnMapping[Old Table.Column],1,) -> #N/A
A279: CALCDETL | B279: 0 | C279: CALCDETL | D279: SOURCE5 | E279: TEXT | F279: 10 | G279: 0 | H279: 0 | K279: 0 | N279: 0 | O279: 0 | P279: =_xlfn.CONCAT(A279,".",D279) -> CALCDETL.SOURCE5 | Q279: =VLOOKUP(Cobra8.6[[#This Row],[Table.Column]],ColumnMapping[Old Table.Column],1,) -> #N/A
A280: CALCDETL | B280: 0 | C280: CALCDETL | D280: SOURCE6 | E280: TEXT | F280: 10 | G280: 0 | H280: 0 | K280: 0 | N280: 0 | O280: 0 | P280: =_xlfn.CONCAT(A280,".",D280) -> CALCDETL.SOURCE6 | Q280: =VLOOKUP(Cobra8.6[[#This Row],[Table.Column]],ColumnMapping[Old Table.Column],1,) -> #N/A
A281: CALCDETL | B281: 0 | C281: CALCDETL | D281: SOURCE7 | E281: TEXT | F281: 10 | G281: 0 | H281: 0 | K281: 0 | N281: 0 | O281: 0 | P281: =_xlfn.CONCAT(A281,".",D281) -> CALCDETL.SOURCE7 | Q281: =VLOOKUP(Cobra8.6[[#This Row],[Table.Column]],ColumnMapping[Old Table.Column],1,) -> #N/A
A282: CALCDETL | B282: 0 | C282: CALCDETL | D282: SOURCE8 | E282: TEXT | F282: 10 | G282: 0 | H282: 0 | K282: 0 | N282: 0 | O282: 0 | P282: =_xlfn.CONCAT(A282,".",D282) -> CALCDETL.SOURCE8 | Q282: =VLOOKUP(Cobra8.6[[#This Row],[Table.Column]],ColumnMapping[Old Table.Column],1,) -> #N/A
A283: CALCDETL | B283: 0 | C283: CALCDETL | D283: SOURCE9 | E283: TEXT | F283: 10 | G283: 0 | H283: 0 | K283: 0 | N283: 0 | O283: 0 | P283: =_xlfn.CONCAT(A283,".",D283) -> CALCDETL.SOURCE9 | Q283: =VLOOKUP(Cobra8.6[[#This Row],[Table.Column]],ColumnMapping[Old Table.Column],1,) -> #N/A
A284: CALCDETL | B284: 0 | C284: CALCDETL | D284: UNITS | E284: TEXT | F284: 10 | G284: 0 | H284: 0 | K284: 0 | N284: 0 | O284: 0 | P284: =_xlfn.CONCAT(A284,".",D284) -> CALCDETL.UNITS | Q284: =VLOOKUP(Cobra8.6[[#This Row],[Table.Column]],ColumnMapping[Old Table.Column],1,) -> CALCDETL.UNITS
A285: CALCDETL | B285: 0 | C285: CALCDETL | D285: USR_ID | E285: TEXT | F285: 20 | G285: 0 | H285: 0 | K285: 0 | N285: 0 | O285: 0 | P285: =_xlfn.CONCAT(A285,".",D285) -> CALCDETL.USR_ID | Q285: =VLOOKUP(Cobra8.6[[#This Row],[Table.Column]],ColumnMapping[Old Table.Column],1,) -> CALCDETL.USR_ID
... A952: WST_CDR | B952: 7 | C952: CDR | D952: DESCRIPTION | E952: TEXT | F952: 125 | G952: 0 | H952: 0 | K952: 30245 | N952: 0 | O952: 0 | P952: =_xlfn.CONCAT(A952,".",D952) -> WST_CDR.DESCRIPTION | Q952: =VLOOKUP(Cobra8.6[[#This Row],[Table.Column]],ColumnMapping[Old Table.Column],1,) -> #N/A
A953: WST_CDR | B953: 7 | C953: CDR | D953: DIR_UID | E953: GUID | F953: 22 | G953: 0 | H953: 0 | K953: 712 | L953: COD | M953: DIR_UID | N953: 1 | O953: 0 | P953: =_xlfn.CONCAT(A953,".",D953) -> WST_CDR.DIR_UID | Q953: =VLOOKUP(Cobra8.6[[#This Row],[Table.Column]],ColumnMapping[Old Table.Column],1,) -> #N/A
A954: WST_CDR | B954: 7 | C954: CDR | D954: INTEGRATION_ID | E954: INTE | F954: 10 | G954: 0 | H954: 0 | K954: 31947 | N954: 0 | O954: 0 | P954: =_xlfn.CONCAT(A954,".",D954) -> WST_CDR.INTEGRATION_ID | Q954: =VLOOKUP(Cobra8.6[[#This Row],[Table.Column]],ColumnMapping[Old Table.Column],1,) -> #N/A
A955: WST_CDR | B955: 7 | C955: CDR | D955: LASTUPDATE | E955: DATE | F955: 20 | G955: 0 | H955: 131072 | K955: 30460 | N955: 0 | O955: 0 | P955: =_xlfn.CONCAT(A955,".",D955) -> WST_CDR.LASTUPDATE | Q955: =VLOOKUP(Cobra8.6[[#This Row],[Table.Column]],ColumnMapping[Old Table.Column],1,) -> #N/A
A956: WST_CDR | B956: 7 | C956: CDR | D956: POSITION_NUM | E956: INTE | F956: 8 | G956: 0 | H956: 0 | K956: 30248 | N956: 0 | O956: 0 | P956: =_xlfn.CONCAT(A956,".",D956) -> WST_CDR.POSITION_NUM | Q956: =VLOOKUP(Cobra8.6[[#This Row],[Table.Column]],ColumnMapping[Old Table.Column],1,) -> #N/A
A957: WST_CDR | B957: 7 | C957: CDR | D957: SEQUENCE | E957: INTE | F957: 4 | G957: 0 | H957: 196608 | K957: 30042 | N957: 0 | O957: 0 | P957: =_xlfn.CONCAT(A957,".",D957) -> WST_CDR.SEQUENCE | Q957: =VLOOKUP(Cobra8.6[[#This Row],[Table.Column]],ColumnMapping[Old Table.Column],1,) -> #N/A
A958: WST_CDR | B958: 7 | C958: CDR | D958: SUPPRESS | E958: BOOL | F958: 4 | G958: 0 | H958: 0 | K958: 30332 | N958: 0 | O958: 0 | P958: =_xlfn.CONCAT(A958,".",D958) -> WST_CDR.SUPPRESS | Q958: =VLOOKUP(Cobra8.6[[#This Row],[Table.Column]],ColumnMapping[Old Table.Column],1,) -> #N/A
A959: WST_CDR | B959: 7 | C959: CDR | D959: USR_ID | E959: TEXT | F959: 20 | G959: 0 | H959: 131072 | K959: 30451 | N959: 0 | O959: 0 | P959: =_xlfn.CONCAT(A959,".",D959) -> WST_CDR.USR_ID | Q959: =VLOOKUP(Cobra8.6[[#This Row],[Table.Column]],ColumnMapping[Old Table.Column],1,) -> #N/A
A960: WST_CFG | B960: 2 | C960: CFG | D960: CFG_ID | E960: TEXT | F960: 60 | G960: 0 | H960: 0 | K960: 0 | N960: 0 | O960: 0 | P960: =_xlfn.CONCAT(A960,".",D960) -> WST_CFG.CFG_ID | Q960: =VLOOKUP(Cobra8.6[[#This Row],[Table.Column]],ColumnMapping[Old Table.Column],1,) -> #N/A
A961: WST_CFG | B961: 2 | C961: CFG | D961: CFG_TYPE | E961: TEXT | F961: 30 | G961: 0 | H961: 0 | K961: 0 | N961: 0 | O961: 0 | P961: =_xlfn.CONCAT(A961,".",D961) -> WST_CFG.CFG_TYPE | Q961: =VLOOKUP(Cobra8.6[[#This Row],[Table.Column]],ColumnMapping[Old Table.Column],1,) -> #N/A
A962: WST_CFG | B962: 2 | C962: CFG | D962: CFG_UID | E962: GUID | F962: 22 | G962: 0 | H962: 0 | K962: 0 | N962: 0 | O962: 0 | P962: =_xlfn.CONCAT(A962,".",D962) -> WST_CFG.CFG_UID | Q962: =VLOOKUP(Cobra8.6[[#This Row],[Table.Column]],ColumnMapping[Old Table.Column],1,) -> #N/A
A963: WST_CFG | B963: 2 | C963: CFG | D963: DATA | E963: TEXT | F963: 8192 | G963: 0 | H963: 0 | K963: 0 | N963: 0 | O963: 0 | P963: =_xlfn.CONCAT(A963,".",D963) -> WST_CFG.DATA | Q963: =VLOOKUP(Cobra8.6[[#This Row],[Table.Column]],ColumnMapping[Old Table.Column],1,) -> #N/A
A964: WST_CFG | B964: 2 | C964: CFG | D964: DESCRIPTION | E964: TEXT | F964: 254 | G964: 0 | H964: 0 | K964: 0 | N964: 0 | O964: 0 | P964: =_xlfn.CONCAT(A964,".",D964) -> WST_CFG.DESCRIPTION | Q964: =VLOOKUP(Cobra8.6[[#This Row],[Table.Column]],ColumnMapping[Old Table.Column],1,) -> #N/A
A965: WST_CFG | B965: 2 | C965: CFG | D965: LASTUPDATE | E965: DATE | F965: 20 | G965: 0 | H965: 131072 | K965: 30460 | N965: 0 | O965: 0 | P965: =_xlfn.CONCAT(A965,".",D965) -> WST_CFG.LASTUPDATE | Q965: =VLOOKUP(Cobra8.6[[#This Row],[Table.Column]],ColumnMapping[Old Table.Column],1,) -> #N/A
... A970: WST_COD | B970: 7 | C970: COD | D970: DATA | E970: TEXT | F970: 60 | G970: 0 | H970: 0 | K970: 30512 | N970: 0 | O970: 0 | P970: =_xlfn.CONCAT(A970,".",D970) -> WST_COD.DATA | Q970: =VLOOKUP(Cobra8.6[[#This Row],[Table.Column]],ColumnMapping[Old Table.Column],1,) -> #N/A
A971: WST_COD | B971: 7 | C971: COD | D971: DIR_UID | E971: GUID | F971: 22 | G971: 0 | H971: 0 | K971: 0 | L971: 0 | M971: DIR_UID | N971: 1 | O971: 0 | P971: =_xlfn.CONCAT(A971,".",D971) -> WST_COD.DIR_UID | Q971: =VLOOKUP(Cobra8.6[[#This Row],[Table.Column]],ColumnMapping[Old Table.Column],1,) -> #N/A
A972: WST_COD | B972: 7 | C972: COD | D972: PROMPT_TEXT | E972: TEXT | F972: 20 | G972: 0 | H972: 0 | K972: 30511 | N972: 0 | O972: 0 | P972: =_xlfn.CONCAT(A972,".",D972) -> WST_COD.PROMPT_TEXT | Q972: =VLOOKUP(Cobra8.6[[#This Row],[Table.Column]],ColumnMapping[Old Table.Column],1,) -> #N/A
A973: WST_COD | B973: 7 | C973: COD | D973: STARTVIEW | E973: TEXT | F973: 20 | G973: 0 | H973: 0 | K973: 31505 | N973: 0 | O973: 0 | P973: =_xlfn.CONCAT(A973,".",D973) -> WST_COD.STARTVIEW | Q973: =VLOOKUP(Cobra8.6[[#This Row],[Table.Column]],ColumnMapping[Old Table.Column],1,) -> #N/A
A974: WST_COD | B974: 7 | C974: COD | D974: TH_FLAGS | E974: TEXT | F974: 10 | G974: 0 | H974: 0 | K974: 30513 | N974: 0 | O974: 0 | P974: =_xlfn.CONCAT(A974,".",D974) -> WST_COD.TH_FLAGS | Q974: =VLOOKUP(Cobra8.6[[#This Row],[Table.Column]],ColumnMapping[Old Table.Column],1,) -> #N/A
A975: WST_DIR | B975: 0 | C975: DIR | D975: DESCRIPTION | E975: TEXT | F975: 125 | G975: 0 | H975: 0 | K975: 30525 | N975: 0 | O975: 0 | P975: =_xlfn.CONCAT(A975,".",D975) -> WST_DIR.DESCRIPTION | Q975: =VLOOKUP(Cobra8.6[[#This Row],[Table.Column]],ColumnMapping[Old Table.Column],1,) -> #N/A
A976: WST_DIR | B976: 0 | C976: DIR | D976: DIR_ID | E976: TEXT | F976: 22 | G976: 0 | H976: 0 | K976: 30527 | N976: 0 | O976: 0 | P976: =_xlfn.CONCAT(A976,".",D976) -> WST_DIR.DIR_ID | Q976: =VLOOKUP(Cobra8.6[[#This Row],[Table.Column]],ColumnMapping[Old Table.Column],1,) -> #N/A
A977: WST_DIR | B977: 0 | C977: DIR | D977: DIR_UID | E977: GUID | F977: 22 | G977: 0 | H977: 0 | K977: 0 | N977: 0 | O977: 0 | P977: =_xlfn.CONCAT(A977,".",D977) -> WST_DIR.DIR_UID | Q977: =VLOOKUP(Cobra8.6[[#This Row],[Table.Column]],ColumnMapping[Old Table.Column],1,) -> #N/A
A978: WST_DIR | B978: 0 | C978: DIR | D978: LASTUPDATE | E978: DATE | F978: 20 | G978: 0 | H978: 131072 | K978: 30460 | N978: 0 | O978: 0 | P978: =_xlfn.CONCAT(A978,".",D978) -> WST_DIR.LASTUPDATE | Q978: =VLOOKUP(Cobra8.6[[#This Row],[Table.Column]],ColumnMapping[Old Table.Column],1,) -> #N/A
A979: WST_DIR | B979: 0 | C979: DIR | D979: OPENMODE | E979: TEXT | F979: 1 | G979: 0 | H979: 0 | K979: 30528 | N979: 0 | O979: 0 | P979: =_xlfn.CONCAT(A979,".",D979) -> WST_DIR.OPENMODE | Q979: =VLOOKUP(Cobra8.6[[#This Row],[Table.Column]],ColumnMapping[Old Table.Column],1,) -> #N/A
A980: WST_DIR | B980: 0 | C980: DIR | D980: OWNER_ID | E980: TEXT | F980: 20 | G980: 0 | H980: 131072 | K980: 30452 | N980: 0 | O980: 0 | P980: =_xlfn.CONCAT(A980,".",D980) -> WST_DIR.OWNER_ID | Q980: =VLOOKUP(Cobra8.6[[#This Row],[Table.Column]],ColumnMapping[Old Table.Column],1,) -> #N/A
A981: WST_DIR | B981: 0 | C981: DIR | D981: SEQUENCE | E981: INTE | F981: 4 | G981: 0 | H981: 196608 | K981: 30042 | N981: 0 | O981: 0 | P981: =_xlfn.CONCAT(A981,".",D981) -> WST_DIR.SEQUENCE | Q981: =VLOOKUP(Cobra8.6[[#This Row],[Table.Column]],ColumnMapping[Old Table.Column],1,) -> #N/A
A982: WST_DIR | B982: 0 | C982: DIR | D982: TABLE_TYPE | E982: TEXT | F982: 30 | G982: 0 | H982: 0 | K982: 30526 | N982: 0 | O982: 0 | P982: =_xlfn.CONCAT(A982,".",D982) -> WST_DIR.TABLE_TYPE | Q982: =VLOOKUP(Cobra8.6[[#This Row],[Table.Column]],ColumnMapping[Old Table.Column],1,) -> #N/A
A983: WST_DIR | B983: 0 | C983: DIR | D983: USR_ID | E983: TEXT | F983: 20 | G983: 0 | H983: 131072 | K983: 30451 | N983: 0 | O983: 0 | P983: =_xlfn.CONCAT(A983,".",D983) -> WST_DIR.USR_ID | Q983: =VLOOKUP(Cobra8.6[[#This Row],[Table.Column]],ColumnMapping[Old Table.Column],1,) -> #N/A
... A997: WST_LCK | B997: 32 | C997: LCK | D997: USR_ID | E997: TEXT | F997: 20 | G997: 0 | H997: 131072 | K997: 30451 | N997: 0 | O997: 0 | P997: =_xlfn.CONCAT(A997,".",D997) -> WST_LCK.USR_ID | Q997: =VLOOKUP(Cobra8.6[[#This Row],[Table.Column]],ColumnMapping[Old Table.Column],1,) -> WST_LCK.USR_ID
A998: WST_NTX | B998: 0 | C998: NTX | D998: DIR_UID | E998: GUID | F998: 22 | G998: 0 | H998: 0 | K998: 0 | L998: 0 | M998: DIR_UID | N998: 0 | O998: 0 | P998: =_xlfn.CONCAT(A998,".",D998) -> WST_NTX.DIR_UID | Q998: =VLOOKUP(Cobra8.6[[#This Row],[Table.Column]],ColumnMapping[Old Table.Column],1,) -> #N/A
A999: WST_NTX | B999: 0 | C999: NTX | D999: FIELD_NAME | E999: TEXT | F999: 60 | G999: 0 | H999: 0 | K999: 0 | N999: 0 | O999: 0 | P999: =_xlfn.CONCAT(A999,".",D999) -> WST_NTX.FIELD_NAME | Q999: =VLOOKUP(Cobra8.6[[#This Row],[Table.Column]],ColumnMapping[Old Table.Column],1,) -> #N/A
A1000: WST_NTX | B1000: 0 | C1000: NTX | D1000: FIELD_VALUE | E1000: MEMO | F1000: 32768 | G1000: 0 | H1000: 0 | K1000: 0 | N1000: 0 | O1000: 0 | P1000: =_xlfn.CONCAT(A1000,".",D1000) -> WST_NTX.FIELD_VALUE | Q1000: =VLOOKUP(Cobra8.6[[#This Row],[Table.Column]],ColumnMapping[Old Table.Column],1,) -> #N/A
A1001: WST_NTX | B1001: 0 | C1001: NTX | D1001: FK_UID | E1001: GUID | F1001: 22 | G1001: 0 | H1001: 0 | K1001: 0 | L1001: 0 | M1001: 0 | N1001: 0 | O1001: 0 | P1001: =_xlfn.CONCAT(A1001,".",D1001) -> WST_NTX.FK_UID | Q1001: =VLOOKUP(Cobra8.6[[#This Row],[Table.Column]],ColumnMapping[Old Table.Column],1,) -> #N/A
A1002: WST_NTX | B1002: 0 | C1002: NTX | D1002: ROW_UID | E1002: GUID | F1002: 22 | G1002: 0 | H1002: 0 | K1002: 0 | N1002: 0 | O1002: 0 | P1002: =_xlfn.CONCAT(A1002,".",D1002) -> WST_NTX.ROW_UID | Q1002: =VLOOKUP(Cobra8.6[[#This Row],[Table.Column]],ColumnMapping[Old Table.Column],1,) -> #N/A
A1003: WST_NTX | B1003: 0 | C1003: NTX | D1003: TABLE_TYPE | E1003: TEXT | F1003: 30 | G1003: 0 | H1003: 0 | K1003: 30526 | N1003: 0 | O1003: 0 | P1003: =_xlfn.CONCAT(A1003,".",D1003) -> WST_NTX.TABLE_TYPE | Q1003: =VLOOKUP(Cobra8.6[[#This Row],[Table.Column]],ColumnMapping[Old Table.Column],1,) -> #N/A
A1004: WST_ROL | B1004: 2 | C1004: ROL | D1004: DESCRIPTION | E1004: TEXT | F1004: 60 | G1004: 0 | H1004: 0 | K1004: 30525 | N1004: 0 | O1004: 0 | P1004: =_xlfn.CONCAT(A1004,".",D1004) -> WST_ROL.DESCRIPTION | Q1004: =VLOOKUP(Cobra8.6[[#This Row],[Table.Column]],ColumnMapping[Old Table.Column],1,) -> #N/A
A1005: WST_ROL | B1005: 2 | C1005: ROL | D1005: MANAGER | E1005: TEXT | F1005: 20 | G1005: 0 | H1005: 0 | K1005: 0 | N1005: 0 | O1005: 0 | P1005: =_xlfn.CONCAT(A1005,".",D1005) -> WST_ROL.MANAGER | Q1005: =VLOOKUP(Cobra8.6[[#This Row],[Table.Column]],ColumnMapping[Old Table.Column],1,) -> #N/A
A1006: WST_ROL | B1006: 2 | C1006: ROL | D1006: ROL_ID | E1006: TEXT | F1006: 20 | G1006: 0 | H1006: 0 | K1006: 0 | N1006: 0 | O1006: 0 | P1006: =_xlfn.CONCAT(A1006,".",D1006) -> WST_ROL.ROL_ID | Q1006: =VLOOKUP(Cobra8.6[[#This Row],[Table.Column]],ColumnMapping[Old Table.Column],1,) -> #N/A
A1007: WST_UDF | B1007: 0 | C1007: UDF | D1007: DESCRIPTION | E1007: TEXT | F1007: 60 | G1007: 0 | H1007: 0 | K1007: 30525 | N1007: 0 | O1007: 0 | P1007: =_xlfn.CONCAT(A1007,".",D1007) -> WST_UDF.DESCRIPTION | Q1007: =VLOOKUP(Cobra8.6[[#This Row],[Table.Column]],ColumnMapping[Old Table.Column],1,) -> WST_UDF.DESCRIPTION
A1008: WST_UDF | B1008: 0 | C1008: UDF | D1008: FIELD_NAME | E1008: TEXT | F1008: 60 | G1008: 0 | H1008: 0 | K1008: 0 | N1008: 0 | O1008: 0 | P1008: =_xlfn.CONCAT(A1008,".",D1008) -> WST_UDF.FIELD_NAME | Q1008: =VLOOKUP(Cobra8.6[[#This Row],[Table.Column]],ColumnMapping[Old Table.Column],1,) -> #N/A
A1009: WST_UDF | B1009: 0 | C1009: UDF | D1009: FIELD_TYPE | E1009: TEXT | F1009: 4 | G1009: 0 | H1009: 0 | K1009: 0 | N1009: 0 | O1009: 0 | P1009: =_xlfn.CONCAT(A1009,".",D1009) -> WST_UDF.FIELD_TYPE | Q1009: =VLOOKUP(Cobra8.6[[#This Row],[Table.Column]],ColumnMapping[Old Table.Column],1,) -> WST_UDF.FIELD_TYPE
A1010: WST_UDF | B1010: 0 | C1010: UDF | D1010: LOOKUP_FIELD | E1010: TEXT | F1010: 30 | G1010: 0 | H1010: 0 | K1010: 0 | N1010: 0 | O1010: 0 | P1010: =_xlfn.CONCAT(A1010,".",D1010) -> WST_UDF.LOOKUP_FIELD | Q1010: =VLOOKUP(Cobra8.6[[#This Row],[Table.Column]],ColumnMapping[Old Table.Column],1,) -> WST_UDF.LOOKUP_FIELD
A1011: WST_UDF | B1011: 0 | C1011: UDF | D1011: LOOKUP_TABLE_NAME | E1011: TEXT | F1011: 30 | G1011: 0 | H1011: 0 | K1011: 0 | N1011: 0 | O1011: 0 | P1011: =_xlfn.CONCAT(A1011,".",D1011) -> WST_UDF.LOOKUP_TABLE_NAME | Q1011: =VLOOKUP(Cobra8.6[[#This Row],[Table.Column]],ColumnMapping[Old Table.Column],1,) -> WST_UDF.LOOKUP_TABLE_NAME
A1012: WST_UDF | B1012: 0 | C1012: UDF | D1012: LOOKUP_TABLE_TYPE | E1012: TEXT | F1012: 30 | G1012: 0 | H1012: 0 | K1012: 0 | N1012: 0 | O1012: 0 | P1012: =_xlfn.CONCAT(A1012,".",D1012) -> WST_UDF.LOOKUP_TABLE_TYPE | Q1012: =VLOOKUP(Cobra8.6[[#This Row],[Table.Column]],ColumnMapping[Old Table.Column],1,) -> WST_UDF.LOOKUP_TABLE_TYPE
A1013: WST_UDF | B1013: 0 | C1013: UDF | D1013: SEQUENCE | E1013: INTE | F1013: 4 | G1013: 0 | H1013: 196608 | K1013: 30042 | N1013: 0 | O1013: 0 | P1013: =_xlfn.CONCAT(A1013,".",D1013) -> WST_UDF.SEQUENCE | Q1013: =VLOOKUP(Cobra8.6[[#This Row],[Table.Column]],ColumnMapping[Old Table.Column],1,) -> #N/A
... A1015: WST_UDF | B1015: 0 | C1015: UDF | D1015: UDF_UID | E1015: GUID | F1015: 22 | G1015: 0 | H1015: 0 | K1015: 0 | N1015: 0 | O1015: 0 | P1015: =_xlfn.CONCAT(A1015,".",D1015) -> WST_UDF.UDF_UID | Q1015: =VLOOKUP(Cobra8.6[[#This Row],[Table.Column]],ColumnMapping[Old Table.Column],1,) -> #N/A
A1016: WST_UDT | B1016: 0 | C1016: UDT | D1016: DIR_UID | E1016: GUID | F1016: 22 | G1016: 0 | H1016: 0 | K1016: 0 | L1016: 0 | M1016: DIR_UID | N1016: 1 | O1016: 0 | P1016: =_xlfn.CONCAT(A1016,".",D1016) -> WST_UDT.DIR_UID | Q1016: =VLOOKUP(Cobra8.6[[#This Row],[Table.Column]],ColumnMapping[Old Table.Column],1,) -> #N/A
A1017: WST_UDT | B1017: 0 | C1017: UDT | D1017: FIELD_NAME | E1017: TEXT | F1017: 60 | G1017: 0 | H1017: 0 | K1017: 0 | N1017: 0 | O1017: 0 | P1017: =_xlfn.CONCAT(A1017,".",D1017) -> WST_UDT.FIELD_NAME | Q1017: =VLOOKUP(Cobra8.6[[#This Row],[Table.Column]],ColumnMapping[Old Table.Column],1,) -> #N/A
A1018: WST_UDT | B1018: 0 | C1018: UDT | D1018: FIELD_VALUE | E1018: DATE | F1018: 20 | G1018: 0 | H1018: 0 | K1018: 0 | N1018: 0 | O1018: 0 | P1018: =_xlfn.CONCAT(A1018,".",D1018) -> WST_UDT.FIELD_VALUE | Q1018: =VLOOKUP(Cobra8.6[[#This Row],[Table.Column]],ColumnMapping[Old Table.Column],1,) -> #N/A
A1019: WST_UDT | B1019: 0 | C1019: UDT | D1019: FK_UID | E1019: GUID | F1019: 22 | G1019: 0 | H1019: 0 | K1019: 0 | L1019: 0 | M1019: 0 | N1019: 0 | O1019: 0 | P1019: =_xlfn.CONCAT(A1019,".",D1019) -> WST_UDT.FK_UID | Q1019: =VLOOKUP(Cobra8.6[[#This Row],[Table.Column]],ColumnMapping[Old Table.Column],1,) -> #N/A
A1020: WST_UDT | B1020: 0 | C1020: UDT | D1020: ROW_UID | E1020: GUID | F1020: 22 | G1020: 0 | H1020: 0 | K1020: 0 | N1020: 0 | O1020: 0 | P1020: =_xlfn.CONCAT(A1020,".",D1020) -> WST_UDT.ROW_UID | Q1020: =VLOOKUP(Cobra8.6[[#This Row],[Table.Column]],ColumnMapping[Old Table.Column],1,) -> #N/A
A1021: WST_UDT | B1021: 0 | C1021: UDT | D1021: TABLE_TYPE | E1021: TEXT | F1021: 30 | G1021: 0 | H1021: 0 | K1021: 30526 | N1021: 0 | O1021: 0 | P1021: =_xlfn.CONCAT(A1021,".",D1021) -> WST_UDT.TABLE_TYPE | Q1021: =VLOOKUP(Cobra8.6[[#This Row],[Table.Column]],ColumnMapping[Old Table.Column],1,) -> #N/A
A1022: WST_UDU | B1022: 0 | C1022: UDU | D1022: DIR_UID | E1022: GUID | F1022: 22 | G1022: 0 | H1022: 0 | K1022: 0 | L1022: 0 | M1022: DIR_UID | N1022: 1 | O1022: 0 | P1022: =_xlfn.CONCAT(A1022,".",D1022) -> WST_UDU.DIR_UID | Q1022: =VLOOKUP(Cobra8.6[[#This Row],[Table.Column]],ColumnMapping[Old Table.Column],1,) -> #N/A
A1023: WST_UDU | B1023: 0 | C1023: UDU | D1023: FIELD_NAME | E1023: TEXT | F1023: 60 | G1023: 0 | H1023: 0 | K1023: 0 | N1023: 0 | O1023: 0 | P1023: =_xlfn.CONCAT(A1023,".",D1023) -> WST_UDU.FIELD_NAME | Q1023: =VLOOKUP(Cobra8.6[[#This Row],[Table.Column]],ColumnMapping[Old Table.Column],1,) -> #N/A
A1024: WST_UDU | B1024: 0 | C1024: UDU | D1024: FIELD_VALUE | E1024: DURA | F1024: 8 | G1024: 0 | H1024: 0 | K1024: 0 | N1024: 0 | O1024: 0 | P1024: =_xlfn.CONCAT(A1024,".",D1024) -> WST_UDU.FIELD_VALUE | Q1024: =VLOOKUP(Cobra8.6[[#This Row],[Table.Column]],ColumnMapping[Old Table.Column],1,) -> #N/A
A1025: WST_UDU | B1025: 0 | C1025: UDU | D1025: FK_UID | E1025: GUID | F1025: 22 | G1025: 0 | H1025: 0 | K1025: 0 | L1025: 0 | M1025: 0 | N1025: 0 | O1025: 0 | P1025: =_xlfn.CONCAT(A1025,".",D1025) -> WST_UDU.FK_UID | Q1025: =VLOOKUP(Cobra8.6[[#This Row],[Table.Column]],ColumnMapping[Old Table.Column],1,) -> #N/A
A1026: WST_UDU | B1026: 0 | C1026: UDU | D1026: ROW_UID | E1026: GUID | F1026: 22 | G1026: 0 | H1026: 0 | K1026: 0 | N1026: 0 | O1026: 0 | P1026: =_xlfn.CONCAT(A1026,".",D1026) -> WST_UDU.ROW_UID | Q1026: =VLOOKUP(Cobra8.6[[#This Row],[Table.Column]],ColumnMapping[Old Table.Column],1,) -> #N/A
A1027: WST_UDU | B1027: 0 | C1027: UDU | D1027: TABLE_TYPE | E1027: TEXT | F1027: 30 | G1027: 0 | H1027: 0 | K1027: 30526 | N1027: 0 | O1027: 0 | P1027: =_xlfn.CONCAT(A1027,".",D1027) -> WST_UDU.TABLE_TYPE | Q1027: =VLOOKUP(Cobra8.6[[#This Row],[Table.Column]],ColumnMapping[Old Table.Column],1,) -> #N/A
A1028: WST_ULI | B1028: 0 | C1028: ULI | D1028: LICENSEREVOKED | E1028: INTE | F1028: 4 | G1028: 0 | H1028: 0 | K1028: 0 | N1028: 0 | O1028: 0 | P1028: =_xlfn.CONCAT(A1028,".",D1028) -> WST_ULI.LICENSEREVOKED | Q1028: =VLOOKUP(Cobra8.6[[#This Row],[Table.Column]],ColumnMapping[Old Table.Column],1,) -> #N/A
A1029: WST_ULI | B1029: 0 | C1029: ULI | D1029: LOGINTIME | E1029: DATE | F1029: 8 | G1029: 0 | H1029: 0 | K1029: 12418 | N1029: 0 | O1029: 0 | P1029: =_xlfn.CONCAT(A1029,".",D1029) -> WST_ULI.LOGINTIME | Q1029: =VLOOKUP(Cobra8.6[[#This Row],[Table.Column]],ColumnMapping[Old Table.Column],1,) -> #N/A
A1030: WST_ULI | B1030: 0 | C1030: ULI | D1030: MACHINE_ID | E1030: TEXT | F1030: 48 | G1030: 0 | H1030: 0 | K1030: 5085 | N1030: 0 | O1030: 0 | P1030: =_xlfn.CONCAT(A1030,".",D1030) -> WST_ULI.MACHINE_ID | Q1030: =VLOOKUP(Cobra8.6[[#This Row],[Table.Column]],ColumnMapping[Old Table.Column],1,) -> #N/A
A1031: WST_ULI | B1031: 0 | C1031: ULI | D1031: PRD_UID | E1031: INTE | F1031: 4 | G1031: 0 | H1031: 0 | K1031: 15032 | N1031: 0 | O1031: 0 | P1031: =_xlfn.CONCAT(A1031,".",D1031) -> WST_ULI.PRD_UID | Q1031: =VLOOKUP(Cobra8.6[[#This Row],[Table.Column]],ColumnMapping[Old Table.Column],1,) -> #N/A
A1032: WST_ULI | B1032: 0 | C1032: ULI | D1032: ULI_UID | E1032: GUID | F1032: 22 | G1032: 0 | H1032: 0 | K1032: 0 | N1032: 0 | O1032: 0 | P1032: =_xlfn.CONCAT(A1032,".",D1032) -> WST_ULI.ULI_UID | Q1032: =VLOOKUP(Cobra8.6[[#This Row],[Table.Column]],ColumnMapping[Old Table.Column],1,) -> #N/A
A1033: WST_ULI | B1033: 0 | C1033: ULI | D1033: USR_ID | E1033: TEXT | F1033: 20 | G1033: 0 | H1033: 131072 | K1033: 10422 | N1033: 0 | O1033: 0 | P1033: =_xlfn.CONCAT(A1033,".",D1033) -> WST_ULI.USR_ID | Q1033: =VLOOKUP(Cobra8.6[[#This Row],[Table.Column]],ColumnMapping[Old Table.Column],1,) -> #N/A
A1034: WST_UNM | B1034: 0 | C1034: UNM | D1034: DIR_UID | E1034: GUID | F1034: 22 | G1034: 0 | H1034: 0 | K1034: 0 | L1034: 0 | M1034: DIR_UID | N1034: 1 | O1034: 0 | P1034: =_xlfn.CONCAT(A1034,".",D1034) -> WST_UNM.DIR_UID | Q1034: =VLOOKUP(Cobra8.6[[#This Row],[Table.Column]],ColumnMapping[Old Table.Column],1,) -> #N/A
A1035: WST_UNM | B1035: 0 | C1035: UNM | D1035: FIELD_NAME | E1035: TEXT | F1035: 60 | G1035: 0 | H1035: 0 | K1035: 0 | N1035: 0 | O1035: 0 | P1035: =_xlfn.CONCAT(A1035,".",D1035) -> WST_UNM.FIELD_NAME | Q1035: =VLOOKUP(Cobra8.6[[#This Row],[Table.Column]],ColumnMapping[Old Table.Column],1,) -> #N/A
A1036: WST_UNM | B1036: 0 | C1036: UNM | D1036: FIELD_VALUE | E1036: DBLE | F1036: 15 | G1036: 2 | H1036: 0 | K1036: 0 | N1036: 0 | O1036: 0 | P1036: =_xlfn.CONCAT(A1036,".",D1036) -> WST_UNM.FIELD_VALUE | Q1036: =VLOOKUP(Cobra8.6[[#This Row],[Table.Column]],ColumnMapping[Old Table.Column],1,) -> #N/A
A1037: WST_UNM | B1037: 0 | C1037: UNM | D1037: FK_UID | E1037: GUID | F1037: 22 | G1037: 0 | H1037: 0 | K1037: 0 | L1037: 0 | M1037: 0 | N1037: 0 | O1037: 0 | P1037: =_xlfn.CONCAT(A1037,".",D1037) -> WST_UNM.FK_UID | Q1037: =VLOOKUP(Cobra8.6[[#This Row],[Table.Column]],ColumnMapping[Old Table.Column],1,) -> #N/A
A1038: WST_UNM | B1038: 0 | C1038: UNM | D1038: ROW_UID | E1038: GUID | F1038: 22 | G1038: 0 | H1038: 0 | K1038: 0 | N1038: 0 | O1038: 0 | P1038: =_xlfn.CONCAT(A1038,".",D1038) -> WST_UNM.ROW_UID | Q1038: =VLOOKUP(Cobra8.6[[#This Row],[Table.Column]],ColumnMapping[Old Table.Column],1,) -> #N/A
A1039: WST_UNM | B1039: 0 | C1039: UNM | D1039: TABLE_TYPE | E1039: TEXT | F1039: 30 | G1039: 0 | H1039: 0 | K1039: 30526 | N1039: 0 | O1039: 0 | P1039: =_xlfn.CONCAT(A1039,".",D1039) -> WST_UNM.TABLE_TYPE | Q1039: =VLOOKUP(Cobra8.6[[#This Row],[Table.Column]],ColumnMapping[Old Table.Column],1,) -> #N/A
A1040: WST_UPA | B1040: 0 | C1040: UPA | D1040: FLAGS | E1040: INTE | F1040: 4 | G1040: 0 | H1040: 0 | K1040: 0 | N1040: 0 | O1040: 0 | P1040: =_xlfn.CONCAT(A1040,".",D1040) -> WST_UPA.FLAGS | Q1040: =VLOOKUP(Cobra8.6[[#This Row],[Table.Column]],ColumnMapping[Old Table.Column],1,) -> #N/A
A1041: WST_UPA | B1041: 0 | C1041: UPA | D1041: LICN_UID | E1041: GUID | F1041: 22 | G1041: 0 | H1041: 0 | K1041: 0 | N1041: 0 | O1041: 0 | P1041: =_xlfn.CONCAT(A1041,".",D1041) -> WST_UPA.LICN_UID | Q1041: =VLOOKUP(Cobra8.6[[#This Row],[Table.Column]],ColumnMapping[Old Table.Column],1,) -> #N/A
A1042: WST_UPA | B1042: 0 | C1042: UPA | D1042: PRD_UID | E1042: INTE | F1042: 4 | G1042: 0 | H1042: 0 | K1042: 15032 | N1042: 0 | O1042: 0 | P1042: =_xlfn.CONCAT(A1042,".",D1042) -> WST_UPA.PRD_UID | Q1042: =VLOOKUP(Cobra8.6[[#This Row],[Table.Column]],ColumnMapping[Old Table.Column],1,) -> #N/A
...

Sheet 8.5 -> Web Table Mapping
A1: Old Table Name | B1: New Table Name | C1: Migrate | D1: Comment | E1: VIEW - Creates view with OLD table name | F1: Legend | G1: Hybridization
A2: ACCOUNTS | C2: [ NONE ] | D2: Obsolete | E2: =IF(AND(A2<>"",B2<>""),_xlfn.CONCAT("CREATE OR REPLACE VIEW ",A2," AS SELECT * FROM ",B2,";"),"") | F2: [ NONE ] = Table not created in Cobra Web. | G2: Y
A3: APPBE | C3: [ FUTURE ] | D3: Apportionment not planned for Cobra Web 1.0 | E3: =IF(AND(A3<>"",B3<>""),_xlfn.CONCAT("CREATE OR REPLACE VIEW ",A3," AS SELECT * FROM ",B3,";"),"") | F3: [ FUTURE ] = Table not needed for Cobra Web 1.0. | G3: Not Required
A4: APPBEDTL | C4: [ FUTURE ] | D4: Apportionment not planned for Cobra Web 1.0 | E4: =IF(AND(A4<>"",B4<>""),_xlfn.CONCAT("CREATE OR REPLACE VIEW ",A4," AS SELECT * FROM ",B4,";"),"") | F4: [ TBD ] = We expect we'll need a table but have not yet determined what the table is or where the data might live | G4: Not Required
A5: APPMAPSC | C5: [ FUTURE ] | D5: Apportionment not planned for Cobra Web 1.0 | E5: =IF(AND(A5<>"",B5<>""),_xlfn.CONCAT("CREATE OR REPLACE VIEW ",A5," AS SELECT * FROM ",B5,";"),"") | G5: Not Required
A6: APPMAPTG | C6: [ FUTURE ] | D6: Apportionment not planned for Cobra Web 1.0 | E6: =IF(AND(A6<>"",B6<>""),_xlfn.CONCAT("CREATE OR REPLACE VIEW ",A6," AS SELECT * FROM ",B6,";"),"") | G6: Not Required
A7: BASEDETL | B7: PROJECT_AUDIT_LOG_TPHASE | D7: This table holds the time phased detail that corresponds to a change logged in the Project_Audit_Log table | E7: =IF(AND(A7<>"",B7<>""),_xlfn.CONCAT("CREATE OR REPLACE VIEW ",A7," AS SELECT * FROM ",B7,";"),"") -> CREATE OR REPLACE VIEW BASEDETL AS SELECT * FROM PROJECT_AUDIT_LOG_TPHASE; | G7: Y
A8: BASEHIST | B8: PROJECT_AUDIT_LOG_HISTORY | D8: This table represents the end of period snapshot of totals for Control Accounts and Work Packages only. Note: I think this table might eventually go away and instead we'll take a snapshot of the materialized view of totals at period end, which might end up in different tables. For now, however, we will still convert this table | E8: =IF(AND(A8<>"",B8<>""),_xlfn.CONCAT("CREATE OR REPLACE VIEW ",A8," AS SELECT * FROM ",B8,";"),"") -> CREATE OR REPLACE VIEW BASEHIST AS SELECT * FROM PROJECT_AUDIT_LOG_HISTORY; | G8: Y
A9: BASELINE | B9: PROJECT_AUDIT_LOG_ACCOUNTS | D9: When a project's status date is advanced to the next period, we take a snapshot of the Project Account totals for the current period and store them in this table. | E9: =IF(AND(A9<>"",B9<>""),_xlfn.CONCAT("CREATE OR REPLACE VIEW ",A9," AS SELECT * FROM ",B9,";"),"") -> CREATE OR REPLACE VIEW BASELINE AS SELECT * FROM PROJECT_AUDIT_LOG_ACCOUNTS; | G9: Y
A10: BASELOG | B10: PROJECT_AUDIT_LOG | D10: Note 1: I think there was a situation where we got an entry added to this table other than when advancing the project status. Stewart will remember. | E10: =IF(AND(A10<>"",B10<>""),_xlfn.CONCAT("CREATE OR REPLACE VIEW ",A10," AS SELECT * FROM ",B10,";"),"") -> CREATE OR REPLACE VIEW BASELOG AS SELECT * FROM PROJECT_AUDIT_LOG; | G10: Y
A11: BATCH | C11: [ NONE ] | D11: Replaced by Reporting service | E11: =IF(AND(A11<>"",B11<>""),_xlfn.CONCAT("CREATE OR REPLACE VIEW ",A11," AS SELECT * FROM ",B11,";"),"") | G11: TBD
A12: BATCHREP | C12: [ NONE ] | D12: Replaced by Reporting service | E12: =IF(AND(A12<>"",B12<>""),_xlfn.CONCAT("CREATE OR REPLACE VIEW ",A12," AS SELECT * FROM ",B12,";"),"") | G12: TBD
A13: BDNDETL | B13: CODE | E13: =IF(AND(A13<>"",B13<>""),_xlfn.CONCAT("CREATE OR REPLACE VIEW ",A13," AS SELECT * FROM ",B13,";"),"") -> CREATE OR REPLACE VIEW BDNDETL AS SELECT * FROM CODE; | G13: Not Required
A14: BDNDETL | B14: CODE_THRESHOLD | E14: =IF(AND(A14<>"",B14<>""),_xlfn.CONCAT("CREATE OR REPLACE VIEW ",A14," AS SELECT * FROM ",B14,";"),"") -> CREATE OR REPLACE VIEW BDNDETL AS SELECT * FROM CODE_THRESHOLD; | G14: Not Required
A15: BREAKDWN | B15: CODE_FILE | E15: =IF(AND(A15<>"",B15<>""),_xlfn.CONCAT("CREATE OR REPLACE VIEW ",A15," AS SELECT * FROM ",B15,";"),"") -> CREATE OR REPLACE VIEW BREAKDWN AS SELECT * FROM CODE_FILE; | G15: Not Required
A16: CALC | B16: RESOURCE_FILE | E16: =IF(AND(A16<>"",B16<>""),_xlfn.CONCAT("CREATE OR REPLACE VIEW ",A16," AS SELECT * FROM ",B16,";"),"") -> CREATE OR REPLACE VIEW CALC AS SELECT * FROM RESOURCE_FILE; | G16: Y
A17: CALCDESC | B17: RESOURCES | E17: =IF(AND(A17<>"",B17<>""),_xlfn.CONCAT("CREATE OR REPLACE VIEW ",A17," AS SELECT * FROM ",B17,";"),"") -> CREATE OR REPLACE VIEW CALCDESC AS SELECT * FROM RESOURCES; | G17: Y
A18: CALCDETL | B18: RESOURCE_COST_CALCULATION | E18: =IF(AND(A18<>"",B18<>""),_xlfn.CONCAT("CREATE OR REPLACE VIEW ",A18," AS SELECT * FROM ",B18,";"),"") -> CREATE OR REPLACE VIEW CALCDETL AS SELECT * FROM RESOURCE_COST_CALCULATION; | G18: Y
A19: CALCEXPR | C19: No | D19: This stores UI column expressions. These will change for the Web product. | E19: =IF(AND(A19<>"",B19<>""),_xlfn.CONCAT("CREATE OR REPLACE VIEW ",A19," AS SELECT * FROM ",B19,";"),"") | G19: Not Required
A20: CALCFLDS | B20: PROJECT_CALC_RESULT | E20: =IF(AND(A20<>"",B20<>""),_xlfn.CONCAT("CREATE OR REPLACE VIEW ",A20," AS SELECT * FROM ",B20,";"),"") -> CREATE OR REPLACE VIEW CALCFLDS AS SELECT * FROM PROJECT_CALC_RESULT; | G20: Y
A21: CALCRESULT | B21: RESOURCE_FILE_COST_RESULT | E21: =IF(AND(A21<>"",B21<>""),_xlfn.CONCAT("CREATE OR REPLACE VIEW ",A21," AS SELECT * FROM ",B21,";"),"") -> CREATE OR REPLACE VIEW CALCRESULT AS SELECT * FROM RESOURCE_FILE_COST_RESULT; | G21: Y
A22: CAWP | B22: PROJECT_CONTROL_ACCOUNT | E22: =IF(AND(A22<>"",B22<>""),_xlfn.CONCAT("CREATE OR REPLACE VIEW ",A22," AS SELECT * FROM ",B22,";"),"") -> CREATE OR REPLACE VIEW CAWP AS SELECT * FROM PROJECT_CONTROL_ACCOUNT; | G22: Y
A23: CAWP | B23: PROJECT_WORK_PACKAGE | E23: =IF(AND(A23<>"",B23<>""),_xlfn.CONCAT("CREATE OR REPLACE VIEW ",A23," AS SELECT * FROM ",B23,";"),"") -> CREATE OR REPLACE VIEW CAWP AS SELECT * FROM PROJECT_WORK_PACKAGE; | G23: Y
A24: CAWP | B24: PROJECT_CAWP_TOTAL | E24: =IF(AND(A24<>"",B24<>""),_xlfn.CONCAT("CREATE OR REPLACE VIEW ",A24," AS SELECT * FROM ",B24,";"),"") -> CREATE OR REPLACE VIEW CAWP AS SELECT * FROM PROJECT_CAWP_TOTAL; | G24: Y
A25: CAWP | B25: USER_FIELD_VALUE | E25: =IF(AND(A25<>"",B25<>""),_xlfn.CONCAT("CREATE OR REPLACE VIEW ",A25," AS SELECT * FROM ",B25,";"),"") -> CREATE OR REPLACE VIEW CAWP AS SELECT * FROM USER_FIELD_VALUE; | G25: Y
A26: CAWP | B26: USER_NOTE_VALUE | E26: =IF(AND(A26<>"",B26<>""),_xlfn.CONCAT("CREATE OR REPLACE VIEW ",A26," AS SELECT * FROM ",B26,";"),"") -> CREATE OR REPLACE VIEW CAWP AS SELECT * FROM USER_NOTE_VALUE; | G26: Y
A27: CHNG_REQST | C27: [ FUTURE ] | D27: Change Requests not planned for Cobra Web 1.0 | E27: =IF(AND(A27<>"",B27<>""),_xlfn.CONCAT("CREATE OR REPLACE VIEW ",A27," AS SELECT * FROM ",B27,";"),"") | G27: Y
A28: CHNG_REQST_PROGRAM | C28: [ FUTURE ] | D28: Change Requests not planned for Cobra Web 1.0 | E28: =IF(AND(A28<>"",B28<>""),_xlfn.CONCAT("CREATE OR REPLACE VIEW ",A28," AS SELECT * FROM ",B28,";"),"") | G28: Y
A29: CLASSRANGES | C29: Yes | D29: Class Ranges not planned for Cobra Web 1.0 per Jamie/Kathy email 13Mar2025. Feature not required by migrating table so we can migrate the process code without having to change logic. | E29: =IF(AND(A29<>"",B29<>""),_xlfn.CONCAT("CREATE OR REPLACE VIEW ",A29," AS SELECT * FROM ",B29,";"),"") | G29: Y
A30: CLASSES | B30: PROJECT_COST_CLASS | E30: =IF(AND(A30<>"",B30<>""),_xlfn.CONCAT("CREATE OR REPLACE VIEW ",A30," AS SELECT * FROM ",B30,";"),"") -> CREATE OR REPLACE VIEW CLASSES AS SELECT * FROM PROJECT_COST_CLASS; | G30: Y
A31: CLASSESLINK | B31: PROJECT_COST_CLASS_LINK | E31: =IF(AND(A31<>"",B31<>""),_xlfn.CONCAT("CREATE OR REPLACE VIEW ",A31," AS SELECT * FROM ",B31,";"),"") -> CREATE OR REPLACE VIEW CLASSESLINK AS SELECT * FROM PROJECT_COST_CLASS_LINK; | G31: Y
A32: COB_CAT | B32: USER_FIELD_DEFINITION | E32: =IF(AND(A32<>"",B32<>""),_xlfn.CONCAT("CREATE OR REPLACE VIEW ",A32," AS SELECT * FROM ",B32,";"),"") -> CREATE OR REPLACE VIEW COB_CAT AS SELECT * FROM USER_FIELD_DEFINITION;
A33: COB_NTX | B33: USER_NOTE_VALUE | E33: =IF(AND(A33<>"",B33<>""),_xlfn.CONCAT("CREATE OR REPLACE VIEW ",A33," AS SELECT * FROM ",B33,";"),"") -> CREATE OR REPLACE VIEW COB_NTX AS SELECT * FROM USER_NOTE_VALUE;
A34: CODEFIELD | B34: USER_FIELD_DEFINITION | E34: =IF(AND(A34<>"",B34<>""),_xlfn.CONCAT("CREATE OR REPLACE VIEW ",A34," AS SELECT * FROM ",B34,";"),"") -> CREATE OR REPLACE VIEW CODEFIELD AS SELECT * FROM USER_FIELD_DEFINITION;
A35: CONFIG | B35: PRODUCT_CONFIG | E35: =IF(AND(A35<>"",B35<>""),_xlfn.CONCAT("CREATE OR REPLACE VIEW ",A35," AS SELECT * FROM ",B35,";"),"") -> CREATE OR REPLACE VIEW CONFIG AS SELECT * FROM PRODUCT_CONFIG;
A36: CONNECTION | C36: Yes | D36: Connection details for 3rd party service integration. We need to have a discussion about integration strategy. | E36: =IF(AND(A36<>"",B36<>""),_xlfn.CONCAT("CREATE OR REPLACE VIEW ",A36," AS SELECT * FROM ",B36,";"),"") | G36: Y
A37: COSTDETL | C37: Yes | D37: Migrate as is initially. | E37: =IF(AND(A37<>"",B37<>""),_xlfn.CONCAT("CREATE OR REPLACE VIEW ",A37," AS SELECT * FROM ",B37,";"),"") | G37: Y
A38: COSTELEM | B38: PROJECT_CAWP_RESOURCE | E38: =IF(AND(A38<>"",B38<>""),_xlfn.CONCAT("CREATE OR REPLACE VIEW ",A38," AS SELECT * FROM ",B38,";"),"") -> CREATE OR REPLACE VIEW COSTELEM AS SELECT * FROM PROJECT_CAWP_RESOURCE; | G38: Y
A39: COSTELEM | B39: USER_CODE_VALUE | E39: =IF(AND(A39<>"",B39<>""),_xlfn.CONCAT("CREATE OR REPLACE VIEW ",A39," AS SELECT * FROM ",B39,";"),"") -> CREATE OR REPLACE VIEW COSTELEM AS SELECT * FROM USER_CODE_VALUE;
A40: COSTREP | B40: PROJECT_COST_SET | E40: =IF(AND(A40<>"",B40<>""),_xlfn.CONCAT("CREATE OR REPLACE VIEW ",A40," AS SELECT * FROM ",B40,";"),"") -> CREATE OR REPLACE VIEW COSTREP AS SELECT * FROM PROJECT_COST_SET; | G40: Y
A41: COSTREPCLASS | B41: PROJECT_COST_SET_CLASS | E41: =IF(AND(A41<>"",B41<>""),_xlfn.CONCAT("CREATE OR REPLACE VIEW ",A41," AS SELECT * FROM ",B41,";"),"") -> CREATE OR REPLACE VIEW COSTREPCLASS AS SELECT * FROM PROJECT_COST_SET_CLASS; | G41: Y
A42: ENUMS | C42: [ NONE ] | D42: Obsolete. | E42: =IF(AND(A42<>"",B42<>""),_xlfn.CONCAT("CREATE OR REPLACE VIEW ",A42," AS SELECT * FROM ",B42,";"),"")
A43: FILTER | C43: [ NONE ] | D43: Replaced by Reporting service | E43: =IF(AND(A43<>"",B43<>""),_xlfn.CONCAT("CREATE OR REPLACE VIEW ",A43," AS SELECT * FROM ",B43,";"),"")
A44: FISCAL | B44: FISCAL_CALENDAR | E44: =IF(AND(A44<>"",B44<>""),_xlfn.CONCAT("CREATE OR REPLACE VIEW ",A44," AS SELECT * FROM ",B44,";"),"") -> CREATE OR REPLACE VIEW FISCAL AS SELECT * FROM FISCAL_CALENDAR; | G44: Y
A45: FISCDETL | B45: FISCAL_CALENDAR_PERIOD | E45: =IF(AND(A45<>"",B45<>""),_xlfn.CONCAT("CREATE OR REPLACE VIEW ",A45," AS SELECT * FROM ",B45,";"),"") -> CREATE OR REPLACE VIEW FISCDETL AS SELECT * FROM FISCAL_CALENDAR_PERIOD; | G45: Not Required
A46: FISCDETL | B46: FISCAL_CALENDAR_SET | E46: =IF(AND(A46<>"",B46<>""),_xlfn.CONCAT("CREATE OR REPLACE VIEW ",A46," AS SELECT * FROM ",B46,";"),"") -> CREATE OR REPLACE VIEW FISCDETL AS SELECT * FROM FISCAL_CALENDAR_SET; | G46: Not Required
A47: FISCDETL | B47: FISCAL_CALENDAR_SET_LABEL | E47: =IF(AND(A47<>"",B47<>""),_xlfn.CONCAT("CREATE OR REPLACE VIEW ",A47," AS SELECT * FROM ",B47,";"),"") -> CREATE OR REPLACE VIEW FISCDETL AS SELECT * FROM FISCAL_CALENDAR_SET_LABEL; | G47: Not Required
A48: FISCHOL | B48: FISCAL_CALENDAR_HOLIDAY | E48: =IF(AND(A48<>"",B48<>""),_xlfn.CONCAT("CREATE OR REPLACE VIEW ",A48," AS SELECT * FROM ",B48,";"),"") -> CREATE OR REPLACE VIEW FISCHOL AS SELECT * FROM FISCAL_CALENDAR_HOLIDAY; | G48: Not Required
A49: LINK | C49: Yes | D49: To be determined how we link CAWP to Schedule Tasks. | E49: =IF(AND(A49<>"",B49<>""),_xlfn.CONCAT("CREATE OR REPLACE VIEW ",A49," AS SELECT * FROM ",B49,";"),"") | G49: Y
A50: MILESTN | B50: PROJECT_WP_MILESTONE | E50: =IF(AND(A50<>"",B50<>""),_xlfn.CONCAT("CREATE OR REPLACE VIEW ",A50," AS SELECT * FROM ",B50,";"),"") -> CREATE OR REPLACE VIEW MILESTN AS SELECT * FROM PROJECT_WP_MILESTONE; | G50: Y
A51: MULTPROG | B51: PROJECT_SUBPROJECT | E51: =IF(AND(A51<>"",B51<>""),_xlfn.CONCAT("CREATE OR REPLACE VIEW ",A51," AS SELECT * FROM ",B51,";"),"") -> CREATE OR REPLACE VIEW MULTPROG AS SELECT * FROM PROJECT_SUBPROJECT; | G51: Y
A52: NARRTEXT | C52: No | D52: This will be replaced by the new user note table | E52: =IF(AND(A52<>"",B52<>""),_xlfn.CONCAT("CREATE OR REPLACE VIEW ",A52," AS SELECT * FROM ",B52,";"),"") | G52: Not Required
A53: PROCESSLOG | C53: Yes | D53: Migrate as is initially. Will be replaced ultimately by Apollo or other logging service, but initially process logs will go to these tables. | E53: =IF(AND(A53<>"",B53<>""),_xlfn.CONCAT("CREATE OR REPLACE VIEW ",A53," AS SELECT * FROM ",B53,";"),"") | G53: Y
A54: PROCESSLOGLINK | C54: Yes | D54: Migrate as is initially. Will be replaced ultimately by Apollo or other logging service, but initially process logs will go to these tables. | E54: =IF(AND(A54<>"",B54<>""),_xlfn.CONCAT("CREATE OR REPLACE VIEW ",A54," AS SELECT * FROM ",B54,";"),"") | G54: Y
A55: PROGRAM | B55: PROJECT | E55: =IF(AND(A55<>"",B55<>""),_xlfn.CONCAT("CREATE OR REPLACE VIEW ",A55," AS SELECT * FROM ",B55,";"),"") -> CREATE OR REPLACE VIEW PROGRAM AS SELECT * FROM PROJECT; | G55: Y
A56: PROGRAM | B56: PROJECT_COST_TOTAL | E56: =IF(AND(A56<>"",B56<>""),_xlfn.CONCAT("CREATE OR REPLACE VIEW ",A56," AS SELECT * FROM ",B56,";"),"") -> CREATE OR REPLACE VIEW PROGRAM AS SELECT * FROM PROJECT_COST_TOTAL;
A57: REPORT | C57: [ NONE ] | D57: Replaced by Reporting service | E57: =IF(AND(A57<>"",B57<>""),_xlfn.CONCAT("CREATE OR REPLACE VIEW ",A57," AS SELECT * FROM ",B57,";"),"")
A58: RATE | B58: RATE_FILE | E58: =IF(AND(A58<>"",B58<>""),_xlfn.CONCAT("CREATE OR REPLACE VIEW ",A58," AS SELECT * FROM ",B58,";"),"") -> CREATE OR REPLACE VIEW RATE AS SELECT * FROM RATE_FILE; | G58: Y
A59: RATEDESC | B59: RATE_SET | E59: =IF(AND(A59<>"",B59<>""),_xlfn.CONCAT("CREATE OR REPLACE VIEW ",A59," AS SELECT * FROM ",B59,";"),"") -> CREATE OR REPLACE VIEW RATEDESC AS SELECT * FROM RATE_SET; | G59: Y
A60: RATEDETL | B60: RATE | E60: =IF(AND(A60<>"",B60<>""),_xlfn.CONCAT("CREATE OR REPLACE VIEW ",A60," AS SELECT * FROM ",B60,";"),"") -> CREATE OR REPLACE VIEW RATEDETL AS SELECT * FROM RATE; | G60: Y
A61: RCUTOFF | C61: Yes | D61: Migrate as is initially. | E61: =IF(AND(A61<>"",B61<>""),_xlfn.CONCAT("CREATE OR REPLACE VIEW ",A61," AS SELECT * FROM ",B61,";"),"") | G61: Y
A62: RESTORE_RESULTS | C62: [ NONE ] | E62: =IF(AND(A62<>"",B62<>""),_xlfn.CONCAT("CREATE OR REPLACE VIEW ",A62," AS SELECT * FROM ",B62,";"),"")
A63: SETTING | B63: PRODUCT_PREFERENCE | E63: =IF(AND(A63<>"",B63<>""),_xlfn.CONCAT("CREATE OR REPLACE VIEW ",A63," AS SELECT * FROM ",B63,";"),"") -> CREATE OR REPLACE VIEW SETTING AS SELECT * FROM PRODUCT_PREFERENCE; | G63: Y
A64: SORT | C64: [ NONE ] | E64: =IF(AND(A64<>"",B64<>""),_xlfn.CONCAT("CREATE OR REPLACE VIEW ",A64," AS SELECT * FROM ",B64,";"),"")
A65: SPREAD | B65: SPREAD_CURVE | E65: =IF(AND(A65<>"",B65<>""),_xlfn.CONCAT("CREATE OR REPLACE VIEW ",A65," AS SELECT * FROM ",B65,";"),"") -> CREATE OR REPLACE VIEW SPREAD AS SELECT * FROM SPREAD_CURVE; | G65: Y
A66: TEMP_CAWPID | C66: Yes | D66: Migrate as is initially. | E66: =IF(AND(A66<>"",B66<>""),_xlfn.CONCAT("CREATE OR REPLACE VIEW ",A66," AS SELECT * FROM ",B66,";"),"") | G66: Y
A67: TEMP_CHAR | C67: Yes | D67: Migrate as is initially. | E67: =IF(AND(A67<>"",B67<>""),_xlfn.CONCAT("CREATE OR REPLACE VIEW ",A67," AS SELECT * FROM ",B67,";"),"") | G67: Y
A68: TEMP_DIR | C68: Yes | D68: Migrate as is initially. | E68: =IF(AND(A68<>"",B68<>""),_xlfn.CONCAT("CREATE OR REPLACE VIEW ",A68," AS SELECT * FROM ",B68,";"),"") | G68: Y
A69: TPHASE | B69: PROJECT_CAWP_RESOURCE_TPHASE | E69: =IF(AND(A69<>"",B69<>""),_xlfn.CONCAT("CREATE OR REPLACE VIEW ",A69," AS SELECT * FROM ",B69,";"),"") -> CREATE OR REPLACE VIEW TPHASE AS SELECT * FROM PROJECT_CAWP_RESOURCE_TPHASE; | G69: Y
A70: USERTBLS | C70: [ NONE ] | D70: Obsolete. | E70: =IF(AND(A70<>"",B70<>""),_xlfn.CONCAT("CREATE OR REPLACE VIEW ",A70," AS SELECT * FROM ",B70,";"),"")
A71: WST_ACL | B71: ACCESS_CONTROL_ENTRY | E71: =IF(AND(A71<>"",B71<>""),_xlfn.CONCAT("CREATE OR REPLACE VIEW ",A71," AS SELECT * FROM ",B71,";"),"") -> CREATE OR REPLACE VIEW WST_ACL AS SELECT * FROM ACCESS_CONTROL_ENTRY;
A72: WST_CDR | B72: CODE | E72: =IF(AND(A72<>"",B72<>""),_xlfn.CONCAT("CREATE OR REPLACE VIEW ",A72," AS SELECT * FROM ",B72,";"),"") -> CREATE OR REPLACE VIEW WST_CDR AS SELECT * FROM CODE;
A73: WST_CFG | B73: PRODUCT_CONFIG | E73: =IF(AND(A73<>"",B73<>""),_xlfn.CONCAT("CREATE OR REPLACE VIEW ",A73," AS SELECT * FROM ",B73,";"),"") -> CREATE OR REPLACE VIEW WST_CFG AS SELECT * FROM PRODUCT_CONFIG;
A74: WST_COD | B74: CODE_FILE | E74: =IF(AND(A74<>"",B74<>""),_xlfn.CONCAT("CREATE OR REPLACE VIEW ",A74," AS SELECT * FROM ",B74,";"),"") -> CREATE OR REPLACE VIEW WST_COD AS SELECT * FROM CODE_FILE;
A75: WST_DIR | C75: [ NONE ] | D75: Obsolete. Shared directory columns are now included in the relevant File tables. | E75: =IF(AND(A75<>"",B75<>""),_xlfn.CONCAT("CREATE OR REPLACE VIEW ",A75," AS SELECT * FROM ",B75,";"),"")
A76: WST_GRP | C76: [ NONE ] | D76: Obsolete. Groups are now part of UAM. | E76: =IF(AND(A76<>"",B76<>""),_xlfn.CONCAT("CREATE OR REPLACE VIEW ",A76," AS SELECT * FROM ",B76,";"),"")
A77: WST_LCK | C77: Yes | D77: File / Record Locks. | E77: =IF(AND(A77<>"",B77<>""),_xlfn.CONCAT("CREATE OR REPLACE VIEW ",A77," AS SELECT * FROM ",B77,";"),"") | G77: Y
A78: WST_NTX | B78: USER_NOTE_VALUE | D78: Stores Note Text Values for fields defined in the USER_FIELD_DEFINITION table. | E78: =IF(AND(A78<>"",B78<>""),_xlfn.CONCAT("CREATE OR REPLACE VIEW ",A78," AS SELECT * FROM ",B78,";"),"") -> CREATE OR REPLACE VIEW WST_NTX AS SELECT * FROM USER_NOTE_VALUE;
A79: WST_ROL | C79: [ NONE ] | D79: Obsolete. Roles are now part of UAM. | E79: =IF(AND(A79<>"",B79<>""),_xlfn.CONCAT("CREATE OR REPLACE VIEW ",A79," AS SELECT * FROM ",B79,";"),"")
A80: WST_UDF | B80: USER_FIELD_DEFINITION | D80: User Defined Field Definitions | E80: =IF(AND(A80<>"",B80<>""),_xlfn.CONCAT("CREATE OR REPLACE VIEW ",A80," AS SELECT * FROM ",B80,";"),"") -> CREATE OR REPLACE VIEW WST_UDF AS SELECT * FROM USER_FIELD_DEFINITION;
A81: WST_UDT | B81: USER_FIELD_VALUE | D81: User Defined Date Field Values are now stored in the USER_FIELD_VALUE table. | E81: =IF(AND(A81<>"",B81<>""),_xlfn.CONCAT("CREATE OR REPLACE VIEW ",A81," AS SELECT * FROM ",B81,";"),"") -> CREATE OR REPLACE VIEW WST_UDT AS SELECT * FROM USER_FIELD_VALUE;
A82: WST_UDU | B82: USER_FIELD_VALUE | D82: We are not using duration fields in Cobra
A83: WST_ULI | C83: No | D83: Managed by service/session/UAM. | E83: =IF(AND(A83<>"",B83<>""),_xlfn.CONCAT("CREATE OR REPLACE VIEW ",A83," AS SELECT * FROM ",B83,";"),"")
A84: WST_UNM | B84: USER_FIELD_VALUE | D84: User Defined Numeric Field Values are now stored in the USER_FIELD_VALUE table. | E84: =IF(AND(A84<>"",B84<>""),_xlfn.CONCAT("CREATE OR REPLACE VIEW ",A84," AS SELECT * FROM ",B84,";"),"") -> CREATE OR REPLACE VIEW WST_UNM AS SELECT * FROM USER_FIELD_VALUE;
A85: WST_UPA | C85: No | D85: User Product Mapping. Obsolete? Is this now UAM functionality? | E85: =IF(AND(A85<>"",B85<>""),_xlfn.CONCAT("CREATE OR REPLACE VIEW ",A85," AS SELECT * FROM ",B85,";"),"")
A86: WST_UPD | C86: [ NONE ] | D86: Obsolete. We no longer have default values for User Preferences. | E86: =IF(AND(A86<>"",B86<>""),_xlfn.CONCAT("CREATE OR REPLACE VIEW ",A86," AS SELECT * FROM ",B86,";"),"")
A87: WST_USG | C87: [ NONE ] | D87: Obsolete. User Group Assignments are now part of UAM. | E87: =IF(AND(A87<>"",B87<>""),_xlfn.CONCAT("CREATE OR REPLACE VIEW ",A87," AS SELECT * FROM ",B87,";"),"")
A88: WST_USR | C88: [ NONE ] | D88: Obsolete. Users are now part of UAM. | E88: =IF(AND(A88<>"",B88<>""),_xlfn.CONCAT("CREATE OR REPLACE VIEW ",A88," AS SELECT * FROM ",B88,";"),"")
A89: WST_UTX | B89: USER_FIELD_VALUE | D89: User Defined Text Field Values are now stored in the USER_FIELD_VALUE table. | E89: =IF(AND(A89<>"",B89<>""),_xlfn.CONCAT("CREATE OR REPLACE VIEW ",A89," AS SELECT * FROM ",B89,";"),"") -> CREATE OR REPLACE VIEW WST_UTX AS SELECT * FROM USER_FIELD_VALUE;

Sheet 8.5 -> Web  Column Mapping
A1: Domain | B1: Old Table Name | C1: Old Column Name | D1: New Table Name | E1: New Column Name | F1: Comments | G1: Old Table.Column | H1: New Table.Column | I1: Add Old Column to New Table? | J1: Add Column Name | K1: New Table.Old Column
A2: Codes | B2: BDNDETL | C2: BREAKFILE | D2: CODE | E2: CODE_FILE_UID | G2: =_xlfn.CONCAT(B2,".",C2) -> BDNDETL.BREAKFILE | H2: =_xlfn.CONCAT(D2,".",E2) -> CODE.CODE_FILE_UID | J2: =IF(ColumnMapping[[#This Row],[Add Old Column to New Table?]]<>"y","",_xlfn.CONCAT(VLOOKUP(ColumnMapping[[#This Row],[Old Table Name]],TableMapping[[#All],[Old Table Name]:[New Table Name]],2,),".",ColumnMapping[[#This Row],[Old Column Name]]))
A3: Codes | B3: BDNDETL | C3: CODE | D3: CODE | E3: NAME | G3: =_xlfn.CONCAT(B3,".",C3) -> BDNDETL.CODE | H3: =_xlfn.CONCAT(D3,".",E3) -> CODE.NAME | J3: =IF(ColumnMapping[[#This Row],[Add Old Column to New Table?]]<>"y","",_xlfn.CONCAT(VLOOKUP(ColumnMapping[[#This Row],[Old Table Name]],TableMapping[[#All],[Old Table Name]:[New Table Name]],2,),".",ColumnMapping[[#This Row],[Old Column Name]]))
A4: Codes | B4: BDNDETL | C4: TAG | D4: CODE | E4: TAG | F4: Tag no longer supported | G4: =_xlfn.CONCAT(B4,".",C4) -> BDNDETL.TAG | H4: =_xlfn.CONCAT(D4,".",E4) -> CODE.TAG | I4: y | J4: =IF(ColumnMapping[[#This Row],[Add Old Column to New Table?]]<>"y","",_xlfn.CONCAT(VLOOKUP(ColumnMapping[[#This Row],[Old Table Name]],TableMapping[[#All],[Old Table Name]:[New Table Name]],2,),".",ColumnMapping[[#This Row],[Old Column Name]])) -> CODE.TAG
A5: Codes | B5: BDNDETL | C5: NUM_CHILD | D5: CODE | E5: CHILD_COUNT | G5: =_xlfn.CONCAT(B5,".",C5) -> BDNDETL.NUM_CHILD | H5: =_xlfn.CONCAT(D5,".",E5) -> CODE.CHILD_COUNT | J5: =IF(ColumnMapping[[#This Row],[Add Old Column to New Table?]]<>"y","",_xlfn.CONCAT(VLOOKUP(ColumnMapping[[#This Row],[Old Table Name]],TableMapping[[#All],[Old Table Name]:[New Table Name]],2,),".",ColumnMapping[[#This Row],[Old Column Name]]))
A6: Codes | B6: BDNDETL | C6: CODEDESC | D6: CODE | E6: DESCRIPTION | G6: =_xlfn.CONCAT(B6,".",C6) -> BDNDETL.CODEDESC | H6: =_xlfn.CONCAT(D6,".",E6) -> CODE.DESCRIPTION | J6: =IF(ColumnMapping[[#This Row],[Add Old Column to New Table?]]<>"y","",_xlfn.CONCAT(VLOOKUP(ColumnMapping[[#This Row],[Old Table Name]],TableMapping[[#All],[Old Table Name]:[New Table Name]],2,),".",ColumnMapping[[#This Row],[Old Column Name]]))
A7: Codes | B7: BDNDETL | C7: D1 | D7: USER_CODE_VALUE | E7: CODE_UID | F7: Moved to USER_CODE_VALUE | G7: =_xlfn.CONCAT(B7,".",C7) -> BDNDETL.D1 | H7: =_xlfn.CONCAT(D7,".",E7) -> USER_CODE_VALUE.CODE_UID | J7: =IF(ColumnMapping[[#This Row],[Add Old Column to New Table?]]<>"y","",_xlfn.CONCAT(VLOOKUP(ColumnMapping[[#This Row],[Old Table Name]],TableMapping[[#All],[Old Table Name]:[New Table Name]],2,),".",ColumnMapping[[#This Row],[Old Column Name]]))
A8: Codes | B8: BDNDETL | C8: D2 | D8: USER_CODE_VALUE | E8: CODE_UID | F8: Moved to USER_CODE_VALUE | G8: =_xlfn.CONCAT(B8,".",C8) -> BDNDETL.D2 | H8: =_xlfn.CONCAT(D8,".",E8) -> USER_CODE_VALUE.CODE_UID | J8: =IF(ColumnMapping[[#This Row],[Add Old Column to New Table?]]<>"y","",_xlfn.CONCAT(VLOOKUP(ColumnMapping[[#This Row],[Old Table Name]],TableMapping[[#All],[Old Table Name]:[New Table Name]],2,),".",ColumnMapping[[#This Row],[Old Column Name]]))
A9: Codes | B9: BDNDETL | C9: D3 | D9: USER_CODE_VALUE | E9: CODE_UID | F9: Moved to USER_CODE_VALUE | G9: =_xlfn.CONCAT(B9,".",C9) -> BDNDETL.D3 | H9: =_xlfn.CONCAT(D9,".",E9) -> USER_CODE_VALUE.CODE_UID | J9: =IF(ColumnMapping[[#This Row],[Add Old Column to New Table?]]<>"y","",_xlfn.CONCAT(VLOOKUP(ColumnMapping[[#This Row],[Old Table Name]],TableMapping[[#All],[Old Table Name]:[New Table Name]],2,),".",ColumnMapping[[#This Row],[Old Column Name]]))
A10: Codes | B10: BDNDETL | C10: D4 | D10: USER_CODE_VALUE | E10: CODE_UID | F10: Moved to USER_CODE_VALUE | G10: =_xlfn.CONCAT(B10,".",C10) -> BDNDETL.D4 | H10: =_xlfn.CONCAT(D10,".",E10) -> USER_CODE_VALUE.CODE_UID | J10: =IF(ColumnMapping[[#This Row],[Add Old Column to New Table?]]<>"y","",_xlfn.CONCAT(VLOOKUP(ColumnMapping[[#This Row],[Old Table Name]],TableMapping[[#All],[Old Table Name]:[New Table Name]],2,),".",ColumnMapping[[#This Row],[Old Column Name]]))
A11: Codes | B11: BDNDETL | C11: D5 | D11: USER_CODE_VALUE | E11: CODE_UID | F11: Moved to USER_CODE_VALUE | G11: =_xlfn.CONCAT(B11,".",C11) -> BDNDETL.D5 | H11: =_xlfn.CONCAT(D11,".",E11) -> USER_CODE_VALUE.CODE_UID | J11: =IF(ColumnMapping[[#This Row],[Add Old Column to New Table?]]<>"y","",_xlfn.CONCAT(VLOOKUP(ColumnMapping[[#This Row],[Old Table Name]],TableMapping[[#All],[Old Table Name]:[New Table Name]],2,),".",ColumnMapping[[#This Row],[Old Column Name]]))
A12: Codes | B12: BDNDETL | C12: D6 | D12: USER_CODE_VALUE | E12: CODE_UID | F12: Moved to USER_CODE_VALUE | G12: =_xlfn.CONCAT(B12,".",C12) -> BDNDETL.D6 | H12: =_xlfn.CONCAT(D12,".",E12) -> USER_CODE_VALUE.CODE_UID | J12: =IF(ColumnMapping[[#This Row],[Add Old Column to New Table?]]<>"y","",_xlfn.CONCAT(VLOOKUP(ColumnMapping[[#This Row],[Old Table Name]],TableMapping[[#All],[Old Table Name]:[New Table Name]],2,),".",ColumnMapping[[#This Row],[Old Column Name]]))
A13: Codes | B13: BDNDETL | C13: D7 | D13: USER_CODE_VALUE | E13: CODE_UID | F13: Moved to USER_CODE_VALUE | G13: =_xlfn.CONCAT(B13,".",C13) -> BDNDETL.D7 | H13: =_xlfn.CONCAT(D13,".",E13) -> USER_CODE_VALUE.CODE_UID | J13: =IF(ColumnMapping[[#This Row],[Add Old Column to New Table?]]<>"y","",_xlfn.CONCAT(VLOOKUP(ColumnMapping[[#This Row],[Old Table Name]],TableMapping[[#All],[Old Table Name]:[New Table Name]],2,),".",ColumnMapping[[#This Row],[Old Column Name]]))
A14: Codes | B14: BDNDETL | C14: D8 | D14: USER_CODE_VALUE | E14: CODE_UID | F14: Moved to USER_CODE_VALUE | G14: =_xlfn.CONCAT(B14,".",C14) -> BDNDETL.D8 | H14: =_xlfn.CONCAT(D14,".",E14) -> USER_CODE_VALUE.CODE_UID | J14: =IF(ColumnMapping[[#This Row],[Add Old Column to New Table?]]<>"y","",_xlfn.CONCAT(VLOOKUP(ColumnMapping[[#This Row],[Old Table Name]],TableMapping[[#All],[Old Table Name]:[New Table Name]],2,),".",ColumnMapping[[#This Row],[Old Column Name]]))
A15: Codes | B15: BDNDETL | C15: D9 | D15: USER_CODE_VALUE | E15: CODE_UID | F15: Moved to USER_CODE_VALUE | G15: =_xlfn.CONCAT(B15,".",C15) -> BDNDETL.D9 | H15: =_xlfn.CONCAT(D15,".",E15) -> USER_CODE_VALUE.CODE_UID | J15: =IF(ColumnMapping[[#This Row],[Add Old Column to New Table?]]<>"y","",_xlfn.CONCAT(VLOOKUP(ColumnMapping[[#This Row],[Old Table Name]],TableMapping[[#All],[Old Table Name]:[New Table Name]],2,),".",ColumnMapping[[#This Row],[Old Column Name]]))
A16: Codes | B16: BDNDETL | C16: PARENT | D16: CODE | E16: PARENT_CODE_UID | G16: =_xlfn.CONCAT(B16,".",C16) -> BDNDETL.PARENT | H16: =_xlfn.CONCAT(D16,".",E16) -> CODE.PARENT_CODE_UID | J16: =IF(ColumnMapping[[#This Row],[Add Old Column to New Table?]]<>"y","",_xlfn.CONCAT(VLOOKUP(ColumnMapping[[#This Row],[Old Table Name]],TableMapping[[#All],[Old Table Name]:[New Table Name]],2,),".",ColumnMapping[[#This Row],[Old Column Name]]))
A17: Codes | B17: BDNDETL | C17: BDN_LEVEL | D17: CODE | E17: CODE_LEVEL | G17: =_xlfn.CONCAT(B17,".",C17) -> BDNDETL.BDN_LEVEL | H17: =_xlfn.CONCAT(D17,".",E17) -> CODE.CODE_LEVEL | J17: =IF(ColumnMapping[[#This Row],[Add Old Column to New Table?]]<>"y","",_xlfn.CONCAT(VLOOKUP(ColumnMapping[[#This Row],[Old Table Name]],TableMapping[[#All],[Old Table Name]:[New Table Name]],2,),".",ColumnMapping[[#This Row],[Old Column Name]]))
A18: Codes | B18: BDNDETL | C18: SEQUENCE | D18: CODE | E18: SEQUENCE | G18: =_xlfn.CONCAT(B18,".",C18) -> BDNDETL.SEQUENCE | H18: =_xlfn.CONCAT(D18,".",E18) -> CODE.SEQUENCE | J18: =IF(ColumnMapping[[#This Row],[Add Old Column to New Table?]]<>"y","",_xlfn.CONCAT(VLOOKUP(ColumnMapping[[#This Row],[Old Table Name]],TableMapping[[#All],[Old Table Name]:[New Table Name]],2,),".",ColumnMapping[[#This Row],[Old Column Name]]))
A19: Codes | B19: BDNDETL | C19: LASTUPDATE | D19: CODE | E19: LAST_MODIFIED_DATE | G19: =_xlfn.CONCAT(B19,".",C19) -> BDNDETL.LASTUPDATE | H19: =_xlfn.CONCAT(D19,".",E19) -> CODE.LAST_MODIFIED_DATE | J19: =IF(ColumnMapping[[#This Row],[Add Old Column to New Table?]]<>"y","",_xlfn.CONCAT(VLOOKUP(ColumnMapping[[#This Row],[Old Table Name]],TableMapping[[#All],[Old Table Name]:[New Table Name]],2,),".",ColumnMapping[[#This Row],[Old Column Name]]))
A20: Codes | B20: BDNDETL | C20: USR_ID | D20: CODE | E20: LAST_MODIFIED_BY_USER_UID | G20: =_xlfn.CONCAT(B20,".",C20) -> BDNDETL.USR_ID | H20: =_xlfn.CONCAT(D20,".",E20) -> CODE.LAST_MODIFIED_BY_USER_UID | J20: =IF(ColumnMapping[[#This Row],[Add Old Column to New Table?]]<>"y","",_xlfn.CONCAT(VLOOKUP(ColumnMapping[[#This Row],[Old Table Name]],TableMapping[[#All],[Old Table Name]:[New Table Name]],2,),".",ColumnMapping[[#This Row],[Old Column Name]]))
A21: Codes | B21: BDNDETL | C21: BREAKFILE | F21: GrandParent key Code File Identifieer is no longer included on the CODE_THRESHOLD record. | G21: =_xlfn.CONCAT(B21,".",C21) -> BDNDETL.BREAKFILE | H21: =_xlfn.CONCAT(D21,".",E21) -> . | I21: y | J21: =IF(ColumnMapping[[#This Row],[Add Old Column to New Table?]]<>"y","",_xlfn.CONCAT(VLOOKUP(ColumnMapping[[#This Row],[Old Table Name]],TableMapping[[#All],[Old Table Name]:[New Table Name]],2,),".",ColumnMapping[[#This Row],[Old Column Name]])) -> CODE.BREAKFILE
A22: Codes | B22: BDNDETL | C22: TH_SPVF | D22: CODE_THRESHOLD | E22: SPVF | G22: =_xlfn.CONCAT(B22,".",C22) -> BDNDETL.TH_SPVF | H22: =_xlfn.CONCAT(D22,".",E22) -> CODE_THRESHOLD.SPVF | J22: =IF(ColumnMapping[[#This Row],[Add Old Column to New Table?]]<>"y","",_xlfn.CONCAT(VLOOKUP(ColumnMapping[[#This Row],[Old Table Name]],TableMapping[[#All],[Old Table Name]:[New Table Name]],2,),".",ColumnMapping[[#This Row],[Old Column Name]]))
A23: Codes | B23: BDNDETL | C23: TH_SPVU | D23: CODE_THRESHOLD | E23: SPVU | G23: =_xlfn.CONCAT(B23,".",C23) -> BDNDETL.TH_SPVU | H23: =_xlfn.CONCAT(D23,".",E23) -> CODE_THRESHOLD.SPVU | J23: =IF(ColumnMapping[[#This Row],[Add Old Column to New Table?]]<>"y","",_xlfn.CONCAT(VLOOKUP(ColumnMapping[[#This Row],[Old Table Name]],TableMapping[[#All],[Old Table Name]:[New Table Name]],2,),".",ColumnMapping[[#This Row],[Old Column Name]]))
A24: Codes | B24: BDNDETL | C24: TH_SPPF | D24: CODE_THRESHOLD | E24: SPPF | G24: =_xlfn.CONCAT(B24,".",C24) -> BDNDETL.TH_SPPF | H24: =_xlfn.CONCAT(D24,".",E24) -> CODE_THRESHOLD.SPPF | J24: =IF(ColumnMapping[[#This Row],[Add Old Column to New Table?]]<>"y","",_xlfn.CONCAT(VLOOKUP(ColumnMapping[[#This Row],[Old Table Name]],TableMapping[[#All],[Old Table Name]:[New Table Name]],2,),".",ColumnMapping[[#This Row],[Old Column Name]]))
A25: Codes | B25: BDNDETL | C25: TH_SPPU | D25: CODE_THRESHOLD | E25: SPPU | G25: =_xlfn.CONCAT(B25,".",C25) -> BDNDETL.TH_SPPU | H25: =_xlfn.CONCAT(D25,".",E25) -> CODE_THRESHOLD.SPPU | J25: =IF(ColumnMapping[[#This Row],[Add Old Column to New Table?]]<>"y","",_xlfn.CONCAT(VLOOKUP(ColumnMapping[[#This Row],[Old Table Name]],TableMapping[[#All],[Old Table Name]:[New Table Name]],2,),".",ColumnMapping[[#This Row],[Old Column Name]]))
A26: Codes | B26: BDNDETL | C26: TH_SCVF | D26: CODE_THRESHOLD | E26: SCVF | G26: =_xlfn.CONCAT(B26,".",C26) -> BDNDETL.TH_SCVF | H26: =_xlfn.CONCAT(D26,".",E26) -> CODE_THRESHOLD.SCVF | J26: =IF(ColumnMapping[[#This Row],[Add Old Column to New Table?]]<>"y","",_xlfn.CONCAT(VLOOKUP(ColumnMapping[[#This Row],[Old Table Name]],TableMapping[[#All],[Old Table Name]:[New Table Name]],2,),".",ColumnMapping[[#This Row],[Old Column Name]]))
A27: Codes | B27: BDNDETL | C27: TH_SCVU | D27: CODE_THRESHOLD | E27: SCVU | G27: =_xlfn.CONCAT(B27,".",C27) -> BDNDETL.TH_SCVU | H27: =_xlfn.CONCAT(D27,".",E27) -> CODE_THRESHOLD.SCVU | J27: =IF(ColumnMapping[[#This Row],[Add Old Column to New Table?]]<>"y","",_xlfn.CONCAT(VLOOKUP(ColumnMapping[[#This Row],[Old Table Name]],TableMapping[[#All],[Old Table Name]:[New Table Name]],2,),".",ColumnMapping[[#This Row],[Old Column Name]]))
A28: Codes | B28: BDNDETL | C28: TH_SCPF | D28: CODE_THRESHOLD | E28: SCPF | G28: =_xlfn.CONCAT(B28,".",C28) -> BDNDETL.TH_SCPF | H28: =_xlfn.CONCAT(D28,".",E28) -> CODE_THRESHOLD.SCPF | J28: =IF(ColumnMapping[[#This Row],[Add Old Column to New Table?]]<>"y","",_xlfn.CONCAT(VLOOKUP(ColumnMapping[[#This Row],[Old Table Name]],TableMapping[[#All],[Old Table Name]:[New Table Name]],2,),".",ColumnMapping[[#This Row],[Old Column Name]]))
A29: Codes | B29: BDNDETL | C29: TH_SCPU | D29: CODE_THRESHOLD | E29: SCPU | G29: =_xlfn.CONCAT(B29,".",C29) -> BDNDETL.TH_SCPU | H29: =_xlfn.CONCAT(D29,".",E29) -> CODE_THRESHOLD.SCPU | J29: =IF(ColumnMapping[[#This Row],[Add Old Column to New Table?]]<>"y","",_xlfn.CONCAT(VLOOKUP(ColumnMapping[[#This Row],[Old Table Name]],TableMapping[[#All],[Old Table Name]:[New Table Name]],2,),".",ColumnMapping[[#This Row],[Old Column Name]]))
A30: Codes | B30: BDNDETL | C30: TH_CPVF | D30: CODE_THRESHOLD | E30: CPVF | G30: =_xlfn.CONCAT(B30,".",C30) -> BDNDETL.TH_CPVF | H30: =_xlfn.CONCAT(D30,".",E30) -> CODE_THRESHOLD.CPVF | J30: =IF(ColumnMapping[[#This Row],[Add Old Column to New Table?]]<>"y","",_xlfn.CONCAT(VLOOKUP(ColumnMapping[[#This Row],[Old Table Name]],TableMapping[[#All],[Old Table Name]:[New Table Name]],2,),".",ColumnMapping[[#This Row],[Old Column Name]]))
A31: Codes | B31: BDNDETL | C31: TH_CPVU | D31: CODE_THRESHOLD | E31: CPVU | G31: =_xlfn.CONCAT(B31,".",C31) -> BDNDETL.TH_CPVU | H31: =_xlfn.CONCAT(D31,".",E31) -> CODE_THRESHOLD.CPVU | J31: =IF(ColumnMapping[[#This Row],[Add Old Column to New Table?]]<>"y","",_xlfn.CONCAT(VLOOKUP(ColumnMapping[[#This Row],[Old Table Name]],TableMapping[[#All],[Old Table Name]:[New Table Name]],2,),".",ColumnMapping[[#This Row],[Old Column Name]]))
A32: Codes | B32: BDNDETL | C32: TH_CPPF | D32: CODE_THRESHOLD | E32: CPPF | G32: =_xlfn.CONCAT(B32,".",C32) -> BDNDETL.TH_CPPF | H32: =_xlfn.CONCAT(D32,".",E32) -> CODE_THRESHOLD.CPPF | J32: =IF(ColumnMapping[[#This Row],[Add Old Column to New Table?]]<>"y","",_xlfn.CONCAT(VLOOKUP(ColumnMapping[[#This Row],[Old Table Name]],TableMapping[[#All],[Old Table Name]:[New Table Name]],2,),".",ColumnMapping[[#This Row],[Old Column Name]]))
A33: Codes | B33: BDNDETL | C33: TH_CPPU | D33: CODE_THRESHOLD | E33: CPPU | G33: =_xlfn.CONCAT(B33,".",C33) -> BDNDETL.TH_CPPU | H33: =_xlfn.CONCAT(D33,".",E33) -> CODE_THRESHOLD.CPPU | J33: =IF(ColumnMapping[[#This Row],[Add Old Column to New Table?]]<>"y","",_xlfn.CONCAT(VLOOKUP(ColumnMapping[[#This Row],[Old Table Name]],TableMapping[[#All],[Old Table Name]:[New Table Name]],2,),".",ColumnMapping[[#This Row],[Old Column Name]]))
... A53: Codes | B53: BREAKDWN | C53: BREAKTYPE | D53: CODE_FILE | E53: CODE_TYPE | G53: =_xlfn.CONCAT(B53,".",C53) -> BREAKDWN.BREAKTYPE | H53: =_xlfn.CONCAT(D53,".",E53) -> CODE_FILE.CODE_TYPE | J53: =IF(ColumnMapping[[#This Row],[Add Old Column to New Table?]]<>"y","",_xlfn.CONCAT(VLOOKUP(ColumnMapping[[#This Row],[Old Table Name]],TableMapping[[#All],[Old Table Name]:[New Table Name]],2,),".",ColumnMapping[[#This Row],[Old Column Name]]))
A54: Codes | B54: BREAKDWN | C54: CODELENGTH | D54: CODE_FILE | E54: CODELENGTH | F54: Fixed-format Codes no longer supported. | G54: =_xlfn.CONCAT(B54,".",C54) -> BREAKDWN.CODELENGTH | H54: =_xlfn.CONCAT(D54,".",E54) -> CODE_FILE.CODELENGTH | I54: y | J54: =IF(ColumnMapping[[#This Row],[Add Old Column to New Table?]]<>"y","",_xlfn.CONCAT(VLOOKUP(ColumnMapping[[#This Row],[Old Table Name]],TableMapping[[#All],[Old Table Name]:[New Table Name]],2,),".",ColumnMapping[[#This Row],[Old Column Name]])) -> CODE_FILE.CODELENGTH
A55: Codes | B55: BREAKDWN | C55: MAX_LEVEL | D55: CODE_FILE | E55: MAX_LEVEL | F55: Fixed-format Codes no longer supported. | G55: =_xlfn.CONCAT(B55,".",C55) -> BREAKDWN.MAX_LEVEL | H55: =_xlfn.CONCAT(D55,".",E55) -> CODE_FILE.MAX_LEVEL | I55: y | J55: =IF(ColumnMapping[[#This Row],[Add Old Column to New Table?]]<>"y","",_xlfn.CONCAT(VLOOKUP(ColumnMapping[[#This Row],[Old Table Name]],TableMapping[[#All],[Old Table Name]:[New Table Name]],2,),".",ColumnMapping[[#This Row],[Old Column Name]])) -> CODE_FILE.MAX_LEVEL
A56: Codes | B56: BREAKDWN | C56: PAD_CHAR | D56: CODE_FILE | E56: PAD_CHAR | F56: Pad Character no longer supported since Fixed Format is not supported. Punctuated Codes will always use a period. | G56: =_xlfn.CONCAT(B56,".",C56) -> BREAKDWN.PAD_CHAR | H56: =_xlfn.CONCAT(D56,".",E56) -> CODE_FILE.PAD_CHAR | I56: y | J56: =IF(ColumnMapping[[#This Row],[Add Old Column to New Table?]]<>"y","",_xlfn.CONCAT(VLOOKUP(ColumnMapping[[#This Row],[Old Table Name]],TableMapping[[#All],[Old Table Name]:[New Table Name]],2,),".",ColumnMapping[[#This Row],[Old Column Name]])) -> CODE_FILE.PAD_CHAR
A57: Codes | B57: BREAKDWN | C57: TH_FLAGS | D57: CODE_FILE | E57: TH_FLAGS | G57: =_xlfn.CONCAT(B57,".",C57) -> BREAKDWN.TH_FLAGS | H57: =_xlfn.CONCAT(D57,".",E57) -> CODE_FILE.TH_FLAGS | J57: CODE_FILE.TH_FLAGS
A58: Codes | B58: BREAKDWN | C58: LEVEL1 | D58: CODE_FILE | E58: LEVEL1 | F58: Fixed-format Codes no longer supported. | G58: =_xlfn.CONCAT(B58,".",C58) -> BREAKDWN.LEVEL1 | H58: =_xlfn.CONCAT(D58,".",E58) -> CODE_FILE.LEVEL1 | I58: y | J58: =IF(ColumnMapping[[#This Row],[Add Old Column to New Table?]]<>"y","",_xlfn.CONCAT(VLOOKUP(ColumnMapping[[#This Row],[Old Table Name]],TableMapping[[#All],[Old Table Name]:[New Table Name]],2,),".",ColumnMapping[[#This Row],[Old Column Name]])) -> CODE_FILE.LEVEL1
A59: Codes | B59: BREAKDWN | C59: LEVEL2 | D59: CODE_FILE | E59: LEVEL2 | F59: Fixed-format Codes no longer supported. | G59: =_xlfn.CONCAT(B59,".",C59) -> BREAKDWN.LEVEL2 | H59: =_xlfn.CONCAT(D59,".",E59) -> CODE_FILE.LEVEL2 | I59: y | J59: =IF(ColumnMapping[[#This Row],[Add Old Column to New Table?]]<>"y","",_xlfn.CONCAT(VLOOKUP(ColumnMapping[[#This Row],[Old Table Name]],TableMapping[[#All],[Old Table Name]:[New Table Name]],2,),".",ColumnMapping[[#This Row],[Old Column Name]])) -> CODE_FILE.LEVEL2
A60: Codes | B60: BREAKDWN | C60: LEVEL3 | D60: CODE_FILE | E60: LEVEL3 | F60: Fixed-format Codes no longer supported. | G60: =_xlfn.CONCAT(B60,".",C60) -> BREAKDWN.LEVEL3 | H60: =_xlfn.CONCAT(D60,".",E60) -> CODE_FILE.LEVEL3 | I60: y | J60: =IF(ColumnMapping[[#This Row],[Add Old Column to New Table?]]<>"y","",_xlfn.CONCAT(VLOOKUP(ColumnMapping[[#This Row],[Old Table Name]],TableMapping[[#All],[Old Table Name]:[New Table Name]],2,),".",ColumnMapping[[#This Row],[Old Column Name]])) -> CODE_FILE.LEVEL3
A61: Codes | B61: BREAKDWN | C61: LEVEL4 | D61: CODE_FILE | E61: LEVEL4 | F61: Fixed-format Codes no longer supported. | G61: =_xlfn.CONCAT(B61,".",C61) -> BREAKDWN.LEVEL4 | H61: =_xlfn.CONCAT(D61,".",E61) -> CODE_FILE.LEVEL4 | I61: y | J61: =IF(ColumnMapping[[#This Row],[Add Old Column to New Table?]]<>"y","",_xlfn.CONCAT(VLOOKUP(ColumnMapping[[#This Row],[Old Table Name]],TableMapping[[#All],[Old Table Name]:[New Table Name]],2,),".",ColumnMapping[[#This Row],[Old Column Name]])) -> CODE_FILE.LEVEL4
A62: Codes | B62: BREAKDWN | C62: LEVEL5 | D62: CODE_FILE | E62: LEVEL5 | F62: Fixed-format Codes no longer supported. | G62: =_xlfn.CONCAT(B62,".",C62) -> BREAKDWN.LEVEL5 | H62: =_xlfn.CONCAT(D62,".",E62) -> CODE_FILE.LEVEL5 | I62: y | J62: =IF(ColumnMapping[[#This Row],[Add Old Column to New Table?]]<>"y","",_xlfn.CONCAT(VLOOKUP(ColumnMapping[[#This Row],[Old Table Name]],TableMapping[[#All],[Old Table Name]:[New Table Name]],2,),".",ColumnMapping[[#This Row],[Old Column Name]])) -> CODE_FILE.LEVEL5
A63: Codes | B63: BREAKDWN | C63: LEVEL6 | D63: CODE_FILE | E63: LEVEL6 | F63: Fixed-format Codes no longer supported. | G63: =_xlfn.CONCAT(B63,".",C63) -> BREAKDWN.LEVEL6 | H63: =_xlfn.CONCAT(D63,".",E63) -> CODE_FILE.LEVEL6 | I63: y | J63: =IF(ColumnMapping[[#This Row],[Add Old Column to New Table?]]<>"y","",_xlfn.CONCAT(VLOOKUP(ColumnMapping[[#This Row],[Old Table Name]],TableMapping[[#All],[Old Table Name]:[New Table Name]],2,),".",ColumnMapping[[#This Row],[Old Column Name]])) -> CODE_FILE.LEVEL6
A64: Codes | B64: BREAKDWN | C64: LEVEL7 | D64: CODE_FILE | E64: LEVEL7 | F64: Fixed-format Codes no longer supported. | G64: =_xlfn.CONCAT(B64,".",C64) -> BREAKDWN.LEVEL7 | H64: =_xlfn.CONCAT(D64,".",E64) -> CODE_FILE.LEVEL7 | I64: y | J64: =IF(ColumnMapping[[#This Row],[Add Old Column to New Table?]]<>"y","",_xlfn.CONCAT(VLOOKUP(ColumnMapping[[#This Row],[Old Table Name]],TableMapping[[#All],[Old Table Name]:[New Table Name]],2,),".",ColumnMapping[[#This Row],[Old Column Name]])) -> CODE_FILE.LEVEL7
A65: Codes | B65: BREAKDWN | C65: LEVEL8 | D65: CODE_FILE | E65: LEVEL8 | F65: Fixed-format Codes no longer supported. | G65: =_xlfn.CONCAT(B65,".",C65) -> BREAKDWN.LEVEL8 | H65: =_xlfn.CONCAT(D65,".",E65) -> CODE_FILE.LEVEL8 | I65: y | J65: =IF(ColumnMapping[[#This Row],[Add Old Column to New Table?]]<>"y","",_xlfn.CONCAT(VLOOKUP(ColumnMapping[[#This Row],[Old Table Name]],TableMapping[[#All],[Old Table Name]:[New Table Name]],2,),".",ColumnMapping[[#This Row],[Old Column Name]])) -> CODE_FILE.LEVEL8
A66: Codes | B66: BREAKDWN | C66: LEVEL9 | D66: CODE_FILE | E66: LEVEL9 | F66: Fixed-format Codes no longer supported. | G66: =_xlfn.CONCAT(B66,".",C66) -> BREAKDWN.LEVEL9 | H66: =_xlfn.CONCAT(D66,".",E66) -> CODE_FILE.LEVEL9 | I66: y | J66: =IF(ColumnMapping[[#This Row],[Add Old Column to New Table?]]<>"y","",_xlfn.CONCAT(VLOOKUP(ColumnMapping[[#This Row],[Old Table Name]],TableMapping[[#All],[Old Table Name]:[New Table Name]],2,),".",ColumnMapping[[#This Row],[Old Column Name]])) -> CODE_FILE.LEVEL9
A67: Codes | B67: BREAKDWN | C67: LEVEL10 | D67: CODE_FILE | E67: LEVEL10 | F67: Fixed-format Codes no longer supported. | G67: =_xlfn.CONCAT(B67,".",C67) -> BREAKDWN.LEVEL10 | H67: =_xlfn.CONCAT(D67,".",E67) -> CODE_FILE.LEVEL10 | I67: y | J67: =IF(ColumnMapping[[#This Row],[Add Old Column to New Table?]]<>"y","",_xlfn.CONCAT(VLOOKUP(ColumnMapping[[#This Row],[Old Table Name]],TableMapping[[#All],[Old Table Name]:[New Table Name]],2,),".",ColumnMapping[[#This Row],[Old Column Name]])) -> CODE_FILE.LEVEL10
A68: Codes | B68: BREAKDWN | C68: LEVEL11 | D68: CODE_FILE | E68: LEVEL11 | F68: Fixed-format Codes no longer supported. | G68: =_xlfn.CONCAT(B68,".",C68) -> BREAKDWN.LEVEL11 | H68: =_xlfn.CONCAT(D68,".",E68) -> CODE_FILE.LEVEL11 | I68: y | J68: =IF(ColumnMapping[[#This Row],[Add Old Column to New Table?]]<>"y","",_xlfn.CONCAT(VLOOKUP(ColumnMapping[[#This Row],[Old Table Name]],TableMapping[[#All],[Old Table Name]:[New Table Name]],2,),".",ColumnMapping[[#This Row],[Old Column Name]])) -> CODE_FILE.LEVEL11
A69: Codes | B69: BREAKDWN | C69: LEVEL12 | D69: CODE_FILE | E69: LEVEL12 | F69: Fixed-format Codes no longer supported. | G69: =_xlfn.CONCAT(B69,".",C69) -> BREAKDWN.LEVEL12 | H69: =_xlfn.CONCAT(D69,".",E69) -> CODE_FILE.LEVEL12 | I69: y | J69: =IF(ColumnMapping[[#This Row],[Add Old Column to New Table?]]<>"y","",_xlfn.CONCAT(VLOOKUP(ColumnMapping[[#This Row],[Old Table Name]],TableMapping[[#All],[Old Table Name]:[New Table Name]],2,),".",ColumnMapping[[#This Row],[Old Column Name]])) -> CODE_FILE.LEVEL12
... A77: Codes | B77: BREAKDWN | C77: LEVEL20 | D77: CODE_FILE | E77: LEVEL20 | F77: Fixed-format Codes no longer supported. | G77: =_xlfn.CONCAT(B77,".",C77) -> BREAKDWN.LEVEL20 | H77: =_xlfn.CONCAT(D77,".",E77) -> CODE_FILE.LEVEL20 | I77: y | J77: =IF(ColumnMapping[[#This Row],[Add Old Column to New Table?]]<>"y","",_xlfn.CONCAT(VLOOKUP(ColumnMapping[[#This Row],[Old Table Name]],TableMapping[[#All],[Old Table Name]:[New Table Name]],2,),".",ColumnMapping[[#This Row],[Old Column Name]])) -> CODE_FILE.LEVEL20
A78: Codes | B78: BREAKDWN | C78: SEQUENCE | D78: CODE_FILE | E78: SEQUENCE | G78: =_xlfn.CONCAT(B78,".",C78) -> BREAKDWN.SEQUENCE | H78: =_xlfn.CONCAT(D78,".",E78) -> CODE_FILE.SEQUENCE | J78: =IF(ColumnMapping[[#This Row],[Add Old Column to New Table?]]<>"y","",_xlfn.CONCAT(VLOOKUP(ColumnMapping[[#This Row],[Old Table Name]],TableMapping[[#All],[Old Table Name]:[New Table Name]],2,),".",ColumnMapping[[#This Row],[Old Column Name]]))
A79: Codes | B79: BREAKDWN | C79: LASTUPDATE | D79: CODE_FILE | E79: LAST_MODIFIED_DATE | G79: =_xlfn.CONCAT(B79,".",C79) -> BREAKDWN.LASTUPDATE | H79: =_xlfn.CONCAT(D79,".",E79) -> CODE_FILE.LAST_MODIFIED_DATE | J79: =IF(ColumnMapping[[#This Row],[Add Old Column to New Table?]]<>"y","",_xlfn.CONCAT(VLOOKUP(ColumnMapping[[#This Row],[Old Table Name]],TableMapping[[#All],[Old Table Name]:[New Table Name]],2,),".",ColumnMapping[[#This Row],[Old Column Name]]))
A80: Codes | B80: BREAKDWN | C80: USR_ID | D80: CODE_FILE | E80: LAST_MODIFIED_BY_USER_UID | G80: =_xlfn.CONCAT(B80,".",C80) -> BREAKDWN.USR_ID | H80: =_xlfn.CONCAT(D80,".",E80) -> CODE_FILE.LAST_MODIFIED_BY_USER_UID | J80: =IF(ColumnMapping[[#This Row],[Add Old Column to New Table?]]<>"y","",_xlfn.CONCAT(VLOOKUP(ColumnMapping[[#This Row],[Old Table Name]],TableMapping[[#All],[Old Table Name]:[New Table Name]],2,),".",ColumnMapping[[#This Row],[Old Column Name]]))
A81: Codes | D81: CODE | E81: ROW_UID | G81: =_xlfn.CONCAT(B81,".",C81) -> . | H81: =_xlfn.CONCAT(D81,".",E81) -> CODE.ROW_UID | J81: =IF(ColumnMapping[[#This Row],[Add Old Column to New Table?]]<>"y","",_xlfn.CONCAT(VLOOKUP(ColumnMapping[[#This Row],[Old Table Name]],TableMapping[[#All],[Old Table Name]:[New Table Name]],2,),".",ColumnMapping[[#This Row],[Old Column Name]]))
A82: Codes | D82: CODE | E82: CHILD_POS | G82: =_xlfn.CONCAT(B82,".",C82) -> . | H82: =_xlfn.CONCAT(D82,".",E82) -> CODE.CHILD_POS | J82: =IF(ColumnMapping[[#This Row],[Add Old Column to New Table?]]<>"y","",_xlfn.CONCAT(VLOOKUP(ColumnMapping[[#This Row],[Old Table Name]],TableMapping[[#All],[Old Table Name]:[New Table Name]],2,),".",ColumnMapping[[#This Row],[Old Column Name]]))
A83: Codes | D83: CODE | E83: CREATED_BY_USER_UID | G83: =_xlfn.CONCAT(B83,".",C83) -> . | H83: =_xlfn.CONCAT(D83,".",E83) -> CODE.CREATED_BY_USER_UID | J83: =IF(ColumnMapping[[#This Row],[Add Old Column to New Table?]]<>"y","",_xlfn.CONCAT(VLOOKUP(ColumnMapping[[#This Row],[Old Table Name]],TableMapping[[#All],[Old Table Name]:[New Table Name]],2,),".",ColumnMapping[[#This Row],[Old Column Name]]))
A84: Codes | D84: CODE | E84: CREATED_DATE | G84: =_xlfn.CONCAT(B84,".",C84) -> . | H84: =_xlfn.CONCAT(D84,".",E84) -> CODE.CREATED_DATE | J84: =IF(ColumnMapping[[#This Row],[Add Old Column to New Table?]]<>"y","",_xlfn.CONCAT(VLOOKUP(ColumnMapping[[#This Row],[Old Table Name]],TableMapping[[#All],[Old Table Name]:[New Table Name]],2,),".",ColumnMapping[[#This Row],[Old Column Name]]))
A85: Codes | D85: CODE_THRESHOLD | E85: ROW_UID | F85: 1:1 Relationship with the CODE table. Uses UID of the CODE table record. | G85: =_xlfn.CONCAT(B85,".",C85) -> . | H85: =_xlfn.CONCAT(D85,".",E85) -> CODE_THRESHOLD.ROW_UID | J85: =IF(ColumnMapping[[#This Row],[Add Old Column to New Table?]]<>"y","",_xlfn.CONCAT(VLOOKUP(ColumnMapping[[#This Row],[Old Table Name]],TableMapping[[#All],[Old Table Name]:[New Table Name]],2,),".",ColumnMapping[[#This Row],[Old Column Name]]))
A86: Codes | D86: CODE_THRESHOLD | E86: SEQUENCE | G86: =_xlfn.CONCAT(B86,".",C86) -> . | H86: =_xlfn.CONCAT(D86,".",E86) -> CODE_THRESHOLD.SEQUENCE | J86: =IF(ColumnMapping[[#This Row],[Add Old Column to New Table?]]<>"y","",_xlfn.CONCAT(VLOOKUP(ColumnMapping[[#This Row],[Old Table Name]],TableMapping[[#All],[Old Table Name]:[New Table Name]],2,),".",ColumnMapping[[#This Row],[Old Column Name]]))
A87: Codes | D87: CODE_FILE | E87: ROW_UID | G87: =_xlfn.CONCAT(B87,".",C87) -> . | H87: =_xlfn.CONCAT(D87,".",E87) -> CODE_FILE.ROW_UID | J87: =IF(ColumnMapping[[#This Row],[Add Old Column to New Table?]]<>"y","",_xlfn.CONCAT(VLOOKUP(ColumnMapping[[#This Row],[Old Table Name]],TableMapping[[#All],[Old Table Name]:[New Table Name]],2,),".",ColumnMapping[[#This Row],[Old Column Name]]))
A88: Codes | D88: CODE_FILE | E88: DESCRIPTION | F88: From WST_DIR | G88: =_xlfn.CONCAT(B88,".",C88) -> . | H88: =_xlfn.CONCAT(D88,".",E88) -> CODE_FILE.DESCRIPTION | J88: =IF(ColumnMapping[[#This Row],[Add Old Column to New Table?]]<>"y","",_xlfn.CONCAT(VLOOKUP(ColumnMapping[[#This Row],[Old Table Name]],TableMapping[[#All],[Old Table Name]:[New Table Name]],2,),".",ColumnMapping[[#This Row],[Old Column Name]]))
A89: Codes | D89: CODE_FILE | E89: FIELD_NAME | G89: =_xlfn.CONCAT(B89,".",C89) -> . | H89: =_xlfn.CONCAT(D89,".",E89) -> CODE_FILE.FIELD_NAME | J89: =IF(ColumnMapping[[#This Row],[Add Old Column to New Table?]]<>"y","",_xlfn.CONCAT(VLOOKUP(ColumnMapping[[#This Row],[Old Table Name]],TableMapping[[#All],[Old Table Name]:[New Table Name]],2,),".",ColumnMapping[[#This Row],[Old Column Name]]))
A90: Codes | D90: CODE_FILE | E90: FIELD_DESCRIPTION | G90: =_xlfn.CONCAT(B90,".",C90) -> . | H90: =_xlfn.CONCAT(D90,".",E90) -> CODE_FILE.FIELD_DESCRIPTION | J90: =IF(ColumnMapping[[#This Row],[Add Old Column to New Table?]]<>"y","",_xlfn.CONCAT(VLOOKUP(ColumnMapping[[#This Row],[Old Table Name]],TableMapping[[#All],[Old Table Name]:[New Table Name]],2,),".",ColumnMapping[[#This Row],[Old Column Name]]))
A91: Codes | D91: CODE_FILE | E91: OWNER_USER_UID | F91: From WST_DIR | G91: =_xlfn.CONCAT(B91,".",C91) -> . | H91: =_xlfn.CONCAT(D91,".",E91) -> CODE_FILE.OWNER_USER_UID | J91: =IF(ColumnMapping[[#This Row],[Add Old Column to New Table?]]<>"y","",_xlfn.CONCAT(VLOOKUP(ColumnMapping[[#This Row],[Old Table Name]],TableMapping[[#All],[Old Table Name]:[New Table Name]],2,),".",ColumnMapping[[#This Row],[Old Column Name]]))
A92: Codes | D92: CODE_FILE | E92: CREATED_BY_USER_UID | G92: =_xlfn.CONCAT(B92,".",C92) -> . | H92: =_xlfn.CONCAT(D92,".",E92) -> CODE_FILE.CREATED_BY_USER_UID | J92: =IF(ColumnMapping[[#This Row],[Add Old Column to New Table?]]<>"y","",_xlfn.CONCAT(VLOOKUP(ColumnMapping[[#This Row],[Old Table Name]],TableMapping[[#All],[Old Table Name]:[New Table Name]],2,),".",ColumnMapping[[#This Row],[Old Column Name]]))
A93: Codes | D93: CODE_FILE | E93: CREATED_DATE | G93: =_xlfn.CONCAT(B93,".",C93) -> . | H93: =_xlfn.CONCAT(D93,".",E93) -> CODE_FILE.CREATED_DATE | J93: =IF(ColumnMapping[[#This Row],[Add Old Column to New Table?]]<>"y","",_xlfn.CONCAT(VLOOKUP(ColumnMapping[[#This Row],[Old Table Name]],TableMapping[[#All],[Old Table Name]:[New Table Name]],2,),".",ColumnMapping[[#This Row],[Old Column Name]]))
A94: FiscalCalendars | B94: FISCAL | C94: FISCFILE | D94: FISCAL_CALENDAR | E94: NAME | G94: =_xlfn.CONCAT(B94,".",C94) -> FISCAL.FISCFILE | H94: =_xlfn.CONCAT(D94,".",E94) -> FISCAL_CALENDAR.NAME | J94: =IF(ColumnMapping[[#This Row],[Add Old Column to New Table?]]<>"y","",_xlfn.CONCAT(VLOOKUP(ColumnMapping[[#This Row],[Old Table Name]],TableMapping[[#All],[Old Table Name]:[New Table Name]],2,),".",ColumnMapping[[#This Row],[Old Column Name]]))
A95: FiscalCalendars | B95: FISCAL | C95: PATTERN | D95: FISCAL_CALENDAR | E95: PATTERN | G95: =_xlfn.CONCAT(B95,".",C95) -> FISCAL.PATTERN | H95: =_xlfn.CONCAT(D95,".",E95) -> FISCAL_CALENDAR.PATTERN | J95: =IF(ColumnMapping[[#This Row],[Add Old Column to New Table?]]<>"y","",_xlfn.CONCAT(VLOOKUP(ColumnMapping[[#This Row],[Old Table Name]],TableMapping[[#All],[Old Table Name]:[New Table Name]],2,),".",ColumnMapping[[#This Row],[Old Column Name]]))
A96: FiscalCalendars | B96: FISCAL | C96: DOW_HOURS | F96: Separated into individual Hours fields for each day. | G96: =_xlfn.CONCAT(B96,".",C96) -> FISCAL.DOW_HOURS | H96: =_xlfn.CONCAT(D96,".",E96) -> . | J96: =IF(ColumnMapping[[#This Row],[Add Old Column to New Table?]]<>"y","",_xlfn.CONCAT(VLOOKUP(ColumnMapping[[#This Row],[Old Table Name]],TableMapping[[#All],[Old Table Name]:[New Table Name]],2,),".",ColumnMapping[[#This Row],[Old Column Name]]))
A97: FiscalCalendars | B97: FISCAL | C97: SEQUENCE | D97: FISCAL_CALENDAR | E97: SEQUENCE | G97: =_xlfn.CONCAT(B97,".",C97) -> FISCAL.SEQUENCE | H97: =_xlfn.CONCAT(D97,".",E97) -> FISCAL_CALENDAR.SEQUENCE | J97: =IF(ColumnMapping[[#This Row],[Add Old Column to New Table?]]<>"y","",_xlfn.CONCAT(VLOOKUP(ColumnMapping[[#This Row],[Old Table Name]],TableMapping[[#All],[Old Table Name]:[New Table Name]],2,),".",ColumnMapping[[#This Row],[Old Column Name]]))
A98: FiscalCalendars | B98: FISCAL | C98: LASTUPDATE | D98: FISCAL_CALENDAR | E98: LAST_MODIFIED_DATE | G98: =_xlfn.CONCAT(B98,".",C98) -> FISCAL.LASTUPDATE | H98: =_xlfn.CONCAT(D98,".",E98) -> FISCAL_CALENDAR.LAST_MODIFIED_DATE | J98: =IF(ColumnMapping[[#This Row],[Add Old Column to New Table?]]<>"y","",_xlfn.CONCAT(VLOOKUP(ColumnMapping[[#This Row],[Old Table Name]],TableMapping[[#All],[Old Table Name]:[New Table Name]],2,),".",ColumnMapping[[#This Row],[Old Column Name]]))
A99: FiscalCalendars | B99: FISCAL | C99: USR_ID | D99: FISCAL_CALENDAR | E99: LAST_MODIFIED_BY_USER_UID | G99: =_xlfn.CONCAT(B99,".",C99) -> FISCAL.USR_ID | H99: =_xlfn.CONCAT(D99,".",E99) -> FISCAL_CALENDAR.LAST_MODIFIED_BY_USER_UID | J99: =IF(ColumnMapping[[#This Row],[Add Old Column to New Table?]]<>"y","",_xlfn.CONCAT(VLOOKUP(ColumnMapping[[#This Row],[Old Table Name]],TableMapping[[#All],[Old Table Name]:[New Table Name]],2,),".",ColumnMapping[[#This Row],[Old Column Name]]))
A100: FiscalCalendars | B100: FISCAL | C100: DESC00 | D100: FISCAL_CALENDAR_SET | E100: DESCRIPTION | F100: Calendar Set Descriptions are now stored rotated. | G100: =_xlfn.CONCAT(B100,".",C100) -> FISCAL.DESC00 | H100: =_xlfn.CONCAT(D100,".",E100) -> FISCAL_CALENDAR_SET.DESCRIPTION | J100: =IF(ColumnMapping[[#This Row],[Add Old Column to New Table?]]<>"y","",_xlfn.CONCAT(VLOOKUP(ColumnMapping[[#This Row],[Old Table Name]],TableMapping[[#All],[Old Table Name]:[New Table Name]],2,),".",ColumnMapping[[#This Row],[Old Column Name]]))
A101: FiscalCalendars | B101: FISCAL | C101: DESC01 | D101: FISCAL_CALENDAR_SET | E101: DESCRIPTION | F101: Calendar Set Descriptions are now stored rotated. | G101: =_xlfn.CONCAT(B101,".",C101) -> FISCAL.DESC01 | H101: =_xlfn.CONCAT(D101,".",E101) -> FISCAL_CALENDAR_SET.DESCRIPTION | J101: =IF(ColumnMapping[[#This Row],[Add Old Column to New Table?]]<>"y","",_xlfn.CONCAT(VLOOKUP(ColumnMapping[[#This Row],[Old Table Name]],TableMapping[[#All],[Old Table Name]:[New Table Name]],2,),".",ColumnMapping[[#This Row],[Old Column Name]]))
A102: FiscalCalendars | B102: FISCAL | C102: DESC02 | D102: FISCAL_CALENDAR_SET | E102: DESCRIPTION | F102: Calendar Set Descriptions are now stored rotated. | G102: =_xlfn.CONCAT(B102,".",C102) -> FISCAL.DESC02 | H102: =_xlfn.CONCAT(D102,".",E102) -> FISCAL_CALENDAR_SET.DESCRIPTION | J102: =IF(ColumnMapping[[#This Row],[Add Old Column to New Table?]]<>"y","",_xlfn.CONCAT(VLOOKUP(ColumnMapping[[#This Row],[Old Table Name]],TableMapping[[#All],[Old Table Name]:[New Table Name]],2,),".",ColumnMapping[[#This Row],[Old Column Name]]))
A103: FiscalCalendars | B103: FISCAL | C103: DESC03 | D103: FISCAL_CALENDAR_SET | E103: DESCRIPTION | F103: Calendar Set Descriptions are now stored rotated. | G103: =_xlfn.CONCAT(B103,".",C103) -> FISCAL.DESC03 | H103: =_xlfn.CONCAT(D103,".",E103) -> FISCAL_CALENDAR_SET.DESCRIPTION | J103: =IF(ColumnMapping[[#This Row],[Add Old Column to New Table?]]<>"y","",_xlfn.CONCAT(VLOOKUP(ColumnMapping[[#This Row],[Old Table Name]],TableMapping[[#All],[Old Table Name]:[New Table Name]],2,),".",ColumnMapping[[#This Row],[Old Column Name]]))
A104: FiscalCalendars | B104: FISCAL | C104: DESC04 | D104: FISCAL_CALENDAR_SET | E104: DESCRIPTION | F104: Calendar Set Descriptions are now stored rotated. | G104: =_xlfn.CONCAT(B104,".",C104) -> FISCAL.DESC04 | H104: =_xlfn.CONCAT(D104,".",E104) -> FISCAL_CALENDAR_SET.DESCRIPTION | J104: =IF(ColumnMapping[[#This Row],[Add Old Column to New Table?]]<>"y","",_xlfn.CONCAT(VLOOKUP(ColumnMapping[[#This Row],[Old Table Name]],TableMapping[[#All],[Old Table Name]:[New Table Name]],2,),".",ColumnMapping[[#This Row],[Old Column Name]]))
A105: FiscalCalendars | B105: FISCAL | C105: DESC05 | D105: FISCAL_CALENDAR_SET | E105: DESCRIPTION | F105: Calendar Set Descriptions are now stored rotated. | G105: =_xlfn.CONCAT(B105,".",C105) -> FISCAL.DESC05 | H105: =_xlfn.CONCAT(D105,".",E105) -> FISCAL_CALENDAR_SET.DESCRIPTION | J105: =IF(ColumnMapping[[#This Row],[Add Old Column to New Table?]]<>"y","",_xlfn.CONCAT(VLOOKUP(ColumnMapping[[#This Row],[Old Table Name]],TableMapping[[#All],[Old Table Name]:[New Table Name]],2,),".",ColumnMapping[[#This Row],[Old Column Name]]))
A106: FiscalCalendars | B106: FISCAL | C106: DESC06 | D106: FISCAL_CALENDAR_SET | E106: DESCRIPTION | F106: Calendar Set Descriptions are now stored rotated. | G106: =_xlfn.CONCAT(B106,".",C106) -> FISCAL.DESC06 | H106: =_xlfn.CONCAT(D106,".",E106) -> FISCAL_CALENDAR_SET.DESCRIPTION | J106: =IF(ColumnMapping[[#This Row],[Add Old Column to New Table?]]<>"y","",_xlfn.CONCAT(VLOOKUP(ColumnMapping[[#This Row],[Old Table Name]],TableMapping[[#All],[Old Table Name]:[New Table Name]],2,),".",ColumnMapping[[#This Row],[Old Column Name]]))
A107: FiscalCalendars | B107: FISCAL | C107: DESC07 | D107: FISCAL_CALENDAR_SET | E107: DESCRIPTION | F107: Calendar Set Descriptions are now stored rotated. | G107: =_xlfn.CONCAT(B107,".",C107) -> FISCAL.DESC07 | H107: =_xlfn.CONCAT(D107,".",E107) -> FISCAL_CALENDAR_SET.DESCRIPTION | J107: =IF(ColumnMapping[[#This Row],[Add Old Column to New Table?]]<>"y","",_xlfn.CONCAT(VLOOKUP(ColumnMapping[[#This Row],[Old Table Name]],TableMapping[[#All],[Old Table Name]:[New Table Name]],2,),".",ColumnMapping[[#This Row],[Old Column Name]]))
